Workbook
Name X65X200: 'Ventas MELI'!$X$56
Name X65X200: 'Ventas Web'!#REF!
Name X65X200: 'Ventas pre diciembre'!$AC$65

Sheet Ventas pre diciembre
Y1: 0.15
A2: ESTADO | B2: Fecha | C2: Procedencia | D2: $ venta ML | E2: Nombre | G2: Telefono | H2: Producto | I2: Cantidad | J2: Venta | K2: FACTURÓ | L2: Cargo por venta | M2: Costo fijo | N2: "impuestos" | O2: Envio entró | P2: Envio salio | Q2: Envio quedó | R2: Costo | S2: Comision MP | T2: IIBB Tucuman | U2: Retencion SIRTAC | V2: IIBB CABA | W2: Ganancia | X2: MONOTRIBUTO | Y2: % a Brisa | AC2: Chocos Colonial Usados | AE2: NECESITO
B3: 45921 | C3: Mercado Libre | D3: 113000 | H3: Mini recuerdo | I3: 100 | J3: 77184 | W3: 45870 | Y3: =W3*$Y$1 -> 6880.5 | Z3: =SUM(Y3:Y9) -> 14292.9 | AR3: MELI | AS3: 0.01
B4: 25 | C4: IG | E4: Beatriz | H4: Choco Suelto | I4: 50 | J4: 23250 | W4: 7646 | Y4: =W4*$Y$1 -> 1146.9 | AR4: WEB | AS4: 0.1
B5: 45915 | C5: WPP | E5: Magali | H5: Cajita de 4 | I5: 15 | J5: 36112 | W5: 12225 | Y5: =W5*$Y$1 -> 1833.75 | AR5: IG | AS5: 0.1
B6: 45929 | C6: Pagina | E6: eugenia | H6: Cajita de 6 | I6: 20 | J6: 63745 | W6: =J6-(2310*20) -> 17545 | Y6: =W6*$Y$1 -> 2631.75 | AR6: OTRO | AS6: 0.05
B7: 45926 | C7: Mercado Libre | D7: 50500 | E7: Silvina edith espindola | H7: Cajita de 4 | I7: 15 | J7: 36746 | W7: 12000 | Y7: =W7*$Y$1 -> 1800
C8: Octubre
B9: 45931 | C9: WPP | E9: Valeria Limonoff | H9: Cajita de 4 | I9: 100 | J9: 216675 | W9: 66294 | AR9: FACTURADO | AS9: =SUM(J9:J26) -> 1936729.9 | AU9: =AS10*0.05 -> 34975.231
B10: 45931 | C10: otro | E10: Stefano | G10: 3416742265 | H10: Mini recuerdo | I10: 200 | J10: 145350 | W10: 69645 | Y10: =W10*$Y$8 -> 0 | Z10: =SUM(Y10:Y120) -> #REF! | AJ10: Choco Suelto | AK10: 294 | AR10: GANANCIA | AS10: =SUM(W9:W26)-W24 -> 699504.62
B11: 45933 | C11: otro | E11: Geraldine desconfiada | G11: 1123192733 | H11: Cajita de 4 | I11: 85 | J11: 203490 | W11: =J11-(1570.84*85) -> 69968.6 | Y11: =W11*$Y$8 -> 0 | AJ11: Mini Recuerdo | AK11: 327 | AU11: =AS9-AS10 -> 1237225.3
B12: 45933 | C12: Meli | E12: Monica | H12: Mini recuerdo/separadores | I12: 80 | J12: 64960 | W12: 32560 | Y12: =W12*$Y$8 -> 0 | AJ12: Tarjeta | AK12: 330
B13: 45936 | C13: Meli | D13: 113000 | E13: Nadia Staiano | H13: Mini recuerdo | I13: 100 | J13: 76950 | W13: 36600 | Y13: {=W13 * _xlfn.XLOOKUP(C13, {"MELI";"WEB";"IG";"OTRO"}, $AS$3:$AS$6)} -> 366 | AJ13: Cajita de 4 | AK13: 1443.5
B14: 45936 | C14: Meli | D14: 32000 | E14: Julia Sansone | H14: Cajita de 4 | I14: 10 | J14: 24000 | W14: 8150 | Y14: {=W14 * _xlfn.XLOOKUP(C14, {"MELI";"WEB";"IG";"OTRO"}, $AS$3:$AS$6)} -> 81.5 | AJ14: Cajita de 4 deluxe | AK14: 1499.86
B15: 45940 | C15: otro | E15: Geraldine desconfiada | G15: 1123192733 | H15: Stickers | I15: 85 | J15: 24000 | W15: =J15-(2079+3036) -> 18885 | Y15: {=W15 * _xlfn.XLOOKUP(C15, {"MELI";"WEB";"IG";"OTRO"}, $AS$3:$AS$6)} -> 944.25 | AJ15: D6 Classic | AK15: 2263.63
B16: 45944 | C16: Ig | E16: Brava | G16: 11 2472-6058 | H16: Chocos Sueltos | I16: 50 | J16: 22500 | W16: 7773 | Y16: {=W16 * _xlfn.XLOOKUP(C16, {"MELI";"WEB";"IG";"OTRO"}, $AS$3:$AS$6)} -> 777.3 | AJ16: D6 Deluxe | AK16: 2422
B17: 45944 | C17: IG | E17: Claudia Galeano | G17: 11 5629-1780 | H17: Mini Recuerdo | I17: 130 | J17: 111150 | W17: 65970 | Y17: {=W17 * _xlfn.XLOOKUP(C17, {"MELI";"WEB";"IG";"OTRO"}, $AS$3:$AS$6)} -> 6597 | AJ17: D6 Gold | AK17: 2384.8
C18: ig | E18: Cris | G18: 2235 22-6326 | H18: Caja 22 chocos | I18: 1 | J18: 13000 | W18: 5871 | Y18: {=W18 * _xlfn.XLOOKUP(C18, {"MELI";"WEB";"IG";"OTRO"}, $AS$3:$AS$6)} -> 587.1 | AJ18: Black | AK18: 2610
C19: ig | E19: =E18 -> Cris | G19: =G18 -> 2235 22-6326 | H19: Choco Cintas | I19: 30 | J19: 33000 | R19: 19710 | W19: =J19-R19 -> 13290 | Y19: {=W19 * _xlfn.XLOOKUP(C19, {"MELI";"WEB";"IG";"OTRO"}, $AS$3:$AS$6)} -> 1329 | AJ19: Señaladores | AK19: 440.7
C20: Meli | E20: Nadia Staiano | H20: Mini Recuerdo | I20: 100 | J20: 93196 | R20: 34754 | W20: =(J20-R20)-9500 -> 48942 | Y20: {=W20 * _xlfn.XLOOKUP(C20, {"MELI";"WEB";"IG";"OTRO"}, $AS$3:$AS$6)} -> 489.42 | AJ20: D2 | AK20: 1293
C21: Meli | E21: Alejandra Beatríz Vecci de Massolo | H21: Petit Box | I21: 10 | J21: 23385.47 | R21: 14190 | W21: =J21-R21 -> 9195.47 | Y21: {=W21 * _xlfn.XLOOKUP(C21, {"MELI";"WEB";"IG";"OTRO"}, $AS$3:$AS$6)} -> 91.9547 | AJ21: D2 moño | AK21: 1367
C22: Meli | E22: GEORGINA VANESA PORTUGAL | H22: Petit Box | I22: 10 | J22: =J21 -> 23385.47 | R22: =R21 -> 14190 | W22: =J22-R22 -> 9195.47 | Y22: {=W22 * _xlfn.XLOOKUP(C22, {"MELI";"WEB";"IG";"OTRO"}, $AS$3:$AS$6)} -> 91.9547 | AJ22: Vela 100cc
C23: meli | E23: Caja Forense de la pampa | G23: 2215 37-4454 | H23: Cajita Gold | I23: 65 | J23: 257985 | R23: =141765+5159+154.79 -> 147078.79 | T23: 154.79 | U23: 5159.7 | W23: =J23-R23 -> 110906.21 | Y23: {=W23 * _xlfn.XLOOKUP(C23, {"MELI";"WEB";"IG";"OTRO"}, $AS$3:$AS$6)} -> 1109.0621 | AJ23: Vela 200cc
C24: meli | E24: =E23 -> Caja Forense de la pampa | G24: =G23 -> 2215 37-4454 | H24: =H23 -> Cajita Gold | I24: =I23 -> 65 | J24: =J23 -> 257985 | R24: =R23 -> 147078.79 | T24: 309.58 | U24: 5159.7 | W24: =J24-R24 -> 110906.21 | Y24: {=W24 * _xlfn.XLOOKUP(C24, {"MELI";"WEB";"IG";"OTRO"}, $AS$3:$AS$6)} -> 1109.0621 | AJ24: caja 44 chocos | AK24: 12512
C25: web | E25: Carla | H25: Caja Deluxe | I25: 50 | J25: 247500 | R25: =123100 -> 123100 | S25: 18834.75 | T25: 61.88 | U25: 7425 | V25: 11137.5 | W25: =J25-R25-S25-T25-U25-V25 -> 86940.87 | X25: =W25*0.05 -> 4347.0435 | Y25: {=W25 * _xlfn.XLOOKUP(C25, {"MELI";"WEB";"IG";"OTRO"}, $AS$3:$AS$6)} -> 8694.087 | AC25: =I25*6 -> 300
C26: MELI | E26: Paula Bianchi | H26: Chocos Sueltos | I26: 200 | J26: 98218 | R26: 58900 | W26: =J26-R26 -> 39318 | X26: =W26*0.05 -> 1965.9 | Y26: {=W26 * _xlfn.XLOOKUP(C26, {"MELI";"WEB";"IG";"OTRO"}, $AS$3:$AS$6)} -> 393.18
C27: MELI | E27: Alejandra Leandro | H27: Mini recuerdo | I27: 100 | J27: 83841 | R27: 34754 | W27: =J27-R27 -> 49087 | X27: =W27*0.05 -> 2454.35 | Y27: {=W27 * _xlfn.XLOOKUP(C27, {"MELI";"WEB";"IG";"OTRO"}, $AS$3:$AS$6)} -> 490.87
B28: 45687 | C28: MELI | E28: Maria Marta derderian | H28: Choco Suelto | I28: 25 | J28: 14458.37 | K28: 20100 | O28: 7370.99 | R28: 7377.75 | W28: =J28-R28 -> 7080.62 | Y28: {=W28 * _xlfn.XLOOKUP(C28, {"MELI";"WEB";"IG";"OTRO"}, $AS$3:$AS$6)} -> 70.8062
B29: 45961 | C29: MELI | E29: Marisa Borello | H29: Cajas 6 choco | I29: 16 | J29: 76614.1 | K29: 92000 | R29: 37023.52 | W29: =J29-R29 -> 39590.58 | Y29: {=W29 * _xlfn.XLOOKUP(C29, {"MELI";"WEB";"IG";"OTRO"}, $AS$3:$AS$6)} -> 395.9058
C30: MELI | E30: Marisa Borello | H30: Cajas 6 choco | I30: 5 | J30: 24000 | R30: 11569.85 | T30: 14.4 | U30: 480 | W30: =J30-SUM(R30:V30) -> 11935.75 | Y30: {=W30 * _xlfn.XLOOKUP(C30, {"MELI";"WEB";"IG";"OTRO"}, $AS$3:$AS$6)} -> 119.3575
D31: Noviembre | Y31: BRISA | Z31: =SUM(Y76:Y200)-4000 -> #REF! | AC31: =SUM(AC32:AC188) -> #REF! | AD31: =AC31/50 -> #REF! | AF31: =SUM(W32:W53) -> 481858.12
B32: 45964 | C32: IG | D32: Completado | E32: Antonella Tunut | G32: 93586016473 | H32: Choco Suelto | I32: 100 | J32: =K32-T32-U32 -> 67335.57 | K32: 68794 | R32: 29500 | T32: 82.55 | U32: 1375.88 | W32: =J32-SUM(R32:V32) -> 36377.14 | X32: =W32*0.05 -> 1818.857 | Y32: {=W32 * _xlfn.XLOOKUP(C32, {"MELI";"WEB";"IG";"OTRO"}, $AS$3:$AS$6)} -> 3637.714 | AA32: Completado
B33: 45932 | C33: MELI | D33: Completado | E33: The park | H33: D6 Gold | I33: 8 | J33: 35286.6 | K33: 53600 | R33: 18511 | W33: =J33-SUM(R33:V33) -> 16775.6 | X33: =W33*0.05 -> 838.78 | Y33: {=W33 * _xlfn.XLOOKUP(C33, {"MELI";"WEB";"IG";"OTRO"}, $AS$3:$AS$6)} -> 167.756 | AA33: Completado
B34: 45964 | C34: MELI | D34: Completado | E34: Romina Rojas | H34: D6 Gold | I34: 25 | J34: 115465 | K34: 140000 | R34: 57849.25 | W34: =J34-SUM(R34:V34) -> 57615.75 | X34: =W34*0.05 -> 2880.7875 | Y34: {=W34 * _xlfn.XLOOKUP(C34, {"MELI";"WEB";"IG";"OTRO"}, $AS$3:$AS$6)} -> 576.1575 | AA34: Completado
B35: 45964 | C35: MELI | D35: Completado | E35: Paula Bianchi | F35: fusion | H35: Choco Suelto | I35: 200 | J35: 113893.26 | K35: 145000 | R35: 59022 | W35: =J35-SUM(R35:V35) -> 54871.26 | X35: =W35*0.05 -> 2743.563 | Y35: {=W35 * _xlfn.XLOOKUP(C35, {"MELI";"WEB";"IG";"OTRO"}, $AS$3:$AS$6)} -> 548.7126 | AA35: Completado
B36: 45964 | C36: OTRO | D36: Completado | E36: Jennifer Ayala | F36: 15 cenicienta | G36: +54 9 11 4494-4551 | H36: D6 Gold | I36: 25 | J36: =K36-T36-U36-O36 -> 107479.32 | K36: 118900 | O36: 8900 | R36: 57849.25 | T36: 142.68 | U36: 2378 | W36: =J36-R36 -> 49630.07 | X36: =W36*0.05 -> 2481.5035 | Y36: {=W36 * _xlfn.XLOOKUP(C36, {"MELI";"WEB";"IG";"OTRO"}, $AS$3:$AS$6)} -> 2481.5035 | AA36: Falta
B37: 45966 | C37: WEB | D37: Completado | E37: Federico Cunioli | F37: Anuncio nacimiento | G37: +54 9 11 5176-0510 | H37: D6 Gold | I37: 10 | J37: =K37-O37-T37-U37 -> 42953.08 | K37: 54100 | O37: 10000 | R37: 23139.7 | T37: 64.92 | U37: 1082 | W37: =J37-SUM(R37:V37) -> 18666.46 | X37: =W37*0.05 -> 933.323 | Y37: {=W37 * _xlfn.XLOOKUP(C37, {"MELI";"WEB";"IG";"OTRO"}, $AS$3:$AS$6)} -> 1866.646 | AA37: Completado
C38: OTRO | D38: Completado | E38: Transf envio correo | G38: antonella tunut | K38: 1600 | W38: =J38-R38 -> 0 | X38: =W38*0.05 -> 0 | Y38: {=W38 * _xlfn.XLOOKUP(C38, {"MELI";"WEB";"IG";"OTRO"}, $AS$3:$AS$6)} -> 0 | AC38: =IF(OR(H38="D6 Classic",H38="D6 Deluxe",H38="D6 Gold"),6*I38, IF(OR(H38="D2",H38="D2 moño"),2*I38, IF(H38="Cajita de 4",4*I38, IF(OR(H38="Mini Recuerdo",H38="Choco Cintas",H38="Choco Suelto"),1*I38, IF(H38="Caja 22 Chocos",22*I38, IF(H38="Caja 44 Chocos",44*I38,""))))))
B39: 45968 | C39: WEB | D39: Completado | E39: Mariana Seren | F39: La de 90 años | G39: 11 5484-5699 | H39: D2 moño | I39: 50 | J39: =K39-R39-T39-U39-8000 -> 81711.87 | K39: 165242 | R39: 72027 | T39: 198.29 | U39: 3304.84 | W39: =J39-SUM(R39:V39) -> 6181.74 | X39: =W39*0.05 -> 309.087 | Y39: {=W39 * _xlfn.XLOOKUP(C39, {"MELI";"WEB";"IG";"OTRO"}, $AS$3:$AS$6)} -> 618.174 | AC39: =IF(OR(H39="D6 Classic",H39="D6 Deluxe",H39="D6 Gold"),6*I39, IF(OR(H39="D2",H39="D2 moño"),2*I39, IF(H39="Cajita de 4",4*I39, IF(OR(H39="Mini Recuerdo",H39="Choco Cintas",H39="Choco Suelto"),1*I39, IF(H39="Caja 22 Chocos",22*I39, IF(H39="Caja 44 Chocos",44*I39,"")))))) -> 100
B40: 45968 | C40: MELI | D40: Completado | E40: Alejandra Patricia | G40: 11 5122-2668 | H40: Mini Recuerdo | I40: 50 | J40: =K40-O40 -> 45742 | K40: 54584 | O40: 8842 | R40: =17377+R41 -> 22385.86 | T40: 65.5 | U40: 1091.68 | W40: =J40-SUM(R40:V40) -> 22198.96 | X40: =W40*0.05 -> 1109.948 | Y40: {=W40 * _xlfn.XLOOKUP(C40, {"MELI";"WEB";"IG";"OTRO"}, $AS$3:$AS$6)} -> 221.9896 | AC40: =IF(OR(H40="D6 Classic",H40="D6 Deluxe",H40="D6 Gold"),6*I40, IF(OR(H40="D2",H40="D2 moño"),2*I40, IF(H40="Cajita de 4",4*I40, IF(OR(H40="Mini Recuerdo",H40="Choco Cintas",H40="Choco Suelto"),1*I40, IF(H40="Caja 22 Chocos",22*I40, IF(H40="Caja 44 Chocos",44*I40,"")))))) -> 50
C41: MELI | D41: Completado | E41: Alejandra Patricia | G41: 11 5122-2668 | H41: Cajita de 4 | I41: 2 | R41: 5008.86 | Y41: {=W41 * _xlfn.XLOOKUP(C41, {"MELI";"WEB";"IG";"OTRO"}, $AS$3:$AS$6)} -> 0 | AC41: =IF(OR(H41="D6 Classic",H41="D6 Deluxe",H41="D6 Gold"),6*I41, IF(OR(H41="D2",H41="D2 moño"),2*I41, IF(H41="Cajita de 4",4*I41, IF(OR(H41="Mini Recuerdo",H41="Choco Cintas",H41="Choco Suelto"),1*I41, IF(H41="Caja 22 Chocos",22*I41, IF(H41="Caja 44 Chocos",44*I41,"")))))) -> 8
C42: MELI | D42: Completado | E42: Mariana Moline | H42: Cajita de 4 | I42: 20 | J42: 49790.66 | K42: 81400 | R42: 28390 | W42: =J42-SUM(R42:V42) -> 21400.66 | X42: =W42*0.05 -> 1070.033 | Y42: {=W42 * _xlfn.XLOOKUP(C42, {"MELI";"WEB";"IG";"OTRO"}, $AS$3:$AS$6)} -> 214.0066 | AC42: =IF(OR(H42="D6 Classic",H42="D6 Deluxe",H42="D6 Gold"),6*I42, IF(OR(H42="D2",H42="D2 moño"),2*I42, IF(H42="Cajita de 4",4*I42, IF(OR(H42="Mini Recuerdo",H42="Choco Cintas",H42="Choco Suelto"),1*I42, IF(H42="Caja 22 Chocos",22*I42, IF(H42="Caja 44 Chocos",44*I42,"")))))) -> 80
C43: MELI | D43: Completado | E43: the park | H43: D6 Gold | I43: 10 | J43: 44108.25 | K43: 67000 | R43: 26159.8 | W43: =J43-SUM(R43:V43) -> 17948.45 | X43: =W43*0.05 -> 897.4225 | Y43: {=W43 * _xlfn.XLOOKUP(C43, {"MELI";"WEB";"IG";"OTRO"}, $AS$3:$AS$6)} -> 179.4845 | AC43: =IF(OR(H43="D6 Classic",H43="D6 Deluxe",H43="D6 Gold"),6*I43, IF(OR(H43="D2",H43="D2 moño"),2*I43, IF(H43="Cajita de 4",4*I43, IF(OR(H43="Mini Recuerdo",H43="Choco Cintas",H43="Choco Suelto"),1*I43, IF(H43="Caja 22 Chocos",22*I43, IF(H43="Caja 44 Chocos",44*I43,"")))))) -> 60
C44: MELI | D44: Completado | E44: María paula gomez | H44: Velas | I44: 5 | W44: =J44-SUM(R44:V44) -> 0 | X44: =W44*0.05 -> 0 | Y44: {=W44 * _xlfn.XLOOKUP(C44, {"MELI";"WEB";"IG";"OTRO"}, $AS$3:$AS$6)} -> 0 | AC44: =IF(OR(H44="D6 Classic",H44="D6 Deluxe",H44="D6 Gold"),6*I44, IF(OR(H44="D2",H44="D2 moño"),2*I44, IF(H44="Cajita de 4",4*I44, IF(OR(H44="Mini Recuerdo",H44="Choco Cintas",H44="Choco Suelto"),1*I44, IF(H44="Caja 22 Chocos",22*I44, IF(H44="Caja 44 Chocos",44*I44,""))))))
C45: MELI | D45: Completado | E45: =E44 -> María paula gomez | H45: Cajita de 4 | I45: 10 | W45: =J45-SUM(R45:V45) -> 0 | X45: =W45*0.05 -> 0 | Y45: {=W45 * _xlfn.XLOOKUP(C45, {"MELI";"WEB";"IG";"OTRO"}, $AS$3:$AS$6)} -> 0 | Z45: =SUM(K32:K78) -> 2606683.5 | AC45: =IF(OR(H45="D6 Classic",H45="D6 Deluxe",H45="D6 Gold"),6*I45, IF(OR(H45="D2",H45="D2 moño"),2*I45, IF(H45="Cajita de 4",4*I45, IF(OR(H45="Mini Recuerdo",H45="Choco Cintas",H45="Choco Suelto"),1*I45, IF(H45="Caja 22 Chocos",22*I45, IF(H45="Caja 44 Chocos",44*I45,"")))))) -> 40
C46: MELI | D46: Completado | E46: María del carmen | H46: Choco Suelto | I46: 100 | J46: 58865 | K46: 79000 | R46: 30100 | W46: =J46-SUM(R46:V46) -> 28765 | X46: =W46*0.05 -> 1438.25 | Y46: {=W46 * _xlfn.XLOOKUP(C46, {"MELI";"WEB";"IG";"OTRO"}, $AS$3:$AS$6)} -> 287.65 | AC46: =IF(OR(H46="D6 Classic",H46="D6 Deluxe",H46="D6 Gold"),6*I46, IF(OR(H46="D2",H46="D2 moño"),2*I46, IF(H46="Cajita de 4",4*I46, IF(OR(H46="Mini Recuerdo",H46="Choco Cintas",H46="Choco Suelto"),1*I46, IF(H46="Caja 22 Chocos",22*I46, IF(H46="Caja 44 Chocos",44*I46,"")))))) -> 100
C47: OTRO | D47: Completado | E47: Dra Lezcano | H47: Choco Suelto | I47: 100 | J47: 59400 | K47: 59400 | R47: 30100 | T47: 71.28 | W47: =J47-SUM(R47:V47) -> 29228.72 | X47: =W47*0.05 -> 1461.436 | AC47: =IF(OR(H47="D6 Classic",H47="D6 Deluxe",H47="D6 Gold"),6*I47, IF(OR(H47="D2",H47="D2 moño"),2*I47, IF(H47="Cajita de 4",4*I47, IF(OR(H47="Mini Recuerdo",H47="Choco Cintas",H47="Choco Suelto"),1*I47, IF(H47="Caja 22 Chocos",22*I47, IF(H47="Caja 44 Chocos",44*I47,"")))))) -> 100
B48: 45972 | C48: MELI | D48: Completado | E48: Bilbao Mabel Susana | H48: Mini Recuerdo | I48: 100 | J48: 85490.75 | K48: 115000 | R48: 61397 | X48: =W48*0.05 -> 0 | Y48: {=W48 * _xlfn.XLOOKUP(C48, {"MELI";"WEB";"IG";"OTRO"}, $AS$3:$AS$6)} -> 0 | AC48: =IF(OR(H48="D6 Classic",H48="D6 Deluxe",H48="D6 Gold"),6*I48, IF(OR(H48="D2",H48="D2 moño"),2*I48, IF(H48="Cajita de 4",4*I48, IF(OR(H48="Mini Recuerdo",H48="Choco Cintas",H48="Choco Suelto"),1*I48, IF(H48="Caja 22 Chocos",22*I48, IF(H48="Caja 44 Chocos",44*I48,"")))))) -> 100
B49: 45975 | C49: MELI | D49: Completado | E49: Bilbao Mabel Susana | H49: Mini Recuerdo | I49: 50 | J49: 42099.76 | K49: 59000 | R49: 30698.5 | W49: =J48-SUM(R49:V49) -> 54792.25 | X49: =W49*0.05 -> 2739.6125 | Y49: {=W49 * _xlfn.XLOOKUP(C49, {"MELI";"WEB";"IG";"OTRO"}, $AS$3:$AS$6)} -> 547.9225 | AC49: =IF(OR(H49="D6 Classic",H49="D6 Deluxe",H49="D6 Gold"),6*I49, IF(OR(H49="D2",H49="D2 moño"),2*I49, IF(H49="Cajita de 4",4*I49, IF(OR(H49="Mini Recuerdo",H49="Choco Cintas",H49="Choco Suelto"),1*I49, IF(H49="Caja 22 Chocos",22*I49, IF(H49="Caja 44 Chocos",44*I49,"")))))) -> 50
C50: OTRO | D50: Completado | E50: Maria Soledad Gomez | H50: Choco Suelto | I50: 50 | J50: 40000 | R50: 15050 | T50: 48 | U50: 800 | W50: =J50-SUM(R50:V50) -> 24102 | X50: =W50*0.05 -> 1205.1 | Y50: {=W50 * _xlfn.XLOOKUP(C50, {"MELI";"WEB";"IG";"OTRO"}, $AS$3:$AS$6)} -> 1205.1 | AC50: =IF(OR(H50="D6 Classic",H50="D6 Deluxe",H50="D6 Gold"),6*I50, IF(OR(H50="D2",H50="D2 moño"),2*I50, IF(H50="Cajita de 4",4*I50, IF(OR(H50="Mini Recuerdo",H50="Choco Cintas",H50="Choco Suelto"),1*I50, IF(H50="Caja 22 Chocos",22*I50, IF(H50="Caja 44 Chocos",44*I50,"")))))) -> 50
C51: OTRO | D51: Completado | E51: Sabrina Gomez | H51: Mini Recuerdo | I51: 50 | J51: 46500 | R51: 30699 | T51: 55.8 | U51: 930 | W51: =J51-SUM(R51:V51) -> 14815.2 | X51: =W51*0.05 -> 740.76 | Y51: {=W51 * _xlfn.XLOOKUP(C51, {"MELI";"WEB";"IG";"OTRO"}, $AS$3:$AS$6)} -> 740.76 | AC51: =IF(OR(H51="D6 Classic",H51="D6 Deluxe",H51="D6 Gold"),6*I51, IF(OR(H51="D2",H51="D2 moño"),2*I51, IF(H51="Cajita de 4",4*I51, IF(OR(H51="Mini Recuerdo",H51="Choco Cintas",H51="Choco Suelto"),1*I51, IF(H51="Caja 22 Chocos",22*I51, IF(H51="Caja 44 Chocos",44*I51,"")))))) -> 50
C52: OTRO | D52: Completado | E52: Lorena Flavia Kannan | J52: 10800 | K52: 10800 | T52: 12.96 | U52: 216 | W52: =J52-SUM(R52:V52) -> 10571.04 | X52: =W52*0.05 -> 528.552 | Y52: {=W52 * _xlfn.XLOOKUP(C52, {"MELI";"WEB";"IG";"OTRO"}, $AS$3:$AS$6)} -> 528.552 | AC52: =IF(OR(H52="D6 Classic",H52="D6 Deluxe",H52="D6 Gold"),6*I52, IF(OR(H52="D2",H52="D2 moño"),2*I52, IF(H52="Cajita de 4",4*I52, IF(OR(H52="Mini Recuerdo",H52="Choco Cintas",H52="Choco Suelto"),1*I52, IF(H52="Caja 22 Chocos",22*I52, IF(H52="Caja 44 Chocos",44*I52,""))))))
B53: 45975 | C53: WEB | D53: Completado | E53: Alicia Beatriz | F53: Mateo bautismo (D11) | G53: 11 6927-6234 | H53: D2 | I53: 12 | J53: 38955.09 | K53: 43591 | O53: 9391 | R53: 16401.36 | S53: 3317.28 | T53: 10.9 | U53: 1307.73 | W53: =J53-SUM(R53:V53) -> 17917.82 | X53: =W53*0.05 -> 895.891 | Y53: {=W53 * _xlfn.XLOOKUP(C53, {"MELI";"WEB";"IG";"OTRO"}, $AS$3:$AS$6)} -> 1791.782 | AC53: =IF(OR(H53="D6 Classic",H53="D6 Deluxe",H53="D6 Gold"),6*I53, IF(OR(H53="D2",H53="D2 moño"),2*I53, IF(H53="Cajita de 4",4*I53, IF(OR(H53="Mini Recuerdo",H53="Choco Cintas",H53="Choco Suelto"),1*I53, IF(H53="Caja 22 Chocos",22*I53, IF(H53="Caja 44 Chocos",44*I53,"")))))) -> 24
B54: 45668 | C54: MELI | D54: Completado | E54: Marianela Pettineroli | F54: Egresado | H54: D6 Gold | I54: 2 | J54: 8821.65 | K54: 13400 | R54: 4859.96 | W54: =J54-R54 -> 3961.69 | X54: =W54*0.05 -> 198.0845 | Y54: {=W54 * _xlfn.XLOOKUP(C54, {"MELI";"WEB";"IG";"OTRO"}, $AS$3:$AS$6)} -> 39.6169 | AC54: =IF(OR(H54="D6 Classic",H54="D6 Deluxe",H54="D6 Gold"),6*I54, IF(OR(H54="D2",H54="D2 moño"),2*I54, IF(H54="Cajita de 4",4*I54, IF(OR(H54="Mini Recuerdo",H54="Choco Cintas",H54="Choco Suelto"),1*I54, IF(H54="Caja 22 Chocos",22*I54, IF(H54="Caja 44 Chocos",44*I54,"")))))) -> 12
B55: 45975 | C55: MELI | D55: Completado | E55: Ana Silvia Fernande | F55: Fotos viajes | H55: Choco Suelto | I55: 25 | J55: 14458.37 | K55: 20100 | R55: 7527.75 | W55: =J55-R55 -> 6930.62 | X55: =W55*0.05 -> 346.531 | Y55: {=W55 * _xlfn.XLOOKUP(C55, {"MELI";"WEB";"IG";"OTRO"}, $AS$3:$AS$6)} -> 69.3062 | AC55: =IF(OR(H55="D6 Classic",H55="D6 Deluxe",H55="D6 Gold"),6*I55, IF(OR(H55="D2",H55="D2 moño"),2*I55, IF(H55="Cajita de 4",4*I55, IF(OR(H55="Mini Recuerdo",H55="Choco Cintas",H55="Choco Suelto"),1*I55, IF(H55="Caja 22 Chocos",22*I55, IF(H55="Caja 44 Chocos",44*I55,"")))))) -> 25
B56: 45973 | C56: WEB | D56: Completado | E56: Silvi | F56: Tobias | G56: 1 3338-1163 | H56: D6 Deluxe | I56: 20 | J56: =K56-T56 -> 87202.565 | K56: 88920 | R56: 49792.6 | T56: 1717.435 | W56: =J56-R56 -> 37409.965 | X56: =W56*0.05 -> 1870.4983 | Y56: {=W56 * _xlfn.XLOOKUP(C56, {"MELI";"WEB";"IG";"OTRO"}, $AS$3:$AS$6)} -> 3740.9965 | AC56: =IF(OR(H56="D6 Classic",H56="D6 Deluxe",H56="D6 Gold"),6*I56, IF(OR(H56="D2",H56="D2 moño"),2*I56, IF(H56="Cajita de 4",4*I56, IF(OR(H56="Mini Recuerdo",H56="Choco Cintas",H56="Choco Suelto"),1*I56, IF(H56="Caja 22 Chocos",22*I56, IF(H56="Caja 44 Chocos",44*I56,"")))))) -> 120
B57: 45973 | C57: WEB | D57: Completado | E57: Silvi | F57: Tobias | G57: 1 3338-1163 | H57: D2 | I57: 30 | J57: =K57-T57 -> 71385.065 | K57: 73102.5 | R57: 41003.4 | T57: 1717.435 | W57: =J57-R57 -> 30381.665 | X57: =W57*0.05 -> 1519.0833 | Y57: {=W57 * _xlfn.XLOOKUP(C57, {"MELI";"WEB";"IG";"OTRO"}, $AS$3:$AS$6)} -> 3038.1665 | AC57: =IF(OR(H57="D6 Classic",H57="D6 Deluxe",H57="D6 Gold"),6*I57, IF(OR(H57="D2",H57="D2 moño"),2*I57, IF(H57="Cajita de 4",4*I57, IF(OR(H57="Mini Recuerdo",H57="Choco Cintas",H57="Choco Suelto"),1*I57, IF(H57="Caja 22 Chocos",22*I57, IF(H57="Caja 44 Chocos",44*I57,"")))))) -> 60
C58: MELI | D58: Completado | E58: Nadia Vera | H58: Choco Suelto | I58: 25 | J58: 14233 | K58: 20100 | R58: 7527.75 | W58: =J58-R58 -> 6705.25 | X58: =W58*0.05 -> 335.2625 | Y58: {=W58 * _xlfn.XLOOKUP(C58, {"MELI";"WEB";"IG";"OTRO"}, $AS$3:$AS$6)} -> 67.0525 | AC58: =IF(OR(H58="D6 Classic",H58="D6 Deluxe",H58="D6 Gold"),6*I58, IF(OR(H58="D2",H58="D2 moño"),2*I58, IF(H58="Cajita de 4",4*I58, IF(OR(H58="Mini Recuerdo",H58="Choco Cintas",H58="Choco Suelto"),1*I58, IF(H58="Caja 22 Chocos",22*I58, IF(H58="Caja 44 Chocos",44*I58,"")))))) -> 25
C59: MELI | D59: Completado | E59: Ariela Fefer | H59: Choco Suelto | I59: 100 | J59: 65204.5 | K59: 80400 | R59: 30111 | W59: =J59-R59 -> 35093.5 | X59: =W59*0.05 -> 1754.675 | Y59: {=W59 * _xlfn.XLOOKUP(C59, {"MELI";"WEB";"IG";"OTRO"}, $AS$3:$AS$6)} -> 350.935 | AC59: =IF(OR(H59="D6 Classic",H59="D6 Deluxe",H59="D6 Gold"),6*I59, IF(OR(H59="D2",H59="D2 moño"),2*I59, IF(H59="Cajita de 4",4*I59, IF(OR(H59="Mini Recuerdo",H59="Choco Cintas",H59="Choco Suelto"),1*I59, IF(H59="Caja 22 Chocos",22*I59, IF(H59="Caja 44 Chocos",44*I59,"")))))) -> 100
C60: MELI | D60: Completado | E60: Jessica Maria Celeste Villegas | H60: Mini Recuerdo | I60: 50 | J60: 42001 | K60: 59000 | R60: 30699 | W60: =J60-R6 -> 42001 | X60: =W60*0.05 -> 2100.05 | Y60: {=W60 * _xlfn.XLOOKUP(C60, {"MELI";"WEB";"IG";"OTRO"}, $AS$3:$AS$6)} -> 420.01 | AC60: =IF(OR(H60="D6 Classic",H60="D6 Deluxe",H60="D6 Gold"),6*I60, IF(OR(H60="D2",H60="D2 moño"),2*I60, IF(H60="Cajita de 4",4*I60, IF(OR(H60="Mini Recuerdo",H60="Choco Cintas",H60="Choco Suelto"),1*I60, IF(H60="Caja 22 Chocos",22*I60, IF(H60="Caja 44 Chocos",44*I60,"")))))) -> 50
C61: MELI | D61: Completado | E61: Jessica Maria Celeste Villegas | H61: Mini Recuerdo | I61: 25 | J61: 22969.7 | K61: 36000 | R61: 15349.5 | W61: =J61-R61 -> 7620.2 | X61: =W61*0.05 -> 381.01 | Y61: {=W61 * _xlfn.XLOOKUP(C61, {"MELI";"WEB";"IG";"OTRO"}, $AS$3:$AS$6)} -> 76.202 | AC61: =IF(OR(H61="D6 Classic",H61="D6 Deluxe",H61="D6 Gold"),6*I61, IF(OR(H61="D2",H61="D2 moño"),2*I61, IF(H61="Cajita de 4",4*I61, IF(OR(H61="Mini Recuerdo",H61="Choco Cintas",H61="Choco Suelto"),1*I61, IF(H61="Caja 22 Chocos",22*I61, IF(H61="Caja 44 Chocos",44*I61,"")))))) -> 25
C62: MELI | D62: Completado | E62: Jisela Maidana | H62: Choco Suelto | I62: 25 | J62: 14458.37 | K62: 20100 | R62: 7527.75 | W62: =J62-R62 -> 6930.62 | X62: =W62*0.05 -> 346.531 | Y62: {=W62 * _xlfn.XLOOKUP(C62, {"MELI";"WEB";"IG";"OTRO"}, $AS$3:$AS$6)} -> 69.3062 | AC62: =IF(OR(H62="D6 Classic",H62="D6 Deluxe",H62="D6 Gold"),6*I62, IF(OR(H62="D2",H62="D2 moño"),2*I62, IF(H62="Cajita de 4",4*I62, IF(OR(H62="Mini Recuerdo",H62="Choco Cintas",H62="Choco Suelto"),1*I62, IF(H62="Caja 22 Chocos",22*I62, IF(H62="Caja 44 Chocos",44*I62,"")))))) -> 25 | AE62: =SUM(AD63:AD500) -> 35 | AF62: =AE62/50 -> 0.7
B63: 45985 | C63: MELI | D63: Completado | E63: Sol Armesto | F63: Malena XV | H63: D6 Gold | I63: 30 | J63: 147667.76 | K63: 187000 | O63: 6560.49 | R63: 72809.443 | T63: 46.75 | U63: 5610 | W63: =J63-R63 -> 74858.317 | X63: =W63*0.05 -> 3742.9159 | Y63: {=W63 * _xlfn.XLOOKUP(C63, {"MELI";"WEB";"IG";"OTRO"}, $AS$3:$AS$6)} -> 748.58317 | AC63: =IF(OR(H63="D6 Classic",H63="D6 Deluxe",H63="D6 Gold"),6*I63, IF(OR(H63="D2",H63="D2 moño"),2*I63, IF(H63="Cajita de 4",4*I63, IF(OR(H63="Mini Recuerdo",H63="Choco Cintas",H63="Choco Suelto"),1*I63, IF(H63="Caja 22 Chocos",22*I63, IF(H63="Caja 44 Chocos",44*I63,"")))))) -> 180 | AD63: =IF(D63="Falta", AC63, 0) -> 0
C64: MELI | D64: Completado | E64: Cinthia Medina | H64: Cajita de 4 | I64: 20 | J64: 55509.01 | K64: 81400 | O64: 11645.99 | R64: 28870 | U64: 2442 | W64: =J64-R64 -> 26639.01 | X64: =W64*0.05 -> 1331.9505 | Y64: {=W64 * _xlfn.XLOOKUP(C64, {"MELI";"WEB";"IG";"OTRO"}, $AS$3:$AS$6)} -> 266.3901 | Z64: =SUM(W32:W79) -> 1150001.2 | AC64: =IF(OR(H64="D6 Classic",H64="D6 Deluxe",H64="D6 Gold"),6*I64, IF(OR(H64="D2",H64="D2 moño"),2*I64, IF(H64="Cajita de 4",4*I64, IF(OR(H64="Mini Recuerdo",H64="Choco Cintas",H64="Choco Suelto"),1*I64, IF(H64="Caja 22 Chocos",22*I64, IF(H64="Caja 44 Chocos",44*I64,"")))))) -> 80 | AD64: =IF(D64="Falta", AC64, 0) -> 0
C65: MELI | D65: Completado | E65: Rosario Cano | H65: D6 Classic | I65: 20 | J65: 98970 | K65: 120000 | R65: 46629.8 | W65: =J65-R65 -> 52340.2 | X65: =W65*0.05 -> 2617.01 | Y65: {=W65 * _xlfn.XLOOKUP(C65, {"MELI";"WEB";"IG";"OTRO"}, $AS$3:$AS$6)} -> 523.402 | AC65: =IF(OR(H65="D6 Classic",H65="D6 Deluxe",H65="D6 Gold"),6*I65, IF(OR(H65="D2",H65="D2 moño"),2*I65, IF(H65="Cajita de 4",4*I65, IF(OR(H65="Mini Recuerdo",H65="Choco Cintas",H65="Choco Suelto"),1*I65, IF(H65="Caja 22 Chocos",22*I65, IF(H65="Caja 44 Chocos",44*I65,"")))))) -> 120 | AD65: =IF(D65="Falta", AC65, 0) -> 0
C66: MELI | D66: Completado | E66: Ana García | F66: St George | H66: Choco Suelto | I66: 50 | J66: 28916.75 | K66: 40200 | R66: 15050 | W66: =J66-R66 -> 13866.75 | X66: =W66*0.05 -> 693.3375 | Y66: {=W66 * _xlfn.XLOOKUP(C66, {"MELI";"WEB";"IG";"OTRO"}, $AS$3:$AS$6)} -> 138.6675 | Z66: =SUM(R32:R68) -> 989823.01 | AC66: =IF(OR(H66="D6 Classic",H66="D6 Deluxe",H66="D6 Gold"),6*I66, IF(OR(H66="D2",H66="D2 moño"),2*I66, IF(H66="Cajita de 4",4*I66, IF(OR(H66="Mini Recuerdo",H66="Choco Cintas",H66="Choco Suelto"),1*I66, IF(H66="Caja 22 Chocos",22*I66, IF(H66="Caja 44 Chocos",44*I66,"")))))) -> 50 | AD66: =IF(D66="Falta", AC66, 0) -> 0
C67: MELI | D67: Completado | E67: Lorena Vanesa Ascione | H67: Mini Recuerdo | I67: 25 | J67: 23130.5 | K67: 36000 | R67: 15349.5 | W67: =J67-R67 -> 7781 | X67: =W67*0.05 -> 389.05 | Y67: {=W67 * _xlfn.XLOOKUP(C67, {"MELI";"WEB";"IG";"OTRO"}, $AS$3:$AS$6)} -> 77.81 | AC67: =IF(OR(H67="D6 Classic",H67="D6 Deluxe",H67="D6 Gold"),6*I67, IF(OR(H67="D2",H67="D2 moño"),2*I67, IF(H67="Cajita de 4",4*I67, IF(OR(H67="Mini Recuerdo",H67="Choco Cintas",H67="Choco Suelto"),1*I67, IF(H67="Caja 22 Chocos",22*I67, IF(H67="Caja 44 Chocos",44*I67,"")))))) -> 25 | AD67: =IF(D67="Falta", AC67, 0) -> 0
C68: MELI | D68: Completado | E68: Marianela Pettineroli | H68: D6 Gold | I68: 1 | J68: 4205 | K68: 6700 | R68: 2426.9814 | W68: =J68-R68 -> 1778.0186 | X68: =W68*0.05 -> 88.900929 | Y68: {=W68 * _xlfn.XLOOKUP(C68, {"MELI";"WEB";"IG";"OTRO"}, $AS$3:$AS$6)} -> 17.780186 | AC68: =IF(OR(H68="D6 Classic",H68="D6 Deluxe",H68="D6 Gold"),6*I68, IF(OR(H68="D2",H68="D2 moño"),2*I68, IF(H68="Cajita de 4",4*I68, IF(OR(H68="Mini Recuerdo",H68="Choco Cintas",H68="Choco Suelto"),1*I68, IF(H68="Caja 22 Chocos",22*I68, IF(H68="Caja 44 Chocos",44*I68,"")))))) -> 6 | AD68: =IF(D68="Falta", AC68, 0) -> 0
C69: MELI | D69: Completado | E69: Marcelo Sigal | H69: Choco Suelto | I69: 200 | J69: =K69-T69-U69 -> 118297.77 | K69: 120860 | R69: 60222 | T69: 145.03 | U69: 2417.2 | W69: =J69-R69 -> 58075.77 | X69: =W69*0.05 -> 2903.7885 | Y69: {=W69 * _xlfn.XLOOKUP(C69, {"MELI";"WEB";"IG";"OTRO"}, $AS$3:$AS$6)} -> 580.7577 | Z69: =SUM(J32:J68) -> 1785009.5 | AC69: =IF(OR(H69="D6 Classic",H69="D6 Deluxe",H69="D6 Gold"),6*I69, IF(OR(H69="D2",H69="D2 moño"),2*I69, IF(H69="Cajita de 4",4*I69, IF(OR(H69="Mini Recuerdo",H69="Choco Cintas",H69="Choco Suelto"),1*I69, IF(H69="Caja 22 Chocos",22*I69, IF(H69="Caja 44 Chocos",44*I69,"")))))) -> 200 | AD69: =IF(D69="Falta", AC69, 0) -> 0
C70: WEB | D70: Completado | E70: Denise Raciti | H70: Choco Suelto | I70: 175 | J70: =K70-T70-U70 -> 149448.08 | K70: 152685 | R70: 73906.65 | T70: 183.22 | U70: 3053.7 | W70: =J70-R70 -> 75541.43 | X70: =W70*0.05 -> 3777.0715 | Y70: {=W70 * _xlfn.XLOOKUP(C70, {"MELI";"WEB";"IG";"OTRO"}, $AS$3:$AS$6)} -> 7554.143 | AC70: =IF(OR(H70="D6 Classic",H70="D6 Deluxe",H70="D6 Gold"),6*I70, IF(OR(H70="D2",H70="D2 moño"),2*I70, IF(H70="Cajita de 4",4*I70, IF(OR(H70="Mini Recuerdo",H70="Choco Cintas",H70="Choco Suelto"),1*I70, IF(H70="Caja 22 Chocos",22*I70, IF(H70="Caja 44 Chocos",44*I70,"")))))) -> 175 | AD70: =IF(D70="Falta", AC70, 0) -> 0
C71: MELI | D71: Completado | E71: Denise Raciti | H71: Mini Recuerdo | I71: 60 | X71: =W71*0.05 -> 0 | Y71: {=W71 * _xlfn.XLOOKUP(C71, {"MELI";"WEB";"IG";"OTRO"}, $AS$3:$AS$6)} -> 0 | AC71: =IF(OR(H71="D6 Classic",H71="D6 Deluxe",H71="D6 Gold"),6*I71, IF(OR(H71="D2",H71="D2 moño"),2*I71, IF(H71="Cajita de 4",4*I71, IF(OR(H71="Mini Recuerdo",H71="Choco Cintas",H71="Choco Suelto"),1*I71, IF(H71="Caja 22 Chocos",22*I71, IF(H71="Caja 44 Chocos",44*I71,"")))))) -> 60 | AD71: =IF(D71="Falta", AC71, 0) -> 0
C72: MELI | D72: Completado | E72: Vanina medina | H72: Mini Recuerdo | I72: 25 | J72: 23130.51 | K72: 36000 | R72: 8838.5 | W72: =J72-R72 -> 14292.01 | X72: =W72*0.05 -> 714.6005 | Y72: {=W72 * _xlfn.XLOOKUP(C72, {"MELI";"WEB";"IG";"OTRO"}, $AS$3:$AS$6)} -> 142.9201 | Z72: =Z64+Z66 -> 2139824.2 | AC72: =IF(OR(H72="D6 Classic",H72="D6 Deluxe",H72="D6 Gold"),6*I72, IF(OR(H72="D2",H72="D2 moño"),2*I72, IF(H72="Cajita de 4",4*I72, IF(OR(H72="Mini Recuerdo",H72="Choco Cintas",H72="Choco Suelto"),1*I72, IF(H72="Caja 22 Chocos",22*I72, IF(H72="Caja 44 Chocos",44*I72,"")))))) -> 25 | AD72: =IF(D72="Falta", AC72, 0) -> 0
C73: MELI | D73: Completado | E73: Vanina medina | H73: Mini Recuerdo | I73: 10 | J73: 9800 | R73: 3535.4 | T73: 11.76 | U73: 196 | W73: =J73-R73-T73-U73 -> 6056.84 | X73: =W73*0.05 -> 302.842 | Y73: {=W73 * _xlfn.XLOOKUP(C73, {"MELI";"WEB";"IG";"OTRO"}, $AS$3:$AS$6)} -> 60.5684 | AC73: =IF(OR(H73="D6 Classic",H73="D6 Deluxe",H73="D6 Gold"),6*I73, IF(OR(H73="D2",H73="D2 moño"),2*I73, IF(H73="Cajita de 4",4*I73, IF(OR(H73="Mini Recuerdo",H73="Choco Cintas",H73="Choco Suelto"),1*I73, IF(H73="Caja 22 Chocos",22*I73, IF(H73="Caja 44 Chocos",44*I73,"")))))) -> 10 | AD73: =IF(D73="Falta", AC73, 0) -> 0
B74: 45989 | C74: MELI | D74: Falta | E74: Marisol Curas | H74: Mini Recuerdo | I74: 35 | J74: 29925 | R74: 12374 | T74: 35.91 | U74: 598.5 | W74: =J74-R74-T74-U74 -> 16916.59 | X74: =W74*0.05 -> 845.8295 | Y74: {=W74 * _xlfn.XLOOKUP(C74, {"MELI";"WEB";"IG";"OTRO"}, $AS$3:$AS$6)} -> 169.1659 | AC74: =IF(OR(H74="D6 Classic",H74="D6 Deluxe",H74="D6 Gold"),6*I74, IF(OR(H74="D2",H74="D2 moño"),2*I74, IF(H74="Cajita de 4",4*I74, IF(OR(H74="Mini Recuerdo",H74="Choco Cintas",H74="Choco Suelto"),1*I74, IF(H74="Caja 22 Chocos",22*I74, IF(H74="Caja 44 Chocos",44*I74,"")))))) -> 35 | AD74: =IF(D74="Falta", AC74, 0) -> 35
B75: 45989 | C75: MELI | D75: Completado | E75: Daniela Carmona | H75: Choco Suelto | I75: 150 | J75: 109000 | O75: 10000 | R75: 45150 | T75: 130.8 | U75: 2180 | W75: =J75-O75-R75-T75-U75 -> 51539.2 | X75: =W75*0.05 -> 2576.96 | Y75: {=W75 * _xlfn.XLOOKUP(C75, {"MELI";"WEB";"IG";"OTRO"}, $AS$3:$AS$6)} -> 515.392 | AC75: =IF(OR(H75="D6 Classic",H75="D6 Deluxe",H75="D6 Gold"),6*I75, IF(OR(H75="D2",H75="D2 moño"),2*I75, IF(H75="Cajita de 4",4*I75, IF(OR(H75="Mini Recuerdo",H75="Choco Cintas",H75="Choco Suelto"),1*I75, IF(H75="Caja 22 Chocos",22*I75, IF(H75="Caja 44 Chocos",44*I75,"")))))) -> 150 | AD75: =IF(D75="Falta", AC75, 0) -> 0
B76: 45988 | C76: IG | D76: Completado | E76: Mar quijada | H76: Choco Suelto | I76: 50 | J76: 29700 | K76: 37659 | O76: =K76-J76 -> 7959 | R76: 15050 | T76: 45.19 | U76: 753.18 | W76: =J76-R76-T76-U76 -> 13851.63 | X76: =W76*0.05 -> 692.5815 | Y76: {=W76 * _xlfn.XLOOKUP(C76, {"MELI";"WEB";"IG";"OTRO"}, $AS$3:$AS$6)} -> 1385.163 | AC76: =IF(OR(H76="D6 Classic",H76="D6 Deluxe",H76="D6 Gold"),6*I76, IF(OR(H76="D2",H76="D2 moño"),2*I76, IF(H76="Cajita de 4",4*I76, IF(OR(H76="Mini Recuerdo",H76="Choco Cintas",H76="Choco Suelto"),1*I76, IF(H76="Caja 22 Chocos",22*I76, IF(H76="Caja 44 Chocos",44*I76,"")))))) -> 50 | AD76: =IF(D76="Falta", AC76, 0) -> 0
C77: IG | D77: Completado | E77: Tefi Greco | H77: D6 Gold | I77: 10 | J77: 50400 | K77: 60046 | O77: 9646 | R77: 24270 | T77: 36.03 | U77: 1200.92 | W77: =J77-R77-T77-U77 -> 24893.05 | X77: =W77*0.05 -> 1244.6525 | Y77: {=W77 * _xlfn.XLOOKUP(C77, {"MELI";"WEB";"IG";"OTRO"}, $AS$3:$AS$6)} -> 2489.305 | AC77: =IF(OR(H77="D6 Classic",H77="D6 Deluxe",H77="D6 Gold"),6*I77, IF(OR(H77="D2",H77="D2 moño"),2*I77, IF(H77="Cajita de 4",4*I77, IF(OR(H77="Mini Recuerdo",H77="Choco Cintas",H77="Choco Suelto"),1*I77, IF(H77="Caja 22 Chocos",22*I77, IF(H77="Caja 44 Chocos",44*I77,"")))))) -> 60 | AD77: =IF(D77="Falta", AC77, 0) -> 0
C78: IG | D78: Completado | E78: yaquelina paez | H78: D2 | I78: 50 | J78: 121125 | R78: 68300 | T78: 146.22 | W78: =J78-R78-T78 -> 52678.78 | X78: =W78*0.05 -> 2633.939 | Y78: {=W78 * _xlfn.XLOOKUP(C78, {"MELI";"WEB";"IG";"OTRO"}, $AS$3:$AS$6)} -> 5267.878 | AC78: =IF(OR(H78="D6 Classic",H78="D6 Deluxe",H78="D6 Gold"),6*I78, IF(OR(H78="D2",H78="D2 moño"),2*I78, IF(H78="Cajita de 4",4*I78, IF(OR(H78="Mini Recuerdo",H78="Choco Cintas",H78="Choco Suelto"),1*I78, IF(H78="Caja 22 Chocos",22*I78, IF(H78="Caja 44 Chocos",44*I78,"")))))) -> 100 | AD78: =IF(D78="Falta", AC78, 0) -> 0
C79: MELI | X79: =W79*0.05 -> 0 | Y79: {=W79 * _xlfn.XLOOKUP(C79, {"MELI";"WEB";"IG";"OTRO"}, $AS$3:$AS$6)} -> 0 | AC79: =IF(OR(H81="D6 Classic",H81="D6 Deluxe",H81="D6 Gold"),6*I79, IF(OR(H81="D2",H81="D2 moño"),2*I79, IF(H81="Cajita de 4",4*I79, IF(OR(H81="Mini Recuerdo",H81="Choco Cintas",H81="Choco Suelto"),1*I79, IF(H81="Caja 22 Chocos",22*I79, IF(H81="Caja 44 Chocos",44*I79,"")))))) -> 0 | AD79: =IF(D79="Falta", AC79, 0) -> 0
C80: MELI | E80: Diciembre | X80: =W80*0.05 -> 0 | Y80: {=W80 * _xlfn.XLOOKUP(C80, {"MELI";"WEB";"IG";"OTRO"}, $AS$3:$AS$6)} -> 0 | AC80: =IF(OR(H80="D6 Classic",H80="D6 Deluxe",H80="D6 Gold"),6*I80, IF(OR(H80="D2",H80="D2 moño"),2*I80, IF(H80="Cajita de 4",4*I80, IF(OR(H80="Mini Recuerdo",H80="Choco Cintas",H80="Choco Suelto"),1*I80, IF(H80="Caja 22 Chocos",22*I80, IF(H80="Caja 44 Chocos",44*I80,"")))))) | AD80: =IF(D80="Falta", AC80, 0) -> 0
C81: MELI | D81: Completado | E81: Ariela fefer | H81: Choco Suelto | I81: 200 | J81: 112860 | K81: 122860 | O81: 10000 | R81: =_xlfn.XLOOKUP(H81, AJ:AJ, AK:AK) * I81 -> 58800 | T81: 73.72 | U81: 2457.2 | W81: =J81-T81-U81-R81 -> 51529.08 | X81: =W81*0.05 -> 2576.454 | Y81: {=W81 * _xlfn.XLOOKUP(C81, {"MELI";"WEB";"IG";"OTRO"}, $AS$3:$AS$6)} -> 515.2908 | AC81: =IF(OR(#REF!="D6 Classic",#REF!="D6 Deluxe",#REF!="D6 Gold"),6*I81, IF(OR(#REF!="D2",#REF!="D2 moño"),2*I81, IF(#REF!="Cajita de 4",4*I81, IF(OR(#REF!="Mini Recuerdo",#REF!="Choco Cintas",#REF!="Choco Suelto"),1*I81, IF(#REF!="Caja 22 Chocos",22*I81, IF(#REF!="Caja 44 Chocos",44*I81,"")))))) -> #REF! | AD81: =IF(D81="Falta", AC81, 0) -> 0
C82: MELI | E82: Anabella Silvia chal | I82: 1 | J82: 15000 | K82: 15000 | R82: 15000 | T82: 9 | U82: 300 | W82: =J82-S82-T82-U82-V82-R82 -> -309 | X82: =W82*0.05 -> -15.45 | Y82: {=W82 * _xlfn.XLOOKUP(C82, {"MELI";"WEB";"IG";"OTRO"}, $AS$3:$AS$6)} -> -3.09 | AC82: =IF(OR(H82="D6 Classic",H82="D6 Deluxe",H82="D6 Gold"),6*I82, IF(OR(H82="D2",H82="D2 moño"),2*I82, IF(H82="Cajita de 4",4*I82, IF(OR(H82="Mini Recuerdo",H82="Choco Cintas",H82="Choco Suelto"),1*I82, IF(H82="Caja 22 Chocos",22*I82, IF(H82="Caja 44 Chocos",44*I82,"")))))) | AD82: =IF(D82="Falta", AC82, 0) -> 0
C83: MELI | E83: Silvana Robel | H83: Mini Recuerdo | I83: 25 | J83: 23398 | K83: 31200 | R83: =_xlfn.XLOOKUP(H83, AJ:AJ, AK:AK) * I83 -> 8175 | W83: =J83-S83-T83-U83-V83-R83 -> 15223 | X83: =#REF!*0.05 -> #REF! | Y83: {=#REF! * _xlfn.XLOOKUP( C83, {"MELI";"WEB";"IG";"OTRO"}, $AS$3:$AS$6)} -> #REF! | AC83: =IF(OR(H83="D6 Classic",H83="D6 Deluxe",H83="D6 Gold"),6*I83, IF(OR(H83="D2",H83="D2 moño"),2*I83, IF(H83="Cajita de 4",4*I83, IF(OR(H83="Mini Recuerdo",H83="Choco Cintas",H83="Choco Suelto"),1*I83, IF(H83="Caja 22 Chocos",22*I83, IF(H83="Caja 44 Chocos",44*I83,"")))))) -> 25 | AD83: =IF(D83="Falta", AC83, 0) -> 0
C84: MELI | E84: Diana Inchauspe | H84: Choco Suelto | I84: 50 | J84: 41628.5 | K84: 55400 | R84: =_xlfn.XLOOKUP(H84, AJ:AJ, AK:AK) * I84 -> 14700 | W84: =J84-S84-T84-U84-V84-R84 -> 26928.5 | X84: =W84*0.05 -> 1346.425 | Y84: {=W84 * _xlfn.XLOOKUP(C84, {"MELI";"WEB";"IG";"OTRO"}, $AS$3:$AS$6)} -> 269.285 | AC84: =IF(OR(H84="D6 Classic",H84="D6 Deluxe",H84="D6 Gold"),6*I84, IF(OR(H84="D2",H84="D2 moño"),2*I84, IF(H84="Cajita de 4",4*I84, IF(OR(H84="Mini Recuerdo",H84="Choco Cintas",H84="Choco Suelto"),1*I84, IF(H84="Caja 22 Chocos",22*I84, IF(H84="Caja 44 Chocos",44*I84,"")))))) -> 50 | AD84: =IF(D84="Falta", AC84, 0) -> 0
A85: =_xlfn.XLOOKUP(H85, AJ:AJ, AK:AK) * I85 -> 7350 | C85: MELI | E85: EDIT NORA MAITINI | H85: Choco Suelto | I85: 25 | J85: 17140 | K85: 22500 | R85: =_xlfn.XLOOKUP(H85, AJ:AJ, AK:AK) * I85 -> 7350 | W85: =J85-S85-T85-U85-V85-R85 -> 9790 | X85: =W85*0.05 -> 489.5 | Y85: {=W85 * _xlfn.XLOOKUP(C85, {"MELI";"WEB";"IG";"OTRO"}, $AS$3:$AS$6)} -> 97.9 | AC85: =IF(OR(H85="D6 Classic",H85="D6 Deluxe",H85="D6 Gold"),6*I85, IF(OR(H85="D2",H85="D2 moño"),2*I85, IF(H85="Cajita de 4",4*I85, IF(OR(H85="Mini Recuerdo",H85="Choco Cintas",H85="Choco Suelto"),1*I85, IF(H85="Caja 22 Chocos",22*I85, IF(H85="Caja 44 Chocos",44*I85,"")))))) -> 25 | AD85: =IF(D85="Falta", AC85, 0) -> 0
C86: MELI | E86: cristian kilapi | H86: Mini Recuerdo | I86: 25 | J86: 23679 | K86: 36000 | R86: =_xlfn.XLOOKUP(H86, AJ:AJ, AK:AK) * I86 -> 8175 | W86: =J86-S86-T86-U86-V86-R86 -> 15504 | X86: =W86*0.05 -> 775.2 | Y86: {=W86 * _xlfn.XLOOKUP(C86, {"MELI";"WEB";"IG";"OTRO"}, $AS$3:$AS$6)} -> 155.04 | AC86: =IF(OR(H86="D6 Classic",H86="D6 Deluxe",H86="D6 Gold"),6*I86, IF(OR(H86="D2",H86="D2 moño"),2*I86, IF(H86="Cajita de 4",4*I86, IF(OR(H86="Mini Recuerdo",H86="Choco Cintas",H86="Choco Suelto"),1*I86, IF(H86="Caja 22 Chocos",22*I86, IF(H86="Caja 44 Chocos",44*I86,"")))))) -> 25 | AD86: =IF(D86="Falta", AC86, 0) -> 0
C87: MELI | R87: =_xlfn.XLOOKUP(H87, AJ:AJ, AK:AK) * I87 -> 0 | W87: =J87-S87-T87-U87-V87-R87 -> 0 | X87: =W87*0.05 -> 0 | Y87: {=W87 * _xlfn.XLOOKUP(C87, {"MELI";"WEB";"IG";"OTRO"}, $AS$3:$AS$6)} -> 0 | AC87: =IF(OR(H87="D6 Classic",H87="D6 Deluxe",H87="D6 Gold"),6*I87, IF(OR(H87="D2",H87="D2 moño"),2*I87, IF(H87="Cajita de 4",4*I87, IF(OR(H87="Mini Recuerdo",H87="Choco Cintas",H87="Choco Suelto"),1*I87, IF(H87="Caja 22 Chocos",22*I87, IF(H87="Caja 44 Chocos",44*I87,"")))))) | AD87: =IF(D87="Falta", AC87, 0) -> 0
C88: MELI | E88: Maria Belen Argañaras | H88: Cajita de 4 | I88: 10 | J88: 41134.19 | K88: 41800 | L88: -5684.8 | M88: -4600 | N88: -627 | O88: 10245.99 | P88: 0 | Q88: =P88+O88 -> 10245.99 | R88: =_xlfn.XLOOKUP(H88, AJ:AJ, AK:AK) * I88 -> 14435 | S88: =K88+L88+M88+N88+Q88 -> 41134.19 | U88: =K88-Q88-#REF!-#REF!-S88 -> #REF! | W88: =J88-S88-T88-U88-V88-R88 -> #REF! | X88: =W88*0.05 -> #REF! | Y88: {=W88 * _xlfn.XLOOKUP(C88, {"MELI";"WEB";"IG";"OTRO"}, $AS$3:$AS$6)} -> #REF! | AC88: =IF(OR(H88="D6 Classic",H88="D6 Deluxe",H88="D6 Gold"),6*I88, IF(OR(H88="D2",H88="D2 moño"),2*I88, IF(H88="Cajita de 4",4*I88, IF(OR(H88="Mini Recuerdo",H88="Choco Cintas",H88="Choco Suelto"),1*I88, IF(H88="Caja 22 Chocos",22*I88, IF(H88="Caja 44 Chocos",44*I88,"")))))) -> 40 | AD88: =IF(D88="Falta", AC88, 0) -> 0
C89: MELI | E89: Joana Fernandez Castro | H89: Choco Suelto | I89: 75 | J89: 58790.99 | K89: 67500 | L89: -9180 | M89: -6900 | O89: 7370.99 | P89: 0 | Q89: =P89+O89 -> 7370.99 | R89: =_xlfn.XLOOKUP(H89, AJ:AJ, AK:AK) * I89 -> 22050 | W89: =J89-S89-T89-U89-V89-R89 -> 36740.99 | X89: =W89*0.05 -> 1837.0495 | Y89: {=W89 * _xlfn.XLOOKUP(C89, {"MELI";"WEB";"IG";"OTRO"}, $AS$3:$AS$6)} -> 367.4099 | AC89: =IF(OR(H89="D6 Classic",H89="D6 Deluxe",H89="D6 Gold"),6*I89, IF(OR(H89="D2",H89="D2 moño"),2*I89, IF(H89="Cajita de 4",4*I89, IF(OR(H89="Mini Recuerdo",H89="Choco Cintas",H89="Choco Suelto"),1*I89, IF(H89="Caja 22 Chocos",22*I89, IF(H89="Caja 44 Chocos",44*I89,"")))))) -> 75 | AD89: =IF(D89="Falta", AC89, 0) -> 0
C90: MELI | E90: Ximena Anahi Barraza | H90: Cajita de 4 | I90: 5 | J90: 15444.1 | K90: 20900 | L90: -2842.4 | M90: -2300 | N90: -313.5 | O90: 16830.99 | P90: -16830.99 | Q90: =P90+O90 -> 0 | R90: =_xlfn.XLOOKUP(H90, AJ:AJ, AK:AK) * I90 -> 7217.5 | W90: =J90-S90-T90-U90-V90-R90 -> 8226.6 | X90: =W90*0.05 -> 411.33 | Y90: {=W90 * _xlfn.XLOOKUP(C90, {"MELI";"WEB";"IG";"OTRO"}, $AS$3:$AS$6)} -> 82.266 | AC90: =IF(OR(H90="D6 Classic",H90="D6 Deluxe",H90="D6 Gold"),6*I90, IF(OR(H90="D2",H90="D2 moño"),2*I90, IF(H90="Cajita de 4",4*I90, IF(OR(H90="Mini Recuerdo",H90="Choco Cintas",H90="Choco Suelto"),1*I90, IF(H90="Caja 22 Chocos",22*I90, IF(H90="Caja 44 Chocos",44*I90,"")))))) -> 20 | AD90: =IF(D90="Falta", AC90, 0) -> 0
C91: MELI | E91: Liana Roxana Castello | H91: Choco Suelto | I91: 25 | J91: 24510.99 | K91: 22500 | L91: -3060 | M91: -2300 | O91: 7370.99 | P91: 0 | Q91: =P91+O91 -> 7370.99 | R91: =_xlfn.XLOOKUP(H91, AJ:AJ, AK:AK) * I91 -> 7350 | W91: =J91-S91-T91-U91-V91-R91 -> 17160.99 | X91: =W91*0.05 -> 858.0495 | Y91: {=W91 * _xlfn.XLOOKUP(C91, {"MELI";"WEB";"IG";"OTRO"}, $AS$3:$AS$6)} -> 171.6099 | AC91: =IF(OR(H91="D6 Classic",H91="D6 Deluxe",H91="D6 Gold"),6*I91, IF(OR(H91="D2",H91="D2 moño"),2*I91, IF(H91="Cajita de 4",4*I91, IF(OR(H91="Mini Recuerdo",H91="Choco Cintas",H91="Choco Suelto"),1*I91, IF(H91="Caja 22 Chocos",22*I91, IF(H91="Caja 44 Chocos",44*I91,"")))))) -> 25 | AD91: =IF(D91="Falta", AC91, 0) -> 0
C92: MELI | E92: Sebastian Martinez Boichuk | H92: Choco Suelto | I92: 25 | J92: 24510.99 | K92: 22500 | L92: -3060 | M92: -2300 | O92: 7370.99 | P92: 0 | Q92: =P92+O92 -> 7370.99 | R92: =_xlfn.XLOOKUP(H92, AJ:AJ, AK:AK) * I92 -> 7350 | W92: =J92-S92-T92-U92-V92-R92 -> 17160.99 | X92: =W92*0.05 -> 858.0495 | Y92: {=W92 * _xlfn.XLOOKUP(C92, {"MELI";"WEB";"IG";"OTRO"}, $AS$3:$AS$6)} -> 171.6099 | AC92: =IF(OR(H92="D6 Classic",H92="D6 Deluxe",H92="D6 Gold"),6*I92, IF(OR(H92="D2",H92="D2 moño"),2*I92, IF(H92="Cajita de 4",4*I92, IF(OR(H92="Mini Recuerdo",H92="Choco Cintas",H92="Choco Suelto"),1*I92, IF(H92="Caja 22 Chocos",22*I92, IF(H92="Caja 44 Chocos",44*I92,"")))))) -> 25 | AD92: =IF(D92="Falta", AC92, 0) -> 0
C93: MELI | E93: Miryam Edith Zavaley | H93: Choco Suelto | I93: 25 | J93: 16664.72 | K93: 22500 | L93: -3060 | M93: -2300 | N93: -475.28 | O93: 9185.14 | P93: -9185.14 | Q93: =P93+O93 -> 0 | R93: =_xlfn.XLOOKUP(H93, AJ:AJ, AK:AK) * I93 -> 7350 | W93: =J93-S93-T93-U93-V93-R93 -> 9314.72 | X93: =W93*0.05 -> 465.736 | Y93: {=W93 * _xlfn.XLOOKUP(C93, {"MELI";"WEB";"IG";"OTRO"}, $AS$3:$AS$6)} -> 93.1472 | AC93: =IF(OR(H93="D6 Classic",H93="D6 Deluxe",H93="D6 Gold"),6*I93, IF(OR(H93="D2",H93="D2 moño"),2*I93, IF(H93="Cajita de 4",4*I93, IF(OR(H93="Mini Recuerdo",H93="Choco Cintas",H93="Choco Suelto"),1*I93, IF(H93="Caja 22 Chocos",22*I93, IF(H93="Caja 44 Chocos",44*I93,"")))))) -> 25 | AD93: =IF(D93="Falta", AC93, 0) -> 0
C94: MELI | E94: Marina Gisela di Fonzo | H94: Choco Suelto | I94: 50 | J94: 37679 | K94: 51000 | L94: -6936 | M94: -5620 | N94: -765 | O94: 0 | P94: 0 | Q94: =P94+O94 -> 0 | R94: =_xlfn.XLOOKUP(H94, AJ:AJ, AK:AK) * I94 -> 14700 | W94: =J94-S94-T94-U94-V94-R94 -> 22979 | X94: =W94*0.05 -> 1148.95 | Y94: {=W94 * _xlfn.XLOOKUP(C94, {"MELI";"WEB";"IG";"OTRO"}, $AS$3:$AS$6)} -> 229.79 | AC94: =IF(OR(H94="D6 Classic",H94="D6 Deluxe",H94="D6 Gold"),6*I94, IF(OR(H94="D2",H94="D2 moño"),2*I94, IF(H94="Cajita de 4",4*I94, IF(OR(H94="Mini Recuerdo",H94="Choco Cintas",H94="Choco Suelto"),1*I94, IF(H94="Caja 22 Chocos",22*I94, IF(H94="Caja 44 Chocos",44*I94,"")))))) -> 50 | AD94: =IF(D94="Falta", AC94, 0) -> 0
C95: MELI | E95: Daniela Anahi Ramallo | H95: Choco Suelto | I95: 25 | J95: 16713.42 | K95: 22500 | L95: -3060 | M95: -2300 | N95: -426.58 | O95: 5938.79 | P95: -5938.79 | Q95: =P95+O95 -> 0 | R95: =_xlfn.XLOOKUP(H95, AJ:AJ, AK:AK) * I95 -> 7350 | W95: =J95-S95-T95-U95-V95-R95 -> 9363.42 | X95: =W95*0.05 -> 468.171 | Y95: {=W95 * _xlfn.XLOOKUP(C95, {"MELI";"WEB";"IG";"OTRO"}, $AS$3:$AS$6)} -> 93.6342 | AC95: =IF(OR(H95="D6 Classic",H95="D6 Deluxe",H95="D6 Gold"),6*I95, IF(OR(H95="D2",H95="D2 moño"),2*I95, IF(H95="Cajita de 4",4*I95, IF(OR(H95="Mini Recuerdo",H95="Choco Cintas",H95="Choco Suelto"),1*I95, IF(H95="Caja 22 Chocos",22*I95, IF(H95="Caja 44 Chocos",44*I95,"")))))) -> 25 | AD95: =IF(D95="Falta", AC95, 0) -> 0
C96: MELI | E96: Veronica Andrea Surdo | H96: Mini Recuerdo | I96: 25 | J96: 30701.1 | K96: 36000 | L96: -5220 | N96: -540 | O96: 461.1 | P96: 0 | Q96: =P96+O96 -> 461.1 | R96: =_xlfn.XLOOKUP(H96, AJ:AJ, AK:AK) * I96 -> 8175 | W96: =J96-S96-T96-U96-V96-R96 -> 22526.1 | X96: =W96*0.05 -> 1126.305 | Y96: {=W96 * _xlfn.XLOOKUP(C96, {"MELI";"WEB";"IG";"OTRO"}, $AS$3:$AS$6)} -> 225.261 | AC96: =IF(OR(H96="D6 Classic",H96="D6 Deluxe",H96="D6 Gold"),6*I96, IF(OR(H96="D2",H96="D2 moño"),2*I96, IF(H96="Cajita de 4",4*I96, IF(OR(H96="Mini Recuerdo",H96="Choco Cintas",H96="Choco Suelto"),1*I96, IF(H96="Caja 22 Chocos",22*I96, IF(H96="Caja 44 Chocos",44*I96,"")))))) -> 25 | AD96: =IF(D96="Falta", AC96, 0) -> 0
C97: MELI | E97: Mabel Susana Gazzero | H97: Choco Suelto | I97: 25 | J97: 16802.5 | K97: 22500 | L97: -3060 | M97: -2300 | N97: -337.5 | O97: 5942.79 | P97: -5942.79 | Q97: =P97+O97 -> 0 | R97: =_xlfn.XLOOKUP(H97, AJ:AJ, AK:AK) * I97 -> 7350 | W97: =J97-S97-T97-U97-V97-R97 -> 9452.5 | X97: =W97*0.05 -> 472.625 | Y97: {=W97 * _xlfn.XLOOKUP(C97, {"MELI";"WEB";"IG";"OTRO"}, $AS$3:$AS$6)} -> 94.525 | AC97: =IF(OR(H97="D6 Classic",H97="D6 Deluxe",H97="D6 Gold"),6*I97, IF(OR(H97="D2",H97="D2 moño"),2*I97, IF(H97="Cajita de 4",4*I97, IF(OR(H97="Mini Recuerdo",H97="Choco Cintas",H97="Choco Suelto"),1*I97, IF(H97="Caja 22 Chocos",22*I97, IF(H97="Caja 44 Chocos",44*I97,"")))))) -> 25 | AD97: =IF(D97="Falta", AC97, 0) -> 0
C98: MELI | E98: Horacio Atilio Ribero | H98: Caja 44 Chocos | I98: 1 | J98: 25057.36 | K98: 32900 | L98: -4474.4 | M98: -2810 | N98: -558.24 | O98: 4315.94 | P98: -4315.94 | Q98: =P98+O98 -> 0 | R98: =_xlfn.XLOOKUP(H98, AJ:AJ, AK:AK) * I98 -> 12512 | W98: =J98-S98-T98-U98-V98-R98 -> 12545.36 | X98: =W98*0.05 -> 627.268 | Y98: {=W98 * _xlfn.XLOOKUP(C98, {"MELI";"WEB";"IG";"OTRO"}, $AS$3:$AS$6)} -> 125.4536 | AC98: =IF(OR(H98="D6 Classic",H98="D6 Deluxe",H98="D6 Gold"),6*I98, IF(OR(H98="D2",H98="D2 moño"),2*I98, IF(H98="Cajita de 4",4*I98, IF(OR(H98="Mini Recuerdo",H98="Choco Cintas",H98="Choco Suelto"),1*I98, IF(H98="Caja 22 Chocos",22*I98, IF(H98="Caja 44 Chocos",44*I98,"")))))) -> 44 | AD98: =IF(D98="Falta", AC98, 0) -> 0
C99: MELI | E99: Andrea Natalia Castro | H99: Mini Recuerdo | I99: 25 | J99: 23679.51 | K99: 36000 | L99: -5220 | N99: -540 | O99: 0 | P99: -6560.49 | Q99: =P99+O99 -> -6560.49 | R99: =_xlfn.XLOOKUP(H99, AJ:AJ, AK:AK) * I99 -> 8175 | W99: =J99-S99-T99-U99-V99-R99 -> 15504.51 | X99: =W99*0.05 -> 775.2255 | Y99: {=W99 * _xlfn.XLOOKUP(C99, {"MELI";"WEB";"IG";"OTRO"}, $AS$3:$AS$6)} -> 155.0451 | AC99: =IF(OR(H99="D6 Classic",H99="D6 Deluxe",H99="D6 Gold"),6*I99, IF(OR(H99="D2",H99="D2 moño"),2*I99, IF(H99="Cajita de 4",4*I99, IF(OR(H99="Mini Recuerdo",H99="Choco Cintas",H99="Choco Suelto"),1*I99, IF(H99="Caja 22 Chocos",22*I99, IF(H99="Caja 44 Chocos",44*I99,"")))))) -> 25 | AD99: =IF(D99="Falta", AC99, 0) -> 0
C100: MELI | E100: Teresa Silvina Petracca | H100: Choco Suelto | I100: 25 | J100: 16702.14 | K100: 22500 | L100: -3060 | M100: -2300 | N100: -437.86 | O100: 6690.99 | P100: -6690.99 | Q100: =P100+O100 -> 0 | R100: =_xlfn.XLOOKUP(H100, AJ:AJ, AK:AK) * I100 -> 7350 | W100: =J100-S100-T100-U100-V100-R100 -> 9352.14 | X100: =W100*0.05 -> 467.607 | Y100: {=W100 * _xlfn.XLOOKUP(C100, {"MELI";"WEB";"IG";"OTRO"}, $AS$3:$AS$6)} -> 93.5214 | AC100: =IF(OR(H100="D6 Classic",H100="D6 Deluxe",H100="D6 Gold"),6*I100, IF(OR(H100="D2",H100="D2 moño"),2*I100, IF(H100="Cajita de 4",4*I100, IF(OR(H100="Mini Recuerdo",H100="Choco Cintas",H100="Choco Suelto"),1*I100, IF(H100="Caja 22 Chocos",22*I100, IF(H100="Caja 44 Chocos",44*I100,"")))))) -> 25 | AD100: =IF(D100="Falta", AC100, 0) -> 0
...

Sheet Gomitas
F3: x gr | H3: Picada
C4: Conitos | D4: 1000 | E4: 7494 | F4: =E4/D4 -> 7.494 | H4: 85 | I4: =F4*$H$4 -> 636.99
C5: Anillos | D5: 1000 | E5: 8795 | F5: =E5/D5 -> 8.795 | H5: 6 | I5: =F5*$H$4 -> 747.575
C6: Redonditos | D6: 1000 | E6: 9999 | F6: =E6/D6 -> 9.999 | H6: =H4*H5 -> 510 | I6: =F6*$H$4 -> 849.915
C7: Gusanitos | D7: 500 | E7: 7400 | F7: =E7/D7 -> 14.8 | I7: =F7*$H$4 -> 1258
C8: Ositos | D8: 500 | E8: 5123 | F8: =E8/D8 -> 10.246 | I8: =F8*$H$4 -> 870.91
C9: Moritas | D9: 500 | E9: 5800 | F9: =E9/D9 -> 11.6 | I9: =F9*$H$4 -> 986
I10: =SUM(I4:I9) -> 5349.39

Sheet Estampitas
N3: 0.1 | O3: 0.08
N4: 0.09 | O4: 0.06
N5: =N4+N3 -> 0.19 | O5: =O4+O3 -> 0.14 | R5: Descuento | S5: Descuento | T5: Descuento
B6: Doble base telada detalles foil | C6: Base | D6: Estampa | E6: Foil | F6: Impresión | G6: Pegamento | K6: Costo total | L6: Ganancia | M6: Total | N6: MP | O6: Ganan MP | R6: 0.05 | S6: 0.1 | T6: 0.15
C7: =Insumos!G12/4 -> 101.75 | D7: =Insumos!G18/6 -> 10.893333 | E7: =Insumos!G15/6 -> 48.666667 | F7: 100 | G7: 100 | K7: =SUM(C7:J7) -> 361.31 | L7: 500 | M7: =L7+K7 -> 861.31 | N7: =(L7+K7)+((K7+L7)*(N5)) -> 1024.9589 | O7: =N7-(N7*O5)-K7 -> 520.15465 | R7: 50 | S7: 100 | T7: 200
R8: Costo total | S8: Costo total | T8: Costo total
R9: =K7*R7 -> 18065.5 | S9: =K7*S7 -> 36131 | T9: =K9*T7 -> 0
N10: Transf | R10: MP | S10: MP | T10: MP
N11: =N7-(N7*R18) -> 922.46301 | R11: =($N7*R7)-(($N7*R7)*R6) -> 48685.548 | S11: =($N7*S7)-(($N7*S7)*S6) -> 92246.301 | T11: =($N7*T7)-(($N7*T7)*T6) -> 174243.01
N12: G. Transf | R12: =R11/R7 -> 973.71095 | S12: =S11/S7 -> 922.46301 | T12: =T11/T7 -> 871.21506
N13: =(N11-(N11*O4))-K7 -> 505.80523 | R13: Ganancia MP | S13: Ganancia MP | T13: Ganancia MP
R14: =(R11-R9)-(R11*$O$27) -> 30620.048 | S14: =(S11-S9)-(S11*$O$27) -> 56115.301 | T14: =(T11-T9)-(T11*$O$27) -> 174243.01
R15: =R14/R7 -> 612.40095 | S15: =S14/S7 -> 561.15301 | T15: =T14/T7 -> 871.21506
R16: Transf | S16: Transf | T16: Transf
R17: =R11-(R11*R18) -> 43816.993 | S17: =S11-(S11*S18) -> 83021.671 | T17: =T11-(T11*T18) -> 156818.71
N18: 0.1 | O18: 0.08 | R18: 0.1 | S18: 0.1 | T18: 0.1
N19: 0.09 | O19: 0.06 | R19: =R17/R7 -> 876.33986 | S19: =S17/S7 -> 830.21671 | T19: =T17/T7 -> 784.09356
N20: =N19+N18 -> 0.19 | O20: =O19+O18 -> 0.14 | R20: Ganancia trans | S20: Ganancia trans | T20: Ganancia trans
B21: Estampa cruz madera | C21: Cruz | D21: tarjeta frontal | E21: Base | F21: Borla | G21: Impresión | K21: Costo total | L21: Ganancia | M21: Total | N21: MP | O21: Ganan MP | R21: =R17-(R17*$O$26)-R9 -> 25751.493 | S21: =S17-(S17*$O$26)-S9 -> 46890.671 | T21: =T17-(T17*$O$26)-T9 -> 156818.71
C22: =Insumos!R18 -> 95.275 | D22: =Insumos!G18/5 -> 13.072 | E22: =Insumos!G18/4 -> 16.34 | F22: =Insumos!R15 -> 347.8 | G22: 100 | K22: =SUM(C22:J22) -> 572.487 | L22: 500 | M22: =L22+K22 -> 1072.487 | N22: =(L22+K22)+((K22+L22)*(N20)) -> 1276.2595 | O22: =N22-(N22*O20)-K22 -> 525.0962 | R22: =R21/R7 -> 515.02986 | S22: =S21/S7 -> 468.90671 | T22: =T21/T7 -> 784.09356
N25: Transf
N26: =N22-(N22*R33) -> 1276.2595
N27: G. Transf
N28: =(N26-(N26*O19))-K22 -> 627.19696
N32: 0.1 | O32: 0.08
N33: 0.09 | O33: 0.06
N34: =N33+N32 -> 0.19 | O34: =O33+O32 -> 0.14
B35: Estampa Fondo Craft | D35: tarjeta frontal | E35: Base | F35: Cinta | G35: Impresión | K35: Costo total | L35: Ganancia | M35: Total | N35: MP | O35: Ganan MP
D36: =Insumos!G21/6 -> 63.375 | E36: =Insumos!G42/6 -> 24.283333 | F36: =Insumos!AK11*16 -> 79.296 | G36: 50 | K36: =SUM(C36:J36) -> 216.95433 | L36: 500 | M36: =L36+K36 -> 716.95433 | N36: =(L36+K36)+((K36+L36)*(N34)) -> 853.17566 | O36: =N36-(N36*O34)-K36 -> 516.77673
N39: Transf
N40: =N36-(N36*R47) -> 853.17566
N41: G. Transf
N42: =(N40-(N40*O33))-K36 -> 585.03078
C59: enero
C60: Febrero
C61: marzo
C62: abril
C63: mayo
C64: junio | D64: 325493.64
C65: julio | D65: 410590.9 | E65: =D65-D64 -> 85097.26
C66: agosto | D66: 499098.12 | E66: =D66-D65 -> 88507.22
C67: septiembre | D67: 600123.73 | E67: =D67-D66 -> 101025.61
C68: Octubre | D68: 715714.53 | E68: =D68-D67 -> 115590.8
C69: Noviembre | D69: 831488.44 | E69: =D69-D68 -> 115773.91
C70: Diciembre | D70: 1451534 | E70: =D70-D69 -> 620045.56

Sheet Tejidos
N3: 0.1 | P3: 0.08
N4: 0.09 | P4: 0.06
N5: =N4+N3 -> 0.19 | P5: =P4+P3 -> 0.14 | S5: Descuento | T5: Descuento | U5: Descuento
B6: Infinito + Tarjeta + Flores | C6: Cord exter | D6: Cord medio | E6: Cordon nudo | F6: Tarjeta | G6: Bolsa | H6: Gancho | I6: Florcitas | K6: Costo total | L6: Ganancia | M6: Total | N6: MP | O6: MP | P6: Ganan MP | S6: 0.05 | T6: 0.1 | U6: 0.15
C7: =(Insumos!V5*70)*2 -> 128.87 | D7: =Insumos!V5*35 -> 32.2175 | E7: =Insumos!V5*15 -> 13.8075 | F7: =Insumos!G12/3 -> 135.66667 | G7: =Insumos!AA8 -> 34.66 | H7: =Insumos!V11 -> 329.9 | I7: 200 | K7: =SUM(C7:J7) -> 875.12167 | L7: 2000 | M7: =L7+K7 -> 2875.1217 | N7: =ROUND(O7/50,0)*50 -> 3400 | O7: =(L7+K7)+((K7+L7)*(N5)) -> 3421.3948 | P7: =N7-(N7*P5)-K7 -> 2048.8783 | S7: 50 | T7: 100 | U7: 200
S8: Costo total | T8: Costo total | U8: Costo total
S9: =K7*S7 -> 43756.083 | T9: =K7*T7 -> 87512.167 | U9: =K9*U7 -> 0
N10: Transf | S10: MP | T10: MP | U10: MP
N11: =N7-(N7*S18) -> 3060 | S11: =($N7*S7)-(($N7*S7)*S6) -> 161500 | T11: =($N7*T7)-(($N7*T7)*T6) -> 306000 | U11: =($N7*U7)-(($N7*U7)*U6) -> 578000
L12: , | N12: G. Transf | S12: =S11/S7 -> 3230 | T12: =T11/T7 -> 3060 | U12: =U11/U7 -> 2890
N13: =(N11-(N11*P4))-K7 -> 2001.2783 | S13: Ganancia MP | T13: Ganancia MP | U13: Ganancia MP
S14: =(S11-S9)-(S11*$P$27) -> 104823.92 | T14: =(T11-T9)-(T11*$P$27) -> 194007.83 | U14: =(U11-U9)-(U11*$P$27) -> 531760
S15: =S14/S7 -> 2096.4783 | T15: =T14/T7 -> 1940.0783 | U15: =U14/U7 -> 2658.8
S16: Transf | T16: Transf | U16: Transf
S17: =S11-(S11*S18) -> 145350 | T17: =T11-(T11*T18) -> 275400 | U17: =U11-(U11*U18) -> 520200
S18: 0.1 | T18: 0.1 | U18: 0.1
S19: =S17/S7 -> 2907 | T19: =T17/T7 -> 2754 | U19: =U17/U7 -> 2601
S20: Ganancia trans | T20: Ganancia trans | U20: Ganancia trans
S21: =S17-(S17*$P$26)-S9 -> 101593.92 | T21: =T17-(T17*$P$26)-T9 -> 187887.83 | U21: =U17-(U17*$P$26)-U9 -> 520200
S22: =S21/S7 -> 2031.8783 | T22: =T21/T7 -> 1878.8783 | U22: =U21/U7 -> 2601
N27: 0.1 | P27: 0.08
N28: 0.09 | P28: 0.06
N29: =N28+N27 -> 0.19 | P29: =P28+P27 -> 0.14 | S29: Descuento | T29: Descuento | U29: Descuento
B30: Colgante tejido + tarjeta | C30: Cord exter | D30: Cord medio | E30: Cordon nudo | F30: Tarjeta | G30: Bolsa | H30: Argolla | K30: Costo total | L30: Ganancia | M30: Total | N30: MP | O30: MP | P30: Ganan MP | S30: 0.05 | T30: 0.1 | U30: 0.15
C31: =C7 -> 128.87 | D31: =D7 -> 32.2175 | E31: =E7 -> 13.8075 | F31: =Insumos!G12/3 -> 135.66667 | G31: =Insumos!AA8 -> 34.66 | H31: =Insumos!V8 -> 51.85 | K31: =SUM(C31:J31) -> 397.07167 | L31: 1500 | M31: =L31+K31 -> 1897.0717 | N31: =ROUND(O31/50,0)*50 -> 2250 | O31: =(L31+K31)+((K31+L31)*(N29)) -> 2257.5153 | P31: =N31-(N31*P29)-K31 -> 1537.9283 | S31: 50 | T31: 100 | U31: 200
S32: Costo total | T32: Costo total | U32: Costo total
S33: =K31*S31 -> 19853.583 | T33: =K31*T31 -> 39707.167 | U33: =K33*U31 -> 0
N34: Transf | S34: MP | T34: MP | U34: MP
N35: =N31-(N31*S42) -> 2025 | S35: =($N31*S31)-(($N31*S31)*S30) -> 106875 | T35: =($N31*T31)-(($N31*T31)*T30) -> 202500 | U35: =($N31*U31)-(($N31*U31)*U30) -> 382500
N36: G. Transf | S36: =S35/S31 -> 2137.5 | T36: =T35/T31 -> 2025 | U36: =U35/U31 -> 1912.5
N37: =(N35-(N35*P28))-K31 -> 1506.4283 | S37: Ganancia MP | T37: Ganancia MP | U37: Ganancia MP
S38: =(S35-S33)-(S35*$P$27) -> 78471.417 | T38: =(T35-T33)-(T35*$P$27) -> 146592.83 | U38: =(U35-U33)-(U35*$P$27) -> 351900
S39: =S38/S31 -> 1569.4283 | T39: =T38/T31 -> 1465.9283 | U39: =U38/U31 -> 1759.5
S40: Transf | T40: Transf | U40: Transf
S41: =S35-(S35*S42) -> 96187.5 | T41: =T35-(T35*T42) -> 182250 | U41: =U35-(U35*U42) -> 344250
S42: 0.1 | T42: 0.1 | U42: 0.1
S43: =S41/S31 -> 1923.75 | T43: =T41/T31 -> 1822.5 | U43: =U41/U31 -> 1721.25
S44: Ganancia trans | T44: Ganancia trans | U44: Ganancia trans
S45: =S41-(S41*$P$26)-S33 -> 76333.917 | T45: =T41-(T41*$P$26)-T33 -> 142542.83 | U45: =U41-(U41*$P$26)-U33 -> 344250
S46: =S45/S31 -> 1526.6783 | T46: =T45/T31 -> 1425.4283 | U46: =U45/U31 -> 1721.25
N50: 0.1 | P50: 0.08
N51: 0.09 | P51: 0.06
N52: =N51+N50 -> 0.19 | P52: =P51+P50 -> 0.14 | S52: Descuento | T52: Descuento | U52: Descuento
B53: Colgante tejido base | C53: Cord exter | D53: Cord medio | E53: Cordon nudo | F53: Tarjeta | G53: Bolsa | H53: Argolla | K53: Costo total | L53: Ganancia | M53: Total | N53: MP | O53: MP | P53: Ganan MP | S53: 0.05 | T53: 0.1 | U53: 0.15
C54: =C31 -> 128.87 | D54: =D31 -> 32.2175 | E54: =E31 -> 13.8075 | F54: =Insumos!G12/20 -> 20.35 | G54: =Insumos!V14 -> 13.795 | H54: =H31 -> 51.85 | K54: =SUM(C54:J54) -> 260.89 | L54: 1500 | M54: =L54+K54 -> 1760.89 | N54: =ROUND(O54/50,0)*50 -> 2100 | O54: =(L54+K54)+((K54+L54)*(N52)) -> 2095.4591 | P54: =N54-(N54*P52)-K54 -> 1545.11 | S54: 50 | T54: 100 | U54: 200
S55: Costo total | T55: Costo total | U55: Costo total
S56: =K54*S54 -> 13044.5 | T56: =K54*T54 -> 26089 | U56: =K56*U54 -> 0
N57: Transf | S57: MP | T57: MP | U57: MP
N58: =N54-(N54*S65) -> 1890 | S58: =($N54*S54)-(($N54*S54)*S53) -> 99750 | T58: =($N54*T54)-(($N54*T54)*T53) -> 189000 | U58: =($N54*U54)-(($N54*U54)*U53) -> 357000
N59: G. Transf | S59: =S58/S54 -> 1995 | T59: =T58/T54 -> 1890 | U59: =U58/U54 -> 1785
N60: =(N58-(N58*P51))-K54 -> 1515.71 | S60: Ganancia MP | T60: Ganancia MP | U60: Ganancia MP
S61: =(S58-S56)-(S58*$P$27) -> 78725.5 | T61: =(T58-T56)-(T58*$P$27) -> 147791 | U61: =(U58-U56)-(U58*$P$27) -> 328440
S62: =S61/S54 -> 1574.51 | T62: =T61/T54 -> 1477.91 | U62: =U61/U54 -> 1642.2
S63: Transf | T63: Transf | U63: Transf
S64: =S58-(S58*S65) -> 89775 | T64: =T58-(T58*T65) -> 170100 | U64: =U58-(U58*U65) -> 321300
S65: 0.1 | T65: 0.1 | U65: 0.1
S66: =S64/S54 -> 1795.5 | T66: =T64/T54 -> 1701 | U66: =U64/U54 -> 1606.5
S67: Ganancia trans | T67: Ganancia trans | U67: Ganancia trans
S68: =S64-(S64*$P$26)-S56 -> 76730.5 | T68: =T64-(T64*$P$26)-T56 -> 144011 | U68: =U64-(U64*$P$26)-U56 -> 321300
S69: =S68/S54 -> 1534.61 | T69: =T68/T54 -> 1440.11 | U69: =U68/U54 -> 1606.5

Sheet Georgalos
C3: Georgalos | L3: 0.1 | N3: 0.08
L4: 0.09 | N4: 0.06
L5: =L4+L3 -> 0.19 | N5: =N4+N3 -> 0.14 | P5: Descuento | Q5: Descuento | R5: Descuento | S5: Descuento | T5: Descuento | U5: Descuento
A6: 2 | B6: Caja de 2 | C6: Choco | D6: Eti choco | E6: Eti caja | F6: Caja | G6: Extra Con Foil | I6: Costo total | J6: Ganancia | K6: Total | L6: MP | M6: MP | N6: Ganan MP | P6: 0 | Q6: 0.05 | R6: 0.07 | S6: 0.09 | T6: 0.11 | U6: 0.13
C7: =Insumos!C16*2 -> 782.4 | D7: =(Insumos!G6/5) -> 47.984 | E7: =Insumos!G6/6 -> 39.986667 | F7: =Insumos!N36 -> 365 | G7: =Insumos!G15/5 -> 58.4 | I7: =SUM(B7:H7) -> 1293.7707 | J7: =K7-I7 -> 2587.5413 | K7: =I7*3 -> 3881.312 | L7: =ROUND(M7/50,0)*50 -> 4600 | M7: =(J7+I7)+((I7+J7)*(L5)) -> 4618.7613 | N7: =(L7-(L7*N5))-I7 -> 2662.2293 | P7: 50 | Q7: 100 | R7: 200 | S7: 500 | T7: 1000 | U7: 2000
P8: Costo total | Q8: Costo total | R8: Costo total | S8: Costo total | T8: Costo total | U8: Costo total
B9: 100 | F9: =Insumos!N39 -> 312.075 | I9: =C7+D7+E7+F9 -> 1182.4457 | K9: =I9+J7 -> 3769.987 | P9: =I7*P7 -> 64688.533 | Q9: =I9*Q7 -> 118244.57 | R9: =$I$9*R7 -> 236489.13 | S9: =$I$9*S7 -> 591222.83 | T9: =$I$9*T7 -> 1182445.7 | U9: =$I$9*U7 -> 2364891.3
L10: Transf | P10: MP | Q10: MP | R10: MP | S10: MP | T10: MP | U10: MP
L11: =L7-(L7*P18) -> 4140 | P11: =($L7*P7)-(($L7*P7)*P6) -> 230000 | Q11: =($L7*Q7)-(($L7*Q7)*Q6) -> 437000 | R11: =($L7*R7)-(($L7*R7)*R6) -> 855600 | S11: =($L7*S7)-(($L7*S7)*S6) -> 2093000 | T11: =($L7*T7)-(($L7*T7)*T6) -> 4094000 | U11: =($L7*U7)-(($L7*U7)*U6) -> 8004000
L12: G. Transf | P12: =P11/P7 -> 4600 | Q12: =Q11/Q7 -> 4370 | R12: =R11/R7 -> 4278 | S12: =S11/S7 -> 4186 | T12: =T11/T7 -> 4094 | U12: =U11/U7 -> 4002
L13: =(L11-(L11*N4))-I7 -> 2597.8293 | P13: G. MP | Q13: G. MP | R13: G. MP | S13: G. MP | T13: G. MP | U13: G. MP
P14: =(P11-P9)-(P11*$N$5) -> 133111.47 | Q14: =(Q11-Q9)-(Q11*$N$5) -> 257575.43 | R14: =(R11-R9)-(R11*$N$5) -> 499326.87 | S14: =(S11-S9)-(S11*$N$5) -> 1208757.2 | T14: =(T11-T9)-(T11*$N$5) -> 2338394.3 | U14: =(U11-U9)-(U11*$N$5) -> 4518548.7
P15: =P14/P7 -> 2662.2293 | Q15: =Q14/Q7 -> 2575.7543 | R15: =R14/R7 -> 2496.6343 | S15: =S14/S7 -> 2417.5143 | T15: =T14/T7 -> 2338.3943 | U15: =U14/U7 -> 2259.2743
P16: Transf | Q16: Transf | R16: Transf | S16: Transf | T16: Transf | U16: Transf
P17: =P11-(P11*P18) -> 207000 | Q17: =Q11-(Q11*Q18) -> 393300 | R17: =R11-(R11*R18) -> 770040 | S17: =S11-(S11*S18) -> 1883700 | T17: =T11-(T11*T18) -> 3684600 | U17: =U11-(U11*U18) -> 7203600
P18: 0.1 | Q18: 0.1 | R18: 0.1 | S18: 0.1 | T18: 0.1 | U18: 0.1
P19: =P17/P7 -> 4140 | Q19: =Q17/Q7 -> 3933 | R19: =R17/R7 -> 3850.2 | S19: =S17/S7 -> 3767.4 | T19: =T17/T7 -> 3684.6 | U19: =U17/U7 -> 3601.8
P20: G. Transf | Q20: G. Transf | R20: G. Transf | S20: G. Transf | T20: G. Transf | U20: G. Transf
P21: =P17-(P17*$N$4)-P9 -> 129891.47 | Q21: =Q17-(Q17*$N$4)-Q9 -> 251457.43 | R21: =R17-(R17*$N$4)-R9 -> 487348.47 | S21: =S17-(S17*$N$4)-S9 -> 1179455.2 | T21: =T17-(T17*$N$4)-T9 -> 2281078.3 | U21: =U17-(U17*$N$4)-U9 -> 4406492.7
P22: =P21/P7 -> 2597.8293 | Q22: =Q21/Q7 -> 2514.5743 | R22: =R21/R7 -> 2436.7423 | S22: =S21/S7 -> 2358.9103 | T22: =T21/T7 -> 2281.0783 | U22: =U21/U7 -> 2203.2463
L27: 0.1 | N27: 0.08
L28: 0.09 | N28: 0.06
L29: =L28+L27 -> 0.19 | N29: =N28+N27 -> 0.14 | P29: Descuento | Q29: Descuento | R29: Descuento | S29: Descuento | T29: Descuento | U29: Descuento
B30: Caja de 2 Moño | C30: Choco | D30: Eti choco | E30: Eti Caja | F30: Caja | G30: Moño | I30: Costo total | J30: Ganancia | K30: Total | L30: MP | M30: MP | N30: Ganan MP | P30: 0 | Q30: 0.05 | R30: 0.07 | S30: 0.09 | T30: 0.11 | U30: 0.13
C31: =C7 -> 782.4 | D31: =D7 -> 47.984 | E31: =E7 -> 39.986667 | F31: =F7 -> 365 | G31: =Insumos!R9*70 -> 132.16 | I31: =SUM(B31:H31) -> 1367.5307 | J31: =K31-I31 -> 3008.5675 | K31: =I31*3.2 -> 4376.0981 | L31: =ROUND(M31/50,0)*50 -> 5200 | M31: =(J31+I31)+((I31+J31)*(L29)) -> 5207.5568 | N31: =(L31-(L31*N29))-I31 -> 3104.4693 | P31: 50 | Q31: 100 | R31: 200 | S31: 500 | T31: 1000 | U31: 2000
P32: Costo total | Q32: Costo total | R32: Costo total | S32: Costo total | T32: Costo total | U32: Costo total
B33: 100 | C33: =C31 -> 782.4 | D33: =D31 -> 47.984 | E33: =E31 -> 39.986667 | F33: =Insumos!N39 -> 312.075 | G33: =G31 -> 132.16 | I33: =C33+D33+E33+F33+G33 -> 1314.6057 | K33: =I33+J31 -> 4323.1731 | P33: =I31*P31 -> 68376.533 | Q33: =I33*Q31 -> 131460.57 | R33: =$I$33*R31 -> 262921.13 | S33: =$I$33*S31 -> 657302.83 | T33: =$I$33*T31 -> 1314605.7 | U33: =$I$33*U31 -> 2629211.3
L34: Transf | P34: MP | Q34: MP | R34: MP | S34: MP | T34: MP | U34: MP
L35: =L31-(L31*Q42) -> 4680 | P35: =($L31*P31)-(($L31*P31)*P30) -> 260000 | Q35: =($L31*Q31)-(($L31*Q31)*Q30) -> 494000 | R35: =($L31*R31)-(($L31*R31)*R30) -> 967200 | S35: =($L31*S31)-(($L31*S31)*S30) -> 2366000 | T35: =($L31*T31)-(($L31*T31)*T30) -> 4628000 | U35: =($L31*U31)-(($L31*U31)*U30) -> 9048000
L36: G. Transf | P36: =P35/P31 -> 5200 | Q36: =Q35/Q31 -> 4940 | R36: =R35/R31 -> 4836 | S36: =S35/S31 -> 4732 | T36: =T35/T31 -> 4628 | U36: =U35/U31 -> 4524
L37: =(L35-(L35*N28))-I31 -> 3031.6693 | P37: G. MP | Q37: G. MP | R37: G. MP | S37: G. MP | T37: G. MP | U37: G. MP
P38: =(P35-P33)-(P35*$N$5) -> 155223.47 | Q38: =(Q35-Q33)-(Q35*$N$5) -> 293379.43 | R38: =(R35-R33)-(R35*$N$5) -> 568870.87 | S38: =(S35-S33)-(S35*$N$5) -> 1377457.2 | T38: =(T35-T33)-(T35*$N$5) -> 2665474.3 | U38: =(U35-U33)-(U35*$N$5) -> 5152068.7
P39: =P38/P31 -> 3104.4693 | Q39: =Q38/Q31 -> 2933.7943 | R39: =R38/R31 -> 2844.3543 | S39: =S38/S31 -> 2754.9143 | T39: =T38/T31 -> 2665.4743 | U39: =U38/U31 -> 2576.0343
P40: Transf | Q40: Transf | R40: Transf | S40: Transf | T40: Transf | U40: Transf
P41: =P35-(P35*P42) -> 234000 | Q41: =Q35-(Q35*Q42) -> 444600 | R41: =R35-(R35*R42) -> 870480 | S41: =S35-(S35*S42) -> 2129400 | T41: =T35-(T35*T42) -> 4165200 | U41: =U35-(U35*U42) -> 8143200
P42: 0.1 | Q42: 0.1 | R42: 0.1 | S42: 0.1 | T42: 0.1 | U42: 0.1
P43: =P41/P31 -> 4680 | Q43: =Q41/Q31 -> 4446 | R43: =R41/R31 -> 4352.4 | S43: =S41/S31 -> 4258.8 | T43: =T41/T31 -> 4165.2 | U43: =U41/U31 -> 4071.6
P44: G. Transf | Q44: G. Transf | R44: G. Transf | S44: G. Transf | T44: G. Transf | U44: G. Transf
P45: =P41-(P41*$N$4)-P33 -> 151583.47 | Q45: =Q41-(Q41*$N$4)-Q33 -> 286463.43 | R45: =R41-(R41*$N$4)-R33 -> 555330.07 | S45: =S41-(S41*$N$4)-S33 -> 1344333.2 | T45: =T41-(T41*$N$4)-T33 -> 2600682.3 | U45: =U41-(U41*$N$4)-U33 -> 5025396.7
P46: =P45/P31 -> 3031.6693 | Q46: =Q45/Q31 -> 2864.6343 | R46: =R45/R31 -> 2776.6503 | S46: =S45/S31 -> 2688.6663 | T46: =T45/T31 -> 2600.6823 | U46: =U45/U31 -> 2512.6983
L49: 0.1 | N49: 0.08
L50: 0.09 | N50: 0.06
L51: =L50+L49 -> 0.19 | N51: =N50+N49 -> 0.14 | P51: Descuento | Q51: Descuento | R51: Descuento | S51: Descuento | T51: Descuento | U51: Descuento
B52: Choco Suelto | C52: Choco | D52: Eti choco | I52: Costo total | J52: Ganancia | K52: Total | L52: MP | M52: MP | N52: Ganan MP | P52: 0 | Q52: 0.05 | R52: 0.07 | S52: 0.09 | T52: 0.11 | U52: 0.13
C53: =Insumos!C16 -> 391.2 | D53: =Insumos!G6/10 -> 23.992 | I53: =SUM(C53:H53) -> 415.192 | J53: 350 | K53: =J53+I53 -> 765.192 | L53: =ROUND(M53/50,0)*50 -> 900 | M53: =(J53+I53)+((I53+J53)*(L51)) -> 910.57848 | N53: =(L53-(L53*N51))-I53 -> 358.808 | P53: 50 | Q53: 100 | R53: 200 | S53: 500 | T53: 1000 | U53: 2000
P54: Costo total | Q54: Costo total | R54: Costo total | S54: Costo total | T54: Costo total | U54: Costo total
P55: =I53*P53 -> 20759.6 | Q55: =I53*Q53 -> 41519.2 | R55: =$I$53*R53 -> 83038.4 | S55: =$I$53*S53 -> 207596 | T55: =$I$53*T53 -> 415192 | U55: =$I$53*U53 -> 830384
L56: Transf | P56: MP | Q56: MP | R56: MP | S56: MP | T56: MP | U56: MP
L57: =L53-(L53*Q64) -> 810 | P57: =($L53*P53)-(($L53*P53)*P52) -> 45000 | Q57: =($L53*Q53)-(($L53*Q53)*Q52) -> 85500 | R57: =($L53*R53)-(($L53*R53)*R52) -> 167400 | S57: =($L53*S53)-(($L53*S53)*S52) -> 409500 | T57: =($L53*T53)-(($L53*T53)*T52) -> 801000 | U57: =($L53*U53)-(($L53*U53)*U52) -> 1566000
L58: G. Transf | P58: =P57/P53 -> 900 | Q58: =Q57/Q53 -> 855 | R58: =R57/R53 -> 837 | S58: =S57/S53 -> 819 | T58: =T57/T53 -> 801 | U58: =U57/U53 -> 783
L59: =(L57-(L57*N50))-I53 -> 346.208 | P59: G. MP | Q59: G. MP | R59: G. MP | S59: G. MP | T59: G. MP | U59: G. MP
P60: =(P57-P55)-(P57*$N$5) -> 17940.4 | Q60: =(Q57-Q55)-(Q57*$N$5) -> 32010.8 | R60: =(R57-R55)-(R57*$N$5) -> 60925.6 | S60: =(S57-S55)-(S57*$N$5) -> 144574 | T60: =(T57-T55)-(T57*$N$5) -> 273668 | U60: =(U57-U55)-(U57*$N$5) -> 516376
P61: =P60/P53 -> 358.808 | Q61: =Q60/Q53 -> 320.108 | R61: =R60/R53 -> 304.628 | S61: =S60/S53 -> 289.148 | T61: =T60/T53 -> 273.668 | U61: =U60/U53 -> 258.188
P62: Transf | Q62: Transf | R62: Transf | S62: Transf | T62: Transf | U62: Transf
P63: =P57-(P57*P64) -> 40500 | Q63: =Q57-(Q57*Q64) -> 76950 | R63: =R57-(R57*R64) -> 150660 | S63: =S57-(S57*S64) -> 368550 | T63: =T57-(T57*T64) -> 720900 | U63: =U57-(U57*U64) -> 1409400
P64: 0.1 | Q64: 0.1 | R64: 0.1 | S64: 0.1 | T64: 0.1 | U64: 0.1
P65: =P63/P53 -> 810 | Q65: =Q63/Q53 -> 769.5 | R65: =R63/R53 -> 753.3 | S65: =S63/S53 -> 737.1 | T65: =T63/T53 -> 720.9 | U65: =U63/U53 -> 704.7
P66: G. Transf | Q66: G. Transf | R66: G. Transf | S66: G. Transf | T66: G. Transf | U66: G. Transf
P67: =P63-(P63*$N$4)-P55 -> 17310.4 | Q67: =Q63-(Q63*$N$4)-Q55 -> 30813.8 | R67: =R63-(R63*$N$4)-R55 -> 58582 | S67: =S63-(S63*$N$4)-S55 -> 138841 | T67: =T63-(T63*$N$4)-T55 -> 262454 | U67: =U63-(U63*$N$4)-U55 -> 494452
P68: =P67/P53 -> 346.208 | Q68: =Q67/Q53 -> 308.138 | R68: =R67/R53 -> 292.91 | S68: =S67/S53 -> 277.682 | T68: =T67/T53 -> 262.454 | U68: =U67/U53 -> 247.226

Sheet Ventas Web
W1: 0.15
A2: ESTADO | B2: Fecha | C2: Procedencia | D2: $ venta ML | E2: Nombre | G2: Telefono | H2: Producto | I2: Cantidad | J2: Modo pago | L2: Venta | M2: FACTURÓ | N2: Envio | P2: Costo | Q2: Comision MP | R2: 1er Impuesto 0,06 | S2: 2do impuesto 2% | T2: Ganancia | U2: AUTO | V2: MONOTRIBUTO | W2: BRISA
C3: MELI | E3: Diciembre | V3: =T3*0.05 -> 0 | X3: =SUM(W5:W22) -> 13214.279 | Y3: =X3+'Ventas MELI'!U3 -> 24232.148
C4: WEB | D4: Completado | E4: Ariela fefer | H4: Choco suelto +200 | I4: 200 | K4: DECOYA | L4: 112860 | M4: 122860 | N4: =M4-L4 -> 10000 | P4: =_xlfn.XLOOKUP(H4, AA:AA, AB:AB) * I4 -> 58800 | R4: =M4*0.0006 -> 73.716 | S4: =M4*0.02 -> 2457.2 | T4: =L4-P4-Q4-R4-S4 -> 51529.084 | U4: =IF(K4="CORREO",0,N4) -> 10000 | V4: =T4*0.05 -> 2576.4542 | W4: =T4*0.05 -> 2576.4542
C5: WEB | E5: Anabella Silvia chal | I5: 1 | K5: CORREO | L5: 15000 | M5: 15000 | N5: =M5-L5 -> 0 | P5: 11000 | R5: =M5*0.0006 -> 9 | S5: =M5*0.02 -> 300 | T5: =L5-P5-Q5-R5-S5 -> 3691 | U5: =IF(K5="CORREO",0,N5) -> 0 | V5: =T5*0.05 -> 184.55 | W5: =T5*0.05 -> 184.55 | AD5: Credito | AE5: Transf
C6: WEB | E6: Daniela Gomez | H6: Mini Recuerdo | I6: 20 | K6: CORREO | L6: 17100 | M6: 28400 | N6: =M6-L6 -> 11300 | P6: =_xlfn.XLOOKUP(H6, AA:AA, AB:AB) * I6 -> 6540 | R6: =M6*0.0006 -> 17.04 | S6: =M6*0.02 -> 568 | T6: =L6-P6-Q6-R6-S6 -> 9974.96 | U6: =IF(K6="CORREO",0,N6) -> 0 | V6: =T6*0.05 -> 498.748 | W6: =T6*0.05 -> 498.748 | AA6: Choco Suelto | AB6: 294 | AD6: 660 | AE6: =AD6-(AD6*0.1) -> 594
E7: Florencia sufi | H7: Mini Recuerdo | I7: 110 | K7: RETIRO | L7: 87318 | M7: 87318 | N7: =M7-L7 -> 0 | P7: =_xlfn.XLOOKUP(H7, AA:AA, AB:AB) * I7 -> 35970 | R7: =M7*0.0006 -> 52.3908 | S7: =M7*0.02 -> 1746.36 | T7: =L7-P7-Q7-R7-S7 -> 49549.249 | U7: =IF(K7="CORREO",0,N7) -> 0 | V7: =T7*0.05 -> 2477.4625 | W7: =T7*0.05 -> 2477.4625
E8: Florencia Franco | H8: Choco Suelto | I8: 50 | K8: DECOYA | L8: 29700 | M8: 39700 | N8: =M8-L8 -> 10000 | P8: =_xlfn.XLOOKUP(H8, AA:AA, AB:AB) * I8 -> 14700 | R8: =M8*0.0006 -> 23.82 | S8: =M8*0.02 -> 794 | T8: =L8-P8-Q8-R8-S8 -> 14182.18 | U8: =IF(K8="CORREO",0,N8) -> 10000 | V8: =T8*0.05 -> 709.109 | W8: =T8*0.05 -> 709.109 | AA8: Mini Recuerdo | AB8: 327 | AD8: 950 | AE8: =AD8-(AD8*0.1) -> 855
E9: Carina Manzano | H9: D6 Gold | I9: 55 | L9: 263340 | M9: 273340 | N9: =M9-L9 -> 10000 | P9: =_xlfn.XLOOKUP(H9, AA:AA, AB:AB) * I9 -> 131164 | R9: =M9*0.0006 -> 164.004 | S9: =M9*0.02 -> 5466.8 | T9: =L9-P9-Q9-R9-S9 -> 126545.2 | U9: =IF(K9="CORREO",0,N9) -> 10000 | V9: =T9*0.05 -> 6327.2598 | W9: =T9*0.05 -> 6327.2598 | AA9: Tarjeta | AB9: 330 | AD9: 980 | AE9: =AD9-(AD9*0.1) -> 882
L10: =IFERROR(IF(J10="Transferencia",_xlfn.XLOOKUP(H10,$AA:$AA,$AE:$AE)*I10,_xlfn.XLOOKUP(H10,$AA:$AA,$AD:$AD)*I10),0) -> 0 | N10: =M10-L10 -> 0 | P10: =_xlfn.XLOOKUP(H10, AA:AA, AB:AB) * I10 -> 0 | R10: =M10*0.0006 -> 0 | S10: =M10*0.02 -> 0 | T10: =L10-P10-Q10-R10-S10 -> 0 | U10: =IF(K10="CORREO",0,N10) -> 0 | V10: =T10*0.05 -> 0 | W10: =T10*0.05 -> 0 | AA10: Cajita de 4 | AB10: 1443.5 | AD10: 3000 | AE10: =AD10-(AD10*0.1) -> 2700
L11: =IFERROR(IF(J11="Transferencia",_xlfn.XLOOKUP(H11,$AA:$AA,$AE:$AE)*I11,_xlfn.XLOOKUP(H11,$AA:$AA,$AD:$AD)*I11),0) -> 0 | N11: =M11-L11 -> 0 | P11: =_xlfn.XLOOKUP(H11, AA:AA, AB:AB) * I11 -> 0 | R11: =M11*0.0006 -> 0 | S11: =M11*0.02 -> 0 | T11: =L11-P11-Q11-R11-S11 -> 0 | U11: =IF(K11="CORREO",0,N11) -> 0 | V11: =T11*0.05 -> 0 | W11: =T11*0.05 -> 0 | AA11: Cajita de 4 deluxe | AB11: 1499.86 | AD11: 3100 | AE11: =AD11-(AD11*0.1) -> 2790
L12: =IFERROR(IF(J12="Transferencia",_xlfn.XLOOKUP(H12,$AA:$AA,$AE:$AE)*I12,_xlfn.XLOOKUP(H12,$AA:$AA,$AD:$AD)*I12),0) -> 0 | N12: =M12-L12 -> 0 | P12: =_xlfn.XLOOKUP(H12, AA:AA, AB:AB) * I12 -> 0 | R12: =M12*0.0006 -> 0 | S12: =M12*0.02 -> 0 | T12: =L12-P12-Q12-R12-S12 -> 0 | U12: =IF(K12="CORREO",0,N12) -> 0 | V12: =T12*0.05 -> 0 | W12: =T12*0.05 -> 0 | AA12: D6 Classic | AB12: 2263.63 | AD12: 4900 | AE12: =AD12-(AD12*0.1) -> 4410
H13: Mini Recuerdo | I13: 100 | J13: Credito | K13: CORREO | L13: =IFERROR(IF(J13="Transferencia",_xlfn.XLOOKUP(H13,$AA:$AA,$AE:$AE)*I13,_xlfn.XLOOKUP(H13,$AA:$AA,$AD:$AD)*I13),0) -> 95000 | M13: 110000 | N13: =M13-L13 -> 15000 | P13: =_xlfn.XLOOKUP(H13, AA:AA, AB:AB) * I13 -> 32700 | R13: =L13*0.0006 -> 57 | S13: =L13*0.02 -> 1900 | T13: =L13-P13-Q13-R13-S13 -> 60343 | U13: =IF(K13="CORREO",0,N13) -> 0 | V13: =T13*0.05 -> 3017.15 | W13: =T13*0.05 -> 3017.15 | AA13: D6 Deluxe | AB13: 2422 | AD13: 5200 | AE13: =AD13-(AD13*0.1) -> 4680
J14: Transferencia | K14: CORREO | L14: =IFERROR(IF(J14="Transferencia",_xlfn.XLOOKUP(H14,$AA:$AA,$AE:$AE)*I14,_xlfn.XLOOKUP(H14,$AA:$AA,$AD:$AD)*I14),0) -> 0 | N14: =M14-L14 -> 0 | P14: =_xlfn.XLOOKUP(H14, AA:AA, AB:AB) * I14 -> 0 | R14: =M14*0.0006 -> 0 | S14: =M14*0.02 -> 0 | T14: =L14-P14-Q14-R14-S14 -> 0 | U14: =IF(K14="CORREO",0,N14) -> 0 | V14: =T14*0.05 -> 0 | W14: =T14*0.05 -> 0 | AA14: D6 Gold | AB14: 2384.8 | AD14: 5600 | AE14: =AD14-(AD14*0.1) -> 5040
L15: =IFERROR(IF(J15="Transferencia",_xlfn.XLOOKUP(H15,$AA:$AA,$AE:$AE)*I15,_xlfn.XLOOKUP(H15,$AA:$AA,$AD:$AD)*I15),0) -> 0 | N15: =M15-L15 -> 0 | P15: =_xlfn.XLOOKUP(H15, AA:AA, AB:AB) * I15 -> 0 | R15: =M15*0.0006 -> 0 | S15: =M15*0.02 -> 0 | T15: =L15-P15-Q15-R15-S15 -> 0 | U15: =IF(K15="CORREO",0,N15) -> 0 | V15: =T15*0.05 -> 0 | W15: =T15*0.05 -> 0 | AA15: Black | AB15: 2610 | AD15: 6100 | AE15: =AD15-(AD15*0.1) -> 5490
L16: =IFERROR(IF(J16="Transferencia",_xlfn.XLOOKUP(H16,$AA:$AA,$AE:$AE)*I16,_xlfn.XLOOKUP(H16,$AA:$AA,$AD:$AD)*I16),0) -> 0 | N16: =M16-L16 -> 0 | P16: =_xlfn.XLOOKUP(H16, AA:AA, AB:AB) * I16 -> 0 | R16: =M16*0.0006 -> 0 | S16: =M16*0.02 -> 0 | T16: =L16-P16-Q16-R16-S16 -> 0 | U16: =IF(K16="CORREO",0,N16) -> 0 | V16: =T16*0.05 -> 0 | W16: =T16*0.05 -> 0 | AA16: Señaladores | AB16: 440.7 | AD16: 1100 | AE16: =AD16-(AD16*0.1) -> 990
L17: =IFERROR(IF(J17="Transferencia",_xlfn.XLOOKUP(H17,$AA:$AA,$AE:$AE)*I17,_xlfn.XLOOKUP(H17,$AA:$AA,$AD:$AD)*I17),0) -> 0 | N17: =M17-L17 -> 0 | P17: =_xlfn.XLOOKUP(H17, AA:AA, AB:AB) * I17 -> 0 | R17: =M17*0.0006 -> 0 | S17: =M17*0.02 -> 0 | T17: =L17-P17-Q17-R17-S17 -> 0 | U17: =IF(K17="CORREO",0,N17) -> 0 | V17: =T17*0.05 -> 0 | W17: =T17*0.05 -> 0 | AA17: D2 | AB17: 1293 | AD17: 2850 | AE17: =AD17-(AD17*0.1) -> 2565
L18: =IFERROR(IF(J18="Transferencia",_xlfn.XLOOKUP(H18,$AA:$AA,$AE:$AE)*I18,_xlfn.XLOOKUP(H18,$AA:$AA,$AD:$AD)*I18),0) -> 0 | N18: =M18-L18 -> 0 | P18: =_xlfn.XLOOKUP(H18, AA:AA, AB:AB) * I18 -> 0 | R18: =M18*0.0006 -> 0 | S18: =M18*0.02 -> 0 | T18: =L18-P18-Q18-R18-S18 -> 0 | U18: =IF(K18="CORREO",0,N18) -> 0 | V18: =T18*0.05 -> 0 | W18: =T18*0.05 -> 0 | AA18: D2 moño | AB18: 1367 | AD18: 3500 | AE18: =AD18-(AD18*0.1) -> 3150
L19: =IFERROR(IF(J19="Transferencia",_xlfn.XLOOKUP(H19,$AA:$AA,$AE:$AE)*I19,_xlfn.XLOOKUP(H19,$AA:$AA,$AD:$AD)*I19),0) -> 0 | N19: =M19-L19 -> 0 | P19: =_xlfn.XLOOKUP(H19, AA:AA, AB:AB) * I19 -> 0 | R19: =M19*0.0006 -> 0 | S19: =M19*0.02 -> 0 | T19: =L19-P19-Q19-R19-S19 -> 0 | U19: =IF(K19="CORREO",0,N19) -> 0 | V19: =T19*0.05 -> 0 | W19: =T19*0.05 -> 0 | AA19: Vela 100cc | AD19: 2600 | AE19: =AD19-(AD19*0.1) -> 2340
L20: =IFERROR(IF(J20="Transferencia",_xlfn.XLOOKUP(H20,$AA:$AA,$AE:$AE)*I20,_xlfn.XLOOKUP(H20,$AA:$AA,$AD:$AD)*I20),0) -> 0 | N20: =M20-L20 -> 0 | P20: =_xlfn.XLOOKUP(H20, AA:AA, AB:AB) * I20 -> 0 | R20: =M20*0.0006 -> 0 | S20: =M20*0.02 -> 0 | T20: =L20-P20-Q20-R20-S20 -> 0 | U20: =IF(K20="CORREO",0,N20) -> 0 | V20: =T20*0.05 -> 0 | W20: =T20*0.05 -> 0 | AA20: Vela 200cc | AE20: =AD20-(AD20*0.1) -> 0
L21: =IFERROR(IF(J21="Transferencia",_xlfn.XLOOKUP(H21,$AA:$AA,$AE:$AE)*I21,_xlfn.XLOOKUP(H21,$AA:$AA,$AD:$AD)*I21),0) -> 0 | N21: =M21-L21 -> 0 | P21: =_xlfn.XLOOKUP(H21, AA:AA, AB:AB) * I21 -> 0 | R21: =M21*0.0006 -> 0 | S21: =M21*0.02 -> 0 | T21: =L21-P21-Q21-R21-S21 -> 0 | U21: =IF(K21="CORREO",0,N21) -> 0 | V21: =T21*0.05 -> 0 | W21: =T21*0.05 -> 0 | AA21: caja 44 chocos | AB21: 12512 | AD21: 31000 | AE21: =AD21-(AD21*0.1) -> 27900
L22: =IFERROR(IF(J22="Transferencia",_xlfn.XLOOKUP(H22,$AA:$AA,$AE:$AE)*I22,_xlfn.XLOOKUP(H22,$AA:$AA,$AD:$AD)*I22),0) -> 0 | N22: =M22-L22 -> 0 | P22: =_xlfn.XLOOKUP(H22, AA:AA, AB:AB) * I22 -> 0 | R22: =M22*0.0006 -> 0 | S22: =M22*0.02 -> 0 | T22: =L22-P22-Q22-R22-S22 -> 0 | U22: =IF(K22="CORREO",0,N22) -> 0 | V22: =T22*0.05 -> 0 | W22: =T22*0.05 -> 0 | AA22: Choco Suelto +200 | AB22: 294 | AD22: =AD6-(AD6*0.05) -> 627 | AE22: =AE6-(AE6*0.05) -> 564.3
L23: =IFERROR(IF(J23="Transferencia",_xlfn.XLOOKUP(H23,$AA:$AA,$AE:$AE)*I23,_xlfn.XLOOKUP(H23,$AA:$AA,$AD:$AD)*I23),0) -> 0 | N23: =M23-L23 -> 0 | P23: =_xlfn.XLOOKUP(H23, AA:AA, AB:AB) * I23 -> 0 | R23: =M23*0.0006 -> 0 | S23: =M23*0.02 -> 0 | T23: =L23-P23-Q23-R23-S23 -> 0 | U23: =IF(K23="CORREO",0,N23) -> 0 | V23: =T23*0.05 -> 0 | W23: =T23*0.05 -> 0
L24: =IFERROR(IF(J24="Transferencia",_xlfn.XLOOKUP(H24,$AA:$AA,$AE:$AE)*I24,_xlfn.XLOOKUP(H24,$AA:$AA,$AD:$AD)*I24),0) -> 0 | N24: =M24-L24 -> 0 | P24: =_xlfn.XLOOKUP(H24, AA:AA, AB:AB) * I24 -> 0 | R24: =M24*0.0006 -> 0 | S24: =M24*0.02 -> 0 | T24: =L24-P24-Q24-R24-S24 -> 0 | U24: =IF(K24="CORREO",0,N24) -> 0 | V24: =T24*0.05 -> 0 | W24: =T24*0.05 -> 0
L25: =IFERROR(IF(J25="Transferencia",_xlfn.XLOOKUP(H25,$AA:$AA,$AE:$AE)*I25,_xlfn.XLOOKUP(H25,$AA:$AA,$AD:$AD)*I25),0) -> 0 | N25: =M25-L25 -> 0 | P25: =_xlfn.XLOOKUP(H25, AA:AA, AB:AB) * I25 -> 0 | R25: =M25*0.0006 -> 0 | S25: =M25*0.02 -> 0 | T25: =L25-P25-Q25-R25-S25 -> 0 | U25: =IF(K25="CORREO",0,N25) -> 0 | V25: =T25*0.05 -> 0 | W25: =T25*0.05 -> 0
L26: =IFERROR(IF(J26="Transferencia",_xlfn.XLOOKUP(H26,$AA:$AA,$AE:$AE)*I26,_xlfn.XLOOKUP(H26,$AA:$AA,$AD:$AD)*I26),0) -> 0 | N26: =M26-L26 -> 0 | P26: =_xlfn.XLOOKUP(H26, AA:AA, AB:AB) * I26 -> 0 | R26: =M26*0.0006 -> 0 | S26: =M26*0.02 -> 0 | T26: =L26-P26-Q26-R26-S26 -> 0 | U26: =IF(K26="CORREO",0,N26) -> 0 | V26: =T26*0.05 -> 0 | W26: =T26*0.05 -> 0
L27: =IFERROR(IF(J27="Transferencia",_xlfn.XLOOKUP(H27,$AA:$AA,$AE:$AE)*I27,_xlfn.XLOOKUP(H27,$AA:$AA,$AD:$AD)*I27),0) -> 0 | N27: =M27-L27 -> 0 | P27: =_xlfn.XLOOKUP(H27, AA:AA, AB:AB) * I27 -> 0 | R27: =M27*0.0006 -> 0 | S27: =M27*0.02 -> 0 | T27: =L27-P27-Q27-R27-S27 -> 0 | U27: =IF(K27="CORREO",0,N27) -> 0 | V27: =T27*0.05 -> 0 | W27: =T27*0.05 -> 0
L28: =IFERROR(IF(J28="Transferencia",_xlfn.XLOOKUP(H28,$AA:$AA,$AE:$AE)*I28,_xlfn.XLOOKUP(H28,$AA:$AA,$AD:$AD)*I28),0) -> 0 | N28: =M28-L28 -> 0 | P28: =_xlfn.XLOOKUP(H28, AA:AA, AB:AB) * I28 -> 0 | R28: =M28*0.0006 -> 0 | S28: =M28*0.02 -> 0 | T28: =L28-P28-Q28-R28-S28 -> 0 | U28: =IF(K28="CORREO",0,N28) -> 0 | V28: =T28*0.05 -> 0 | W28: =T28*0.05 -> 0
L29: =IFERROR(IF(J29="Transferencia",_xlfn.XLOOKUP(H29,$AA:$AA,$AE:$AE)*I29,_xlfn.XLOOKUP(H29,$AA:$AA,$AD:$AD)*I29),0) -> 0 | N29: =M29-L29 -> 0 | P29: =_xlfn.XLOOKUP(H29, AA:AA, AB:AB) * I29 -> 0 | R29: =M29*0.0006 -> 0 | S29: =M29*0.02 -> 0 | T29: =L29-P29-Q29-R29-S29 -> 0 | U29: =IF(K29="CORREO",0,N29) -> 0 | V29: =T29*0.05 -> 0 | W29: =T29*0.05 -> 0
L30: =IFERROR(IF(J30="Transferencia",_xlfn.XLOOKUP(H30,$AA:$AA,$AE:$AE)*I30,_xlfn.XLOOKUP(H30,$AA:$AA,$AD:$AD)*I30),0) -> 0 | N30: =M30-L30 -> 0 | P30: =_xlfn.XLOOKUP(H30, AA:AA, AB:AB) * I30 -> 0 | R30: =M30*0.0006 -> 0 | S30: =M30*0.02 -> 0 | T30: =L30-P30-Q30-R30-S30 -> 0 | U30: =IF(K30="CORREO",0,N30) -> 0 | V30: =T30*0.05 -> 0 | W30: =T30*0.05 -> 0
L31: =IFERROR(IF(J31="Transferencia",_xlfn.XLOOKUP(H31,$AA:$AA,$AE:$AE)*I31,_xlfn.XLOOKUP(H31,$AA:$AA,$AD:$AD)*I31),0) -> 0 | N31: =M31-L31 -> 0 | P31: =_xlfn.XLOOKUP(H31, AA:AA, AB:AB) * I31 -> 0 | R31: =M31*0.0006 -> 0 | S31: =M31*0.02 -> 0 | T31: =L31-P31-Q31-R31-S31 -> 0 | U31: =IF(K31="CORREO",0,N31) -> 0 | V31: =T31*0.05 -> 0 | W31: =T31*0.05 -> 0
L32: =IFERROR(IF(J32="Transferencia",_xlfn.XLOOKUP(H32,$AA:$AA,$AE:$AE)*I32,_xlfn.XLOOKUP(H32,$AA:$AA,$AD:$AD)*I32),0) -> 0 | N32: =M32-L32 -> 0 | P32: =_xlfn.XLOOKUP(H32, AA:AA, AB:AB) * I32 -> 0 | R32: =M32*0.0006 -> 0 | S32: =M32*0.02 -> 0 | T32: =L32-P32-Q32-R32-S32 -> 0 | U32: =IF(K32="CORREO",0,N32) -> 0 | V32: =T32*0.05 -> 0 | W32: =T32*0.05 -> 0
L33: =IFERROR(IF(J33="Transferencia",_xlfn.XLOOKUP(H33,$AA:$AA,$AE:$AE)*I33,_xlfn.XLOOKUP(H33,$AA:$AA,$AD:$AD)*I33),0) -> 0 | N33: =M33-L33 -> 0 | P33: =_xlfn.XLOOKUP(H33, AA:AA, AB:AB) * I33 -> 0 | R33: =M33*0.0006 -> 0 | S33: =M33*0.02 -> 0 | T33: =L33-P33-Q33-R33-S33 -> 0 | U33: =IF(K33="CORREO",0,N33) -> 0 | V33: =T33*0.05 -> 0 | W33: =T33*0.05 -> 0
L34: =IFERROR(IF(J34="Transferencia",_xlfn.XLOOKUP(H34,$AA:$AA,$AE:$AE)*I34,_xlfn.XLOOKUP(H34,$AA:$AA,$AD:$AD)*I34),0) -> 0 | N34: =M34-L34 -> 0 | P34: =_xlfn.XLOOKUP(H34, AA:AA, AB:AB) * I34 -> 0 | R34: =M34*0.0006 -> 0 | S34: =M34*0.02 -> 0 | T34: =L34-P34-Q34-R34-S34 -> 0 | U34: =IF(K34="CORREO",0,N34) -> 0 | V34: =T34*0.05 -> 0 | W34: =T34*0.05 -> 0
C35: MELI | L35: =IFERROR(IF(J35="Transferencia",_xlfn.XLOOKUP(H35,$AA:$AA,$AE:$AE)*I35,_xlfn.XLOOKUP(H35,$AA:$AA,$AD:$AD)*I35),0) -> 0 | N35: =M35-L35 -> 0 | P35: =_xlfn.XLOOKUP(H35, AA:AA, AB:AB) * I35 -> 0 | R35: =M35*0.0006 -> 0 | S35: =M35*0.02 -> 0 | T35: =L35-P35-Q35-R35-S35 -> 0 | U35: =IF(K35="CORREO",0,N35) -> 0 | V35: =T35*0.05 -> 0 | W35: =T35*0.05 -> 0
C36: MELI | L36: =IFERROR(IF(J36="Transferencia",_xlfn.XLOOKUP(H36,$AA:$AA,$AE:$AE)*I36,_xlfn.XLOOKUP(H36,$AA:$AA,$AD:$AD)*I36),0) -> 0 | N36: =M36-L36 -> 0 | P36: =_xlfn.XLOOKUP(H36, AA:AA, AB:AB) * I36 -> 0 | R36: =M36*0.0006 -> 0 | S36: =M36*0.02 -> 0 | T36: =L36-P36-Q36-R36-S36 -> 0 | U36: =IF(K36="CORREO",0,N36) -> 0 | V36: =T36*0.05 -> 0 | W36: =T36*0.05 -> 0
C37: MELI | L37: =IFERROR(IF(J37="Transferencia",_xlfn.XLOOKUP(H37,$AA:$AA,$AE:$AE)*I37,_xlfn.XLOOKUP(H37,$AA:$AA,$AD:$AD)*I37),0) -> 0 | N37: =M37-L37 -> 0 | P37: =_xlfn.XLOOKUP(H37, AA:AA, AB:AB) * I37 -> 0 | R37: =M37*0.0006 -> 0 | S37: =M37*0.02 -> 0 | T37: =L37-P37-Q37-R37-S37 -> 0 | U37: =IF(K37="CORREO",0,N37) -> 0 | V37: =T37*0.05 -> 0 | W37: =T37*0.05 -> 0
C38: MELI | L38: =IFERROR(IF(J38="Transferencia",_xlfn.XLOOKUP(H38,$AA:$AA,$AE:$AE)*I38,_xlfn.XLOOKUP(H38,$AA:$AA,$AD:$AD)*I38),0) -> 0 | N38: =M38-L38 -> 0 | P38: =_xlfn.XLOOKUP(H38, AA:AA, AB:AB) * I38 -> 0 | R38: =M38*0.0006 -> 0 | S38: =M38*0.02 -> 0 | T38: =L38-P38-Q38-R38-S38 -> 0 | U38: =IF(K38="CORREO",0,N38) -> 0 | V38: =T38*0.05 -> 0 | W38: =T38*0.05 -> 0
C39: MELI | L39: =IFERROR(IF(J39="Transferencia",_xlfn.XLOOKUP(H39,$AA:$AA,$AE:$AE)*I39,_xlfn.XLOOKUP(H39,$AA:$AA,$AD:$AD)*I39),0) -> 0 | N39: =M39-L39 -> 0 | P39: =_xlfn.XLOOKUP(H39, AA:AA, AB:AB) * I39 -> 0 | R39: =M39*0.0006 -> 0 | S39: =M39*0.02 -> 0 | T39: =L39-P39-Q39-R39-S39 -> 0 | U39: =IF(K39="CORREO",0,N39) -> 0 | V39: =T39*0.05 -> 0 | W39: =T39*0.05 -> 0
C40: MELI | L40: =IFERROR(IF(J40="Transferencia",_xlfn.XLOOKUP(H40,$AA:$AA,$AE:$AE)*I40,_xlfn.XLOOKUP(H40,$AA:$AA,$AD:$AD)*I40),0) -> 0 | N40: =M40-L40 -> 0 | P40: =_xlfn.XLOOKUP(H40, AA:AA, AB:AB) * I40 -> 0 | R40: =M40*0.0006 -> 0 | S40: =M40*0.02 -> 0 | T40: =L40-P40-Q40-R40-S40 -> 0 | U40: =IF(K40="CORREO",0,N40) -> 0 | V40: =T40*0.05 -> 0 | W40: =T40*0.05 -> 0
C41: MELI | L41: =IFERROR(IF(J41="Transferencia",_xlfn.XLOOKUP(H41,$AA:$AA,$AE:$AE)*I41,_xlfn.XLOOKUP(H41,$AA:$AA,$AD:$AD)*I41),0) -> 0 | N41: =M41-L41 -> 0 | P41: =_xlfn.XLOOKUP(H41, AA:AA, AB:AB) * I41 -> 0 | R41: =M41*0.0006 -> 0 | S41: =M41*0.02 -> 0 | T41: =L41-P41-Q41-R41-S41 -> 0 | U41: =IF(K41="CORREO",0,N41) -> 0 | V41: =T41*0.05 -> 0 | W41: =T41*0.05 -> 0
C42: MELI | L42: =IFERROR(IF(J42="Transferencia",_xlfn.XLOOKUP(H42,$AA:$AA,$AE:$AE)*I42,_xlfn.XLOOKUP(H42,$AA:$AA,$AD:$AD)*I42),0) -> 0 | N42: =M42-L42 -> 0 | P42: =_xlfn.XLOOKUP(H42, AA:AA, AB:AB) * I42 -> 0 | R42: =M42*0.0006 -> 0 | S42: =M42*0.02 -> 0 | T42: =L42-P42-Q42-R42-S42 -> 0 | U42: =IF(K42="CORREO",0,N42) -> 0 | V42: =T42*0.05 -> 0 | W42: =T42*0.05 -> 0
C43: MELI | L43: =IFERROR(IF(J43="Transferencia",_xlfn.XLOOKUP(H43,$AA:$AA,$AE:$AE)*I43,_xlfn.XLOOKUP(H43,$AA:$AA,$AD:$AD)*I43),0) -> 0 | N43: =M43-L43 -> 0 | P43: =_xlfn.XLOOKUP(H43, AA:AA, AB:AB) * I43 -> 0 | R43: =M43*0.0006 -> 0 | S43: =M43*0.02 -> 0 | T43: =L43-P43-Q43-R43-S43 -> 0 | U43: =IF(K43="CORREO",0,N43) -> 0 | V43: =T43*0.05 -> 0 | W43: =T43*0.05 -> 0
C44: MELI | L44: =IFERROR(IF(J44="Transferencia",_xlfn.XLOOKUP(H44,$AA:$AA,$AE:$AE)*I44,_xlfn.XLOOKUP(H44,$AA:$AA,$AD:$AD)*I44),0) -> 0 | N44: =M44-L44 -> 0 | P44: =_xlfn.XLOOKUP(H44, AA:AA, AB:AB) * I44 -> 0 | R44: =M44*0.0006 -> 0 | S44: =M44*0.02 -> 0 | T44: =L44-P44-Q44-R44-S44 -> 0 | U44: =IF(K44="CORREO",0,N44) -> 0 | V44: =T44*0.05 -> 0 | W44: =T44*0.05 -> 0
C45: MELI | L45: =IFERROR(IF(J45="Transferencia",_xlfn.XLOOKUP(H45,$AA:$AA,$AE:$AE)*I45,_xlfn.XLOOKUP(H45,$AA:$AA,$AD:$AD)*I45),0) -> 0 | N45: =M45-L45 -> 0 | P45: =_xlfn.XLOOKUP(H45, AA:AA, AB:AB) * I45 -> 0 | R45: =M45*0.0006 -> 0 | S45: =M45*0.02 -> 0 | T45: =L45-P45-Q45-R45-S45 -> 0 | U45: =IF(K45="CORREO",0,N45) -> 0 | V45: =T45*0.05 -> 0 | W45: =T45*0.05 -> 0
C46: MELI | L46: =IFERROR(IF(J46="Transferencia",_xlfn.XLOOKUP(H46,$AA:$AA,$AE:$AE)*I46,_xlfn.XLOOKUP(H46,$AA:$AA,$AD:$AD)*I46),0) -> 0 | N46: =M46-L46 -> 0 | P46: =_xlfn.XLOOKUP(H46, AA:AA, AB:AB) * I46 -> 0 | R46: =M46*0.0006 -> 0 | S46: =M46*0.02 -> 0 | T46: =L46-P46-Q46-R46-S46 -> 0 | U46: =IF(K46="CORREO",0,N46) -> 0 | V46: =T46*0.05 -> 0 | W46: =T46*0.05 -> 0
... C302: MELI | L302: =IFERROR(IF(J302="Transferencia",_xlfn.XLOOKUP(H302,$AA:$AA,$AE:$AE)*I302,_xlfn.XLOOKUP(H302,$AA:$AA,$AD:$AD)*I302),0) -> 0 | N302: =M302-L302 -> 0 | P302: =_xlfn.XLOOKUP(H302, AA:AA, AB:AB) * I302 -> 0 | R302: =M302*0.0006 -> 0 | S302: =M302*0.02 -> 0 | T302: =L302-P302-Q302-R302-S302 -> 0 | U302: =IF(K302="CORREO",0,N302) -> 0 | V302: =T302*0.05 -> 0 | W302: =T302*0.05 -> 0
C303: MELI | N303: =M303-L303 -> 0 | P303: =_xlfn.XLOOKUP(H303, AA:AA, AB:AB) * I303 -> 0 | R303: =M303*0.0006 -> 0 | S303: =M303*0.02 -> 0 | T303: =L303-P303-Q303-R303-S303 -> 0 | U303: =IF(K303="CORREO",0,N303) -> 0 | V303: =T303*0.05 -> 0 | W303: =T303*0.05 -> 0
C304: MELI | N304: =M304-L304 -> 0 | P304: =_xlfn.XLOOKUP(H304, AA:AA, AB:AB) * I304 -> 0 | R304: =M304*0.0006 -> 0 | S304: =M304*0.02 -> 0 | T304: =L304-P304-Q304-R304-S304 -> 0 | U304: =IF(K304="CORREO",0,N304) -> 0 | V304: =T304*0.05 -> 0 | W304: =T304*0.05 -> 0
C305: MELI | N305: =M305-L305 -> 0 | P305: =_xlfn.XLOOKUP(H305, AA:AA, AB:AB) * I305 -> 0 | R305: =M305*0.0006 -> 0 | S305: =M305*0.02 -> 0 | T305: =L305-P305-Q305-R305-S305 -> 0 | U305: =IF(K305="CORREO",0,N305) -> 0 | V305: =T305*0.05 -> 0 | W305: =T305*0.05 -> 0
C306: MELI | N306: =M306-L306 -> 0 | P306: =_xlfn.XLOOKUP(H306, AA:AA, AB:AB) * I306 -> 0 | R306: =M306*0.0006 -> 0 | S306: =M306*0.02 -> 0 | T306: =L306-P306-Q306-R306-S306 -> 0 | U306: =IF(K306="CORREO",0,N306) -> 0 | V306: =T306*0.05 -> 0 | W306: =T306*0.05 -> 0
C307: MELI | N307: =M307-L307 -> 0 | P307: =_xlfn.XLOOKUP(H307, AA:AA, AB:AB) * I307 -> 0 | R307: =M307*0.0006 -> 0 | S307: =M307*0.02 -> 0 | T307: =L307-P307-Q307-R307-S307 -> 0 | U307: =IF(K307="CORREO",0,N307) -> 0 | V307: =T307*0.05 -> 0 | W307: =T307*0.05 -> 0
C308: MELI | N308: =M308-L308 -> 0 | P308: =_xlfn.XLOOKUP(H308, AA:AA, AB:AB) * I308 -> 0 | R308: =M308*0.0006 -> 0 | S308: =M308*0.02 -> 0 | T308: =L308-P308-Q308-R308-S308 -> 0 | U308: =IF(K308="CORREO",0,N308) -> 0 | V308: =T308*0.05 -> 0 | W308: =T308*0.05 -> 0
C309: MELI | N309: =M309-L309 -> 0 | P309: =_xlfn.XLOOKUP(H309, AA:AA, AB:AB) * I309 -> 0 | R309: =M309*0.0006 -> 0 | S309: =M309*0.02 -> 0 | T309: =L309-P309-Q309-R309-S309 -> 0 | U309: =IF(K309="CORREO",0,N309) -> 0 | V309: =T309*0.05 -> 0 | W309: =T309*0.05 -> 0
C310: MELI | N310: =M310-L310 -> 0 | P310: =_xlfn.XLOOKUP(H310, AA:AA, AB:AB) * I310 -> 0 | R310: =M310*0.0006 -> 0 | S310: =M310*0.02 -> 0 | T310: =L310-P310-Q310-R310-S310 -> 0 | U310: =IF(K310="CORREO",0,N310) -> 0 | V310: =T310*0.05 -> 0 | W310: =T310*0.05 -> 0
C311: MELI | N311: =M311-L311 -> 0 | P311: =_xlfn.XLOOKUP(H311, AA:AA, AB:AB) * I311 -> 0 | R311: =M311*0.0006 -> 0 | S311: =M311*0.02 -> 0 | T311: =L311-P311-Q311-R311-S311 -> 0 | U311: =IF(K311="CORREO",0,N311) -> 0 | V311: =T311*0.05 -> 0 | W311: =T311*0.05 -> 0
C312: MELI | N312: =M312-L312 -> 0 | P312: =_xlfn.XLOOKUP(H312, AA:AA, AB:AB) * I312 -> 0 | R312: =M312*0.0006 -> 0 | S312: =M312*0.02 -> 0 | T312: =L312-P312-Q312-R312-S312 -> 0 | U312: =IF(K312="CORREO",0,N312) -> 0 | V312: =T312*0.05 -> 0 | W312: =T312*0.05 -> 0
C313: MELI | N313: =M313-L313 -> 0 | P313: =_xlfn.XLOOKUP(H313, AA:AA, AB:AB) * I313 -> 0 | R313: =M313*0.0006 -> 0 | S313: =M313*0.02 -> 0 | T313: =L313-P313-Q313-R313-S313 -> 0 | U313: =IF(K313="CORREO",0,N313) -> 0 | V313: =T313*0.05 -> 0 | W313: =T313*0.05 -> 0
C314: MELI | N314: =M314-L314 -> 0 | P314: =_xlfn.XLOOKUP(H314, AA:AA, AB:AB) * I314 -> 0 | R314: =M314*0.0006 -> 0 | S314: =M314*0.02 -> 0 | T314: =L314-P314-Q314-R314-S314 -> 0 | U314: =IF(K314="CORREO",0,N314) -> 0 | V314: =T314*0.05 -> 0 | W314: =T314*0.05 -> 0
... C400: MELI | N400: =M400-L400 -> 0 | P400: =_xlfn.XLOOKUP(H400, AA:AA, AB:AB) * I400 -> 0 | R400: =M400*0.0006 -> 0 | S400: =M400*0.02 -> 0 | T400: =L400-P400-Q400-R400-S400 -> 0 | U400: =IF(K400="CORREO",0,N400) -> 0 | V400: =T400*0.05 -> 0 | W400: =T400*0.05 -> 0
C401: MELI | P401: =_xlfn.XLOOKUP(H401, AA:AA, AB:AB) * I401 -> 0 | S401: =M401*0.02 -> 0 | T401: =L401-N401-P401-Q401-R401-S401 -> 0 | U401: =IF(K401="CORREO","0","L6") -> L6 | V401: =T401*0.05 -> 0 | W401: =T401*0.05 -> 0
C402: MELI | P402: =_xlfn.XLOOKUP(H402, AA:AA, AB:AB) * I402 -> 0 | S402: =M402*0.02 -> 0 | T402: =L402-N402-P402-Q402-R402-S402 -> 0 | U402: =IF(K402="CORREO","0","L6") -> L6 | V402: =T402*0.05 -> 0 | W402: =T402*0.05 -> 0
C403: MELI | P403: =_xlfn.XLOOKUP(H403, AA:AA, AB:AB) * I403 -> 0 | S403: =M403*0.02 -> 0 | T403: =L403-N403-P403-Q403-R403-S403 -> 0 | U403: =IF(K403="CORREO","0","L6") -> L6 | V403: =T403*0.05 -> 0 | W403: =T403*0.05 -> 0
C404: MELI | P404: =_xlfn.XLOOKUP(H404, AA:AA, AB:AB) * I404 -> 0 | S404: =M404*0.02 -> 0 | T404: =L404-N404-P404-Q404-R404-S404 -> 0 | U404: =IF(K404="CORREO","0","L6") -> L6 | V404: =T404*0.05 -> 0 | W404: =T404*0.05 -> 0
C405: MELI | P405: =_xlfn.XLOOKUP(H405, AA:AA, AB:AB) * I405 -> 0 | S405: =M405*0.02 -> 0 | T405: =L405-N405-P405-Q405-R405-S405 -> 0 | U405: =IF(K405="CORREO","0","L6") -> L6 | V405: =T405*0.05 -> 0 | W405: =T405*0.05 -> 0
C406: MELI | P406: =_xlfn.XLOOKUP(H406, AA:AA, AB:AB) * I406 -> 0 | S406: =M406*0.02 -> 0 | T406: =L406-N406-P406-Q406-R406-S406 -> 0 | U406: =IF(K406="CORREO","0","L6") -> L6 | V406: =T406*0.05 -> 0 | W406: =T406*0.05 -> 0
C407: MELI | P407: =_xlfn.XLOOKUP(H407, AA:AA, AB:AB) * I407 -> 0 | S407: =M407*0.02 -> 0 | T407: =L407-N407-P407-Q407-R407-S407 -> 0 | U407: =IF(K407="CORREO","0","L6") -> L6 | V407: =T407*0.05 -> 0 | W407: =T407*0.05 -> 0
C408: MELI | P408: =_xlfn.XLOOKUP(H408, AA:AA, AB:AB) * I408 -> 0 | S408: =M408*0.02 -> 0 | T408: =L408-N408-P408-Q408-R408-S408 -> 0 | U408: =IF(K408="CORREO","0","L6") -> L6 | V408: =T408*0.05 -> 0 | W408: =T408*0.05 -> 0
C409: MELI | P409: =_xlfn.XLOOKUP(H409, AA:AA, AB:AB) * I409 -> 0 | S409: =M409*0.02 -> 0 | T409: =L409-N409-P409-Q409-R409-S409 -> 0 | U409: =IF(K409="CORREO","0","L6") -> L6 | V409: =T409*0.05 -> 0 | W409: =T409*0.05 -> 0
C410: MELI | P410: =_xlfn.XLOOKUP(H410, AA:AA, AB:AB) * I410 -> 0 | S410: =M410*0.02 -> 0 | T410: =L410-N410-P410-Q410-R410-S410 -> 0 | U410: =IF(K410="CORREO","0","L6") -> L6 | V410: =T410*0.05 -> 0 | W410: =T410*0.05 -> 0
C411: MELI | P411: =_xlfn.XLOOKUP(H411, AA:AA, AB:AB) * I411 -> 0 | S411: =M411*0.02 -> 0 | T411: =L411-N411-P411-Q411-R411-S411 -> 0 | U411: =IF(K411="CORREO","0","L6") -> L6 | V411: =T411*0.05 -> 0 | W411: =T411*0.05 -> 0
C412: MELI | P412: =_xlfn.XLOOKUP(H412, AA:AA, AB:AB) * I412 -> 0 | S412: =M412*0.02 -> 0 | T412: =L412-N412-P412-Q412-R412-S412 -> 0 | U412: =IF(K412="CORREO","0","L6") -> L6 | V412: =T412*0.05 -> 0 | W412: =T412*0.05 -> 0
... C419: MELI | P419: =_xlfn.XLOOKUP(H419, AA:AA, AB:AB) * I419 -> 0 | S419: =M419*0.02 -> 0 | T419: =L419-N419-P419-Q419-R419-S419 -> 0 | U419: =IF(K419="CORREO","0","L6") -> L6 | V419: =T419*0.05 -> 0 | W419: =T419*0.05 -> 0
P420: =_xlfn.XLOOKUP(H420, AA:AA, AB:AB) * I420 -> 0 | S420: =M420*0.02 -> 0 | T420: =L420-N420-P420-Q420-R420-S420 -> 0 | U420: =IF(K420="CORREO","0","L6") -> L6 | V420: =T420*0.05 -> 0 | W420: =T420*0.05 -> 0
P421: =_xlfn.XLOOKUP(H421, AA:AA, AB:AB) * I421 -> 0 | S421: =M421*0.02 -> 0 | T421: =L421-N421-P421-Q421-R421-S421 -> 0 | U421: =IF(K421="CORREO","0","L6") -> L6 | V421: =T421*0.05 -> 0 | W421: =T421*0.05 -> 0
P422: =_xlfn.XLOOKUP(H422, AA:AA, AB:AB) * I422 -> 0 | S422: =M422*0.02 -> 0 | T422: =L422-N422-P422-Q422-R422-S422 -> 0 | U422: =IF(K422="CORREO","0","L6") -> L6 | V422: =T422*0.05 -> 0 | W422: =T422*0.05 -> 0
P423: =_xlfn.XLOOKUP(H423, AA:AA, AB:AB) * I423 -> 0 | S423: =M423*0.02 -> 0 | T423: =L423-N423-P423-Q423-R423-S423 -> 0 | U423: =IF(K423="CORREO","0","L6") -> L6 | V423: =T423*0.05 -> 0 | W423: =T423*0.05 -> 0
P424: =_xlfn.XLOOKUP(H424, AA:AA, AB:AB) * I424 -> 0 | S424: =M424*0.02 -> 0 | T424: =L424-N424-P424-Q424-R424-S424 -> 0 | U424: =IF(K424="CORREO","0","L6") -> L6 | V424: =T424*0.05 -> 0 | W424: =T424*0.05 -> 0
P425: =_xlfn.XLOOKUP(H425, AA:AA, AB:AB) * I425 -> 0 | S425: =M425*0.02 -> 0 | T425: =L425-N425-P425-Q425-R425-S425 -> 0 | U425: =IF(K425="CORREO","0","L6") -> L6 | V425: =T425*0.05 -> 0 | W425: =T425*0.05 -> 0
P426: =_xlfn.XLOOKUP(H426, AA:AA, AB:AB) * I426 -> 0 | S426: =M426*0.02 -> 0 | T426: =L426-N426-P426-Q426-R426-S426 -> 0 | U426: =IF(K426="CORREO","0","L6") -> L6 | V426: =T426*0.05 -> 0 | W426: =T426*0.05 -> 0
P427: =_xlfn.XLOOKUP(H427, AA:AA, AB:AB) * I427 -> 0 | S427: =M427*0.02 -> 0 | T427: =L427-N427-P427-Q427-R427-S427 -> 0 | U427: =IF(K427="CORREO","0","L6") -> L6 | V427: =T427*0.05 -> 0 | W427: =T427*0.05 -> 0
P428: =_xlfn.XLOOKUP(H428, AA:AA, AB:AB) * I428 -> 0 | S428: =M428*0.02 -> 0 | T428: =L428-N428-P428-Q428-R428-S428 -> 0 | U428: =IF(K428="CORREO","0","L6") -> L6 | V428: =T428*0.05 -> 0 | W428: =T428*0.05 -> 0
P429: =_xlfn.XLOOKUP(H429, AA:AA, AB:AB) * I429 -> 0 | S429: =M429*0.02 -> 0 | T429: =L429-N429-P429-Q429-R429-S429 -> 0 | U429: =IF(K429="CORREO","0","L6") -> L6 | V429: =T429*0.05 -> 0 | W429: =T429*0.05 -> 0
P430: =_xlfn.XLOOKUP(H430, AA:AA, AB:AB) * I430 -> 0 | S430: =M430*0.02 -> 0 | T430: =L430-N430-P430-Q430-R430-S430 -> 0 | U430: =IF(K430="CORREO","0","L6") -> L6 | V430: =T430*0.05 -> 0 | W430: =T430*0.05 -> 0
P431: =_xlfn.XLOOKUP(H431, AA:AA, AB:AB) * I431 -> 0 | S431: =M431*0.02 -> 0 | T431: =L431-N431-P431-Q431-R431-S431 -> 0 | U431: =IF(K431="CORREO","0","L6") -> L6 | V431: =T431*0.05 -> 0 | W431: =T431*0.05 -> 0
... P488: =_xlfn.XLOOKUP(H488, AA:AA, AB:AB) * I488 -> 0 | S488: =M488*0.02 -> 0 | T488: =L488-N488-P488-Q488-R488-S488 -> 0 | U488: =IF(K488="CORREO","0","L6") -> L6 | V488: =T488*0.05 -> 0 | W488: =T488*0.05 -> 0
P489: =_xlfn.XLOOKUP(H489, AA:AA, AB:AB) * I489 -> 0 | S489: =M489*0.02 -> 0 | T489: =L489-N489-P489-Q489-R489-S489 -> 0 | V489: =T489*0.05 -> 0 | W489: =T489*0.05 -> 0
P490: =_xlfn.XLOOKUP(H490, AA:AA, AB:AB) * I490 -> 0 | S490: =M490*0.02 -> 0 | T490: =L490-N490-P490-Q490-R490-S490 -> 0 | V490: =T490*0.05 -> 0 | W490: =T490*0.05 -> 0
P491: =_xlfn.XLOOKUP(H491, AA:AA, AB:AB) * I491 -> 0 | S491: =M491*0.02 -> 0 | T491: =L491-N491-P491-Q491-R491-S491 -> 0 | V491: =T491*0.05 -> 0 | W491: =T491*0.05 -> 0
P492: =_xlfn.XLOOKUP(H492, AA:AA, AB:AB) * I492 -> 0 | S492: =M492*0.02 -> 0 | T492: =L492-N492-P492-Q492-R492-S492 -> 0 | V492: =T492*0.05 -> 0 | W492: =T492*0.05 -> 0
P493: =_xlfn.XLOOKUP(H493, AA:AA, AB:AB) * I493 -> 0 | S493: =M493*0.02 -> 0 | T493: =L493-N493-P493-Q493-R493-S493 -> 0 | V493: =T493*0.05 -> 0 | W493: =T493*0.05 -> 0
P494: =_xlfn.XLOOKUP(H494, AA:AA, AB:AB) * I494 -> 0 | S494: =M494*0.02 -> 0 | T494: =L494-N494-P494-Q494-R494-S494 -> 0 | V494: =T494*0.05 -> 0 | W494: =T494*0.05 -> 0
P495: =_xlfn.XLOOKUP(H495, AA:AA, AB:AB) * I495 -> 0 | S495: =M495*0.02 -> 0 | T495: =L495-N495-P495-Q495-R495-S495 -> 0 | V495: =T495*0.05 -> 0 | W495: =T495*0.05 -> 0
P496: =_xlfn.XLOOKUP(H496, AA:AA, AB:AB) * I496 -> 0 | S496: =M496*0.02 -> 0 | T496: =L496-N496-P496-Q496-R496-S496 -> 0 | V496: =T496*0.05 -> 0 | W496: =T496*0.05 -> 0
P497: =_xlfn.XLOOKUP(H497, AA:AA, AB:AB) * I497 -> 0 | S497: =M497*0.02 -> 0 | T497: =L497-N497-P497-Q497-R497-S497 -> 0 | V497: =T497*0.05 -> 0 | W497: =T497*0.05 -> 0
P498: =_xlfn.XLOOKUP(H498, AA:AA, AB:AB) * I498 -> 0 | S498: =M498*0.02 -> 0 | T498: =L498-N498-P498-Q498-R498-S498 -> 0 | V498: =T498*0.05 -> 0 | W498: =T498*0.05 -> 0
P499: =_xlfn.XLOOKUP(H499, AA:AA, AB:AB) * I499 -> 0 | S499: =M499*0.02 -> 0 | T499: =L499-N499-P499-Q499-R499-S499 -> 0 | V499: =T499*0.05 -> 0
P500: =_xlfn.XLOOKUP(H500, AA:AA, AB:AB) * I500 -> 0 | S500: =M500*0.02 -> 0 | T500: =L500-N500-P500-Q500-R500-S500 -> 0 | V500: =T500*0.05 -> 0
P501: =_xlfn.XLOOKUP(H501, AA:AA, AB:AB) * I501 -> 0
P502: =_xlfn.XLOOKUP(H502, AA:AA, AB:AB) * I502 -> 0
...

Sheet Ventas MELI
T1: 0.15
A2: ESTADO | B2: Fecha | C2: Nombre AD | E2: Telefono | F2: Producto | G2: Cantidad | H2: FACTURÓ | I2: Cargo por venta | J2: Costo fijo | K2: "impuestos" P | L2: Envio entró | M2: Envio salio | N2: Envio Flex | P2: me quedó | Q2: Costo | R2: Ganancia | S2: MONOTRIBUTO | T2: 0.02 | X2: Chocos Colonial Usados | Z2: NECESITO
C3: Diciembre | T3: Brisa | U3: =SUM(T4:T39) -> 11017.869 | V3: FLEX
V4: =SUM(T3:T32) -> 9433.1812 | W4: Facturacion | X4: Me quedó | Y4: Costos | Z4: Ganancias | AE4: Choco Suelto | AF4: 294
C5: Maria Belen Argañaras | F5: Cajita de 4 | G5: 10 | H5: 41800 | I5: -5684.8 | J5: -4600 | K5: -627 | L5: 10245.99 | M5: 0 | N5: =IF(O5="Mercado Envíos Flex","SI","NO") -> SI | O5: Mercado Envíos Flex | P5: =H5+I5+J5+K5+L5+M5 -> 41134.19 | Q5: =_xlfn.XLOOKUP(F5, AE:AE, AF:AF) * G5 -> 14435 | R5: =IF(N5="Si", P5-Q5-L5, P5-Q5) -> 16453.2 | S5: =R5*0.05 -> 822.66 | T5: =R5*$T$2 -> 329.064 | V5: =IF(N5= "Si",L5,0) -> 10245.99 | W5: =SUM(H5:H400) -> 1294600 | X5: =SUM(P5:P400) -> 1030724 | Y5: =SUM(Q5:Q400) -> 411776.5 | Z5: =SUM(R5:R400) -> 550893.46 | AE5: Mini Recuerdo | AF5: 327
C6: Joana Fernandez Castro | F6: Choco Suelto | G6: 75 | H6: 67500 | I6: -9180 | J6: -6900 | K6: 0 | L6: 7370.99 | M6: 0 | N6: =IF(O6="Mercado Envíos Flex","SI","NO") -> SI | O6: Mercado Envíos Flex | P6: =H6+I6+J6+K6+L6+M6 -> 58790.99 | Q6: =_xlfn.XLOOKUP(F6, AE:AE, AF:AF) * G6 -> 22050 | R6: =IF(N6="Si", P6-Q6-L6, P6-Q6) -> 29370 | S6: =R6*0.05 -> 1468.5 | T6: =R6*$T$2 -> 587.4 | V6: =IF(N6= "Si",L6,0) -> 7370.99 | AE6: Tarjeta | AF6: 330
C7: Ximena Anahi Barraza | F7: Cajita de 4 | G7: 5 | H7: 20900 | I7: -2842.4 | J7: -2300 | K7: -313.5 | L7: 16830.99 | M7: -16830.99 | N7: =IF(O7="Mercado Envíos Flex","SI","NO") -> NO | O7: Correo y puntos de despacho | P7: =H7+I7+J7+K7+L7+M7 -> 15444.1 | Q7: =_xlfn.XLOOKUP(F7, AE:AE, AF:AF) * G7 -> 7217.5 | R7: =IF(N7="Si", P7-Q7-L7, P7-Q7) -> 8226.6 | S7: =R7*0.05 -> 411.33 | T7: =R7*$T$2 -> 164.532 | V7: =IF(N7= "Si",L7,0) -> 0 | AE7: Cajita de 4 | AF7: 1443.5
C8: Liana Roxana Castello | F8: Choco Suelto | G8: 25 | H8: 22500 | I8: -3060 | J8: -2300 | K8: 0 | L8: 7370.99 | M8: 0 | N8: =IF(O8="Mercado Envíos Flex","SI","NO") -> SI | O8: Mercado Envíos Flex | P8: =H8+I8+J8+K8+L8+M8 -> 24510.99 | Q8: =_xlfn.XLOOKUP(F8, AE:AE, AF:AF) * G8 -> 7350 | R8: =IF(N8="Si", P8-Q8-L8, P8-Q8) -> 9790 | S8: =R8*0.05 -> 489.5 | T8: =R8*$T$2 -> 195.8 | V8: =IF(N8= "Si",L8,0) -> 7370.99 | AE8: Cajita de 4 deluxe | AF8: 1499.86
C9: Sebastian Martinez Boichuk | F9: Choco Suelto | G9: 25 | H9: 22500 | I9: -3060 | J9: -2300 | K9: 0 | L9: 7370.99 | M9: 0 | N9: =IF(O9="Mercado Envíos Flex","SI","NO") -> SI | O9: Mercado Envíos Flex | P9: =H9+I9+J9+K9+L9+M9 -> 24510.99 | Q9: =_xlfn.XLOOKUP(F9, AE:AE, AF:AF) * G9 -> 7350 | R9: =IF(N9="Si", P9-Q9-L9, P9-Q9) -> 9790 | S9: =R9*0.05 -> 489.5 | T9: =R9*$T$2 -> 195.8 | V9: =IF(N9= "Si",L9,0) -> 7370.99 | AE9: D6 Classic | AF9: 2263.63
C10: Miryam Edith Zavaley | F10: Choco Suelto | G10: 25 | H10: 22500 | I10: -3060 | J10: -2300 | K10: -475.28 | L10: 9185.14 | M10: -9185.14 | N10: =IF(O10="Mercado Envíos Flex","SI","NO") -> NO | O10: Correo y puntos de despacho | P10: =H10+I10+J10+K10+L10+M10 -> 16664.72 | Q10: =_xlfn.XLOOKUP(F10, AE:AE, AF:AF) * G10 -> 7350 | R10: =IF(N10="Si", P10-Q10-L10, P10-Q10) -> 9314.72 | S10: =R10*0.05 -> 465.736 | T10: =R10*$T$2 -> 186.2944 | V10: =IF(N10= "Si",L10,0) -> 0 | AE10: D6 Deluxe | AF10: 2422
C11: Marina Gisela di Fonzo | F11: Choco Suelto | G11: 50 | H11: 51000 | I11: -6936 | J11: -5620 | K11: -765 | L11: 0 | M11: 0 | N11: =IF(O11="Mercado Envíos Flex","SI","NO") -> NO | O11: Correo y puntos de despacho | P11: =H11+I11+J11+K11+L11+M11 -> 37679 | Q11: =_xlfn.XLOOKUP(F11, AE:AE, AF:AF) * G11 -> 14700 | R11: =IF(N11="Si", P11-Q11-L11, P11-Q11) -> 22979 | S11: =R11*0.05 -> 1148.95 | T11: =R11*$T$2 -> 459.58 | V11: =IF(N11= "Si",L11,0) -> 0 | AE11: D6 Gold | AF11: 2384.8
C12: Daniela Anahi Ramallo | F12: Choco Suelto | G12: 25 | H12: 22500 | I12: -3060 | J12: -2300 | K12: -426.58 | L12: 5938.79 | M12: -5938.79 | N12: =IF(O12="Mercado Envíos Flex","SI","NO") -> NO | O12: Correo y puntos de despacho | P12: =H12+I12+J12+K12+L12+M12 -> 16713.42 | Q12: =_xlfn.XLOOKUP(F12, AE:AE, AF:AF) * G12 -> 7350 | R12: =IF(N12="Si", P12-Q12-L12, P12-Q12) -> 9363.42 | S12: =R12*0.05 -> 468.171 | T12: =R12*$T$2 -> 187.2684 | V12: =IF(N12= "Si",L12,0) -> 0 | AE12: Black | AF12: 2610
C13: Veronica Andrea Surdo | F13: Mini Recuerdo | G13: 25 | H13: 36000 | I13: -5220 | J13: 0 | K13: -540 | L13: 461.1 | M13: 0 | N13: =IF(O13="Mercado Envíos Flex","SI","NO") -> SI | O13: Mercado Envíos Flex | P13: =H13+I13+J13+K13+L13+M13 -> 30701.1 | Q13: =_xlfn.XLOOKUP(F13, AE:AE, AF:AF) * G13 -> 8175 | R13: =IF(N13="Si", P13-Q13-L13, P13-Q13) -> 22065 | S13: =R13*0.05 -> 1103.25 | T13: =R13*$T$2 -> 441.3 | V13: =IF(N13= "Si",L13,0) -> 461.1 | AE13: Señaladores | AF13: 440.7
C14: Mabel Susana Gazzero | F14: Choco Suelto | G14: 25 | H14: 22500 | I14: -3060 | J14: -2300 | K14: -337.5 | L14: 5942.79 | M14: -5942.79 | N14: =IF(O14="Mercado Envíos Flex","SI","NO") -> NO | O14: Correo y puntos de despacho | P14: =H14+I14+J14+K14+L14+M14 -> 16802.5 | Q14: =_xlfn.XLOOKUP(F14, AE:AE, AF:AF) * G14 -> 7350 | R14: =IF(N14="Si", P14-Q14-L14, P14-Q14) -> 9452.5 | S14: =R14*0.05 -> 472.625 | T14: =R14*$T$2 -> 189.05 | V14: =IF(N14= "Si",L14,0) -> 0 | AE14: D2 | AF14: 1293
C15: Horacio Atilio Ribero | F15: Caja 44 Chocos | G15: 1 | H15: 32900 | I15: -4474.4 | J15: -2810 | K15: -558.24 | L15: 4315.94 | M15: -4315.94 | N15: =IF(O15="Mercado Envíos Flex","SI","NO") -> NO | O15: Correo y puntos de despacho | P15: =H15+I15+J15+K15+L15+M15 -> 25057.36 | Q15: =_xlfn.XLOOKUP(F15, AE:AE, AF:AF) * G15 -> 12512 | R15: =IF(N15="Si", P15-Q15-L15, P15-Q15) -> 12545.36 | S15: =R15*0.05 -> 627.268 | T15: =R15*$T$2 -> 250.9072 | V15: =IF(N15= "Si",L15,0) -> 0 | AE15: D2 moño | AF15: 1367
C16: Andrea Natalia Castro | F16: Mini Recuerdo | G16: 25 | H16: 36000 | I16: -5220 | J16: 0 | K16: -540 | L16: 0 | M16: -6560.49 | N16: =IF(O16="Mercado Envíos Flex","SI","NO") -> NO | O16: Correo y puntos de despacho | P16: =H16+I16+J16+K16+L16+M16 -> 23679.51 | Q16: =_xlfn.XLOOKUP(F16, AE:AE, AF:AF) * G16 -> 8175 | R16: =IF(N16="Si", P16-Q16-L16, P16-Q16) -> 15504.51 | S16: =R16*0.05 -> 775.2255 | T16: =R16*$T$2 -> 310.0902 | V16: =IF(N16= "Si",L16,0) -> 0 | AE16: Vela 100cc
C17: Teresa Silvina Petracca | F17: Choco Suelto | G17: 25 | H17: 22500 | I17: -3060 | J17: -2300 | K17: -437.86 | L17: 6690.99 | M17: -6690.99 | N17: =IF(O17="Mercado Envíos Flex","SI","NO") -> NO | O17: Correo y puntos de despacho | P17: =H17+I17+J17+K17+L17+M17 -> 16702.14 | Q17: =_xlfn.XLOOKUP(F17, AE:AE, AF:AF) * G17 -> 7350 | R17: =IF(N17="Si", P17-Q17-L17, P17-Q17) -> 9352.14 | S17: =R17*0.05 -> 467.607 | T17: =R17*$T$2 -> 187.0428 | V17: =IF(N17= "Si",L17,0) -> 0 | AE17: Vela 200cc
C18: Cristina Mabel Salatin | F18: Choco Suelto | G18: 25 | H18: 22500 | I18: -3060 | J18: -2300 | K18: -426.58 | L18: 5938.79 | M18: -5938.79 | N18: =IF(O18="Mercado Envíos Flex","SI","NO") -> NO | O18: Correo y puntos de despacho | P18: =H18+I18+J18+K18+L18+M18 -> 16713.42 | Q18: =_xlfn.XLOOKUP(F18, AE:AE, AF:AF) * G18 -> 7350 | R18: =IF(N18="Si", P18-Q18-L18, P18-Q18) -> 9363.42 | S18: =R18*0.05 -> 468.171 | T18: =R18*$T$2 -> 187.2684 | V18: =IF(N18= "Si",L18,0) -> 0 | AE18: caja 44 chocos | AF18: 12512
C19: Liana Roxana Castello | F19: Choco Suelto | G19: 25 | H19: 22500 | I19: -3060 | J19: -2300 | K19: 0 | L19: 7370.99 | M19: 0 | N19: =IF(O19="Mercado Envíos Flex","SI","NO") -> SI | O19: Mercado Envíos Flex | P19: =H19+I19+J19+K19+L19+M19 -> 24510.99 | Q19: =_xlfn.XLOOKUP(F19, AE:AE, AF:AF) * G19 -> 7350 | R19: =IF(N19="Si", P19-Q19-L19, P19-Q19) -> 9790 | S19: =R19*0.05 -> 489.5 | T19: =R19*$T$2 -> 195.8 | V19: =IF(N19= "Si",L19,0) -> 7370.99
C20: Ximena Alejandra Cisneros | F20: Choco Suelto | G20: 400 | H20: 316000 | I20: -42976 | J20: 0 | K20: -4740 | L20: 0 | M20: -28001.98 | N20: =IF(O20="Mercado Envíos Flex","SI","NO") -> NO | O20: Correo y puntos de despacho | P20: =H20+I20+J20+K20+L20+M20 -> 240282.02 | Q20: =_xlfn.XLOOKUP(F20, AE:AE, AF:AF) * G20 -> 117600 | R20: =IF(N20="Si", P20-Q20-L20, P20-Q20) -> 122682.02 | S20: =R20*0.05 -> 6134.101 | T20: =R20*$T$2 -> 2453.6404 | V20: =IF(N20= "Si",L20,0) -> 0
C21: Martin Leonardo Cardenas | F21: Choco Suelto | G21: 50 | H21: 45000 | I21: -6120 | J21: -4600 | K21: -675 | L21: 10245.99 | M21: 0 | N21: =IF(O21="Mercado Envíos Flex","SI","NO") -> SI | O21: Mercado Envíos Flex | P21: =H21+I21+J21+K21+L21+M21 -> 43850.99 | Q21: =_xlfn.XLOOKUP(F21, AE:AE, AF:AF) * G21 -> 14700 | R21: =IF(N21="Si", P21-Q21-L21, P21-Q21) -> 18905 | S21: =R21*0.05 -> 945.25 | T21: =R21*$T$2 -> 378.1 | V21: =IF(N21= "Si",L21,0) -> 10245.99
C22: Silvana Veronica Castagnari | F22: Mini Recuerdo | G22: 25 | H22: 36000 | I22: -5220 | J22: 0 | K22: -540 | L22: 0 | M22: -6560.49 | N22: =IF(O22="Mercado Envíos Flex","SI","NO") -> NO | O22: Correo y puntos de despacho | P22: =H22+I22+J22+K22+L22+M22 -> 23679.51 | Q22: =_xlfn.XLOOKUP(F22, AE:AE, AF:AF) * G22 -> 8175 | R22: =IF(N22="Si", P22-Q22-L22, P22-Q22) -> 15504.51 | S22: =R22*0.05 -> 775.2255 | T22: =R22*$T$2 -> 310.0902 | V22: =IF(N22= "Si",L22,0) -> 0
C23: Carolina Elizabeth Baez | F23: Mini Recuerdo | G23: 25 | H23: 36000 | I23: -5220 | J23: 0 | K23: -540 | L23: 0 | M23: -6560.49 | N23: =IF(O23="Mercado Envíos Flex","SI","NO") -> NO | O23: Correo y puntos de despacho | P23: =H23+I23+J23+K23+L23+M23 -> 23679.51 | Q23: =_xlfn.XLOOKUP(F23, AE:AE, AF:AF) * G23 -> 8175 | R23: =IF(N23="Si", P23-Q23-L23, P23-Q23) -> 15504.51 | S23: =R23*0.05 -> 775.2255 | T23: =R23*$T$2 -> 310.0902 | V23: =IF(N23= "Si",L23,0) -> 0
C24: Marina Vanesa Barbieri | F24: Choco Suelto | G24: 25 | H24: 22500 | I24: -3060 | J24: -2300 | K24: -437.86 | L24: 6690.99 | M24: -6690.99 | N24: =IF(O24="Mercado Envíos Flex","SI","NO") -> NO | O24: Correo y puntos de despacho | P24: =H24+I24+J24+K24+L24+M24 -> 16702.14 | Q24: =_xlfn.XLOOKUP(F24, AE:AE, AF:AF) * G24 -> 7350 | R24: =IF(N24="Si", P24-Q24-L24, P24-Q24) -> 9352.14 | S24: =R24*0.05 -> 467.607 | T24: =R24*$T$2 -> 187.0428 | V24: =IF(N24= "Si",L24,0) -> 0
C25: Patricia Analia Penna | F25: Choco Suelto | G25: 50 | H25: 45000 | I25: -6120 | J25: -4600 | K25: -675 | L25: 0 | M25: 0 | N25: =IF(O25="Mercado Envíos Flex","SI","NO") -> NO | O25: Correo y puntos de despacho | P25: =H25+I25+J25+K25+L25+M25 -> 33605 | Q25: =_xlfn.XLOOKUP(F25, AE:AE, AF:AF) * G25 -> 14700 | R25: =IF(N25="Si", P25-Q25-L25, P25-Q25) -> 18905 | S25: =R25*0.05 -> 945.25 | T25: =R25*$T$2 -> 378.1 | V25: =IF(N25= "Si",L25,0) -> 0
R26: =IF(N26="Si", P26-Q26-L26, P26-Q26) -> 0 | S26: =R26*0.05 -> 0 | T26: =R26*$T$2 -> 0 | V26: =IF(N26= "Si",L26,0) -> 0
A27: 29 | C27: cristian kilapi | F27: Mini Recuerdo | G27: 25 | H27: 36000 | I27: -5220 | J27: 0 | K27: -540 | L27: 4075.49 | M27: -10635.98 | N27: =IF(O27="Mercado Envíos Flex","SI","NO") -> NO | O27: Correo y puntos de despacho | P27: =H27+I27+J27+K27+L27+M27 -> 23679.51 | Q27: =_xlfn.XLOOKUP(F27, AE:AE, AF:AF) * G27 -> 8175 | R27: =IF(N27="Si", P27-Q27-L27, P27-Q27) -> 15504.51 | S27: =R27*0.05 -> 775.2255 | T27: =R27*$T$2 -> 310.0902 | V27: =IF(N27= "Si",L27,0) -> 0
A28: 30 | C28: EDIT NORA MAITINI | F28: Choco Suelto | G28: 25 | H28: 22500 | I28: -3060 | J28: -2300 | K28: 0 | L28: 7370.99 | M28: 0 | N28: =IF(O28="Mercado Envíos Flex","SI","NO") -> SI | O28: Mercado Envíos Flex | P28: =H28+I28+J28+K28+L28+M28 -> 24510.99 | Q28: =_xlfn.XLOOKUP(F28, AE:AE, AF:AF) * G28 -> 7350 | R28: =IF(N28="Si", P28-Q28-L28, P28-Q28) -> 9790 | S28: =R28*0.05 -> 489.5 | T28: =R28*$T$2 -> 195.8 | V28: =IF(N28= "Si",L28,0) -> 7370.99
A29: 31 | C29: Diana Inchauspe | F29: Choco Suelto | G29: 50 | H29: 55400 | I29: -7830.5 | J29: -5110 | K29: -831 | L29: 0 | M29: 0 | N29: =IF(O29="Mercado Envíos Flex","SI","NO") -> NO | O29: Correo y puntos de despacho | P29: =H29+I29+J29+K29+L29+M29 -> 41628.5 | Q29: =_xlfn.XLOOKUP(F29, AE:AE, AF:AF) * G29 -> 14700 | R29: =IF(N29="Si", P29-Q29-L29, P29-Q29) -> 26928.5 | S29: =R29*0.05 -> 1346.425 | T29: =R29*$T$2 -> 538.57 | V29: =IF(N29= "Si",L29,0) -> 0
N30: =IF(O30="Mercado Envíos Flex","SI","NO") -> NO | T30: =R30*$T$2 -> 0
N31: =IF(O31="Mercado Envíos Flex","SI","NO") -> NO | T31: =R31*$T$2 -> 0
A32: 34 | C32: Silvana Robel | F32: Mini Recuerdo | G32: 25 | H32: 31200 | I32: -4524 | J32: -2810 | K32: -468 | L32: 9155.99 | M32: -9155.99 | N32: =IF(O32="Mercado Envíos Flex","SI","NO") -> NO | O32: Correo y puntos de despacho | P32: =H32+I32+J32+K32+L32+M32 -> 23398 | Q32: =_xlfn.XLOOKUP(F32, AE:AE, AF:AF) * G32 -> 8175 | R32: =IF(N32="Si", P32-Q32-L32, P32-Q32) -> 15223 | S32: =R32*0.05 -> 761.15 | T32: =R32*$T$2 -> 304.46 | V32: =IF(N32= "Si",L32,0) -> 0
C33: María ines Monzo | F33: Choco Suelto | G33: 25 | H33: 25000 | I33: -3400 | J33: -2810 | K33: -450.96 | L33: 5064.14 | M33: -5064.14 | N33: =IF(O33="Mercado Envíos Flex","SI","NO") -> NO | O33: Correo y puntos de despacho | P33: 18339.04 | Q33: =_xlfn.XLOOKUP(F33, AE:AE, AF:AF) * G33 -> 7350 | R33: =IF(N33="Si", P33-Q33-L33, P33-Q33) -> 10989.04 | S33: =R33*0.05 -> 549.452 | T33: =R33*$T$2 -> 219.7808
C34: Lisi cas | F34: Choco Suelto | G34: 100 | H34: 100000 | I34: -13600 | J34: -11240 | K34: -1500 | L34: 10245.99 | M34: 0 | N34: =IF(O34="Mercado Envíos Flex","SI","NO") -> SI | O34: Mercado Envíos Flex | P34: 83905.99 | Q34: =_xlfn.XLOOKUP(F34, AE:AE, AF:AF) * G34 -> 29400 | R34: =IF(N34="Si", P34-Q34-L34, P34-Q34) -> 44260 | S34: =R34*0.05 -> 2213 | T34: =R34*$T$2 -> 885.2
C35: Myriam | F35: Choco Suelto | G35: 25 | H35: 25000 | I35: -3400 | J35: -2810 | L35: 4667.64 | M35: -4667.64 | N35: =IF(O35="Mercado Envíos Flex","SI","NO") -> NO | O35: Correo y puntos de despacho | P35: 18790 | Q35: =_xlfn.XLOOKUP(F35, AE:AE, AF:AF) * G35 -> 7350 | R35: =IF(N35="Si", P35-Q35-L35, P35-Q35) -> 11440 | S35: =R35*0.05 -> 572 | T35: =R35*$T$2 -> 228.8 | V35: =IF(N35= "Si",L35,0) -> 0
C36: Horacio Ribero | F36: Caja 44 Chocos | G36: 1 | H36: 32900 | I36: -4474.4 | J36: -2810 | K36: -558.24 | L36: 4315.94 | M36: -4315.94 | N36: =IF(O36="Mercado Envíos Flex","SI","NO") -> NO | O36: Correo y puntos de despacho | P36: 25057.36 | Q36: =_xlfn.XLOOKUP(F36, AE:AE, AF:AF) * G36 -> 12512 | R36: =IF(N36="Si", P36-Q36-L36, P36-Q36) -> 12545.36 | S36: =R36*0.05 -> 627.268 | T36: =R36*$T$2 -> 250.9072 | V36: =IF(N36= "Si",L36,0) -> 0
N37: =IF(O37="Mercado Envíos Flex","SI","NO") -> NO | Q37: =_xlfn.XLOOKUP(F37, AE:AE, AF:AF) * G37 -> 0 | R37: =IF(N37="Si", P37-Q37-L37, P37-Q37) -> 0 | S37: =R37*0.05 -> 0 | T37: =R37*$T$2 -> 0
N38: =IF(O38="Mercado Envíos Flex","SI","NO") -> NO | Q38: =_xlfn.XLOOKUP(F38, AE:AE, AF:AF) * G38 -> 0 | R38: =IF(N38="Si", P38-Q38-L38, P38-Q38) -> 0 | S38: =R38*0.05 -> 0 | T38: =R38*$T$2 -> 0
N39: =IF(O39="Mercado Envíos Flex","SI","NO") -> NO | Q39: =_xlfn.XLOOKUP(F39, AE:AE, AF:AF) * G39 -> 0 | R39: =IF(N39="Si", P39-Q39-L39, P39-Q39) -> 0 | S39: =R39*0.05 -> 0 | T39: =R39*$T$2 -> 0
N40: =IF(O40="Mercado Envíos Flex","SI","NO") -> NO | Q40: =_xlfn.XLOOKUP(F40, AE:AE, AF:AF) * G40 -> 0 | R40: =IF(N40="Si", P40-Q40-L40, P40-Q40) -> 0 | S40: =R40*0.05 -> 0 | T40: =R40*$T$2 -> 0
N41: =IF(O41="Mercado Envíos Flex","SI","NO") -> NO | Q41: =_xlfn.XLOOKUP(F41, AE:AE, AF:AF) * G41 -> 0 | R41: =IF(N41="Si", P41-Q41-L41, P41-Q41) -> 0 | S41: =R41*0.05 -> 0 | T41: =R41*$T$2 -> 0
N42: =IF(O42="Mercado Envíos Flex","SI","NO") -> NO | Q42: =_xlfn.XLOOKUP(F42, AE:AE, AF:AF) * G42 -> 0 | R42: =IF(N42="Si", P42-Q42-L42, P42-Q42) -> 0 | S42: =R42*0.05 -> 0 | T42: =R42*$T$2 -> 0
N43: =IF(O43="Mercado Envíos Flex","SI","NO") -> NO | Q43: =_xlfn.XLOOKUP(F43, AE:AE, AF:AF) * G43 -> 0 | R43: =IF(N43="Si", P43-Q43-L43, P43-Q43) -> 0 | S43: =R43*0.05 -> 0 | T43: =R43*$T$2 -> 0
N44: =IF(O44="Mercado Envíos Flex","SI","NO") -> NO | Q44: =_xlfn.XLOOKUP(F44, AE:AE, AF:AF) * G44 -> 0 | R44: =IF(N44="Si", P44-Q44-L44, P44-Q44) -> 0 | S44: =R44*0.05 -> 0 | T44: =R44*$T$2 -> 0
N45: =IF(O45="Mercado Envíos Flex","SI","NO") -> NO | Q45: =_xlfn.XLOOKUP(F45, AE:AE, AF:AF) * G45 -> 0 | R45: =IF(N45="Si", P45-Q45-L45, P45-Q45) -> 0 | S45: =R45*0.05 -> 0 | T45: =R45*$T$2 -> 0
N46: =IF(O46="Mercado Envíos Flex","SI","NO") -> NO | Q46: =_xlfn.XLOOKUP(F46, AE:AE, AF:AF) * G46 -> 0 | R46: =IF(N46="Si", P46-Q46-L46, P46-Q46) -> 0 | S46: =R46*0.05 -> 0 | T46: =R46*$T$2 -> 0
N47: =IF(O47="Mercado Envíos Flex","SI","NO") -> NO | Q47: =_xlfn.XLOOKUP(F47, AE:AE, AF:AF) * G47 -> 0 | R47: =IF(N47="Si", P47-Q47-L47, P47-Q47) -> 0 | S47: =R47*0.05 -> 0 | T47: =R47*$T$2 -> 0
N48: =IF(O48="Mercado Envíos Flex","SI","NO") -> NO | Q48: =_xlfn.XLOOKUP(F48, AE:AE, AF:AF) * G48 -> 0 | R48: =IF(N48="Si", P48-Q48-L48, P48-Q48) -> 0 | S48: =R48*0.05 -> 0 | T48: =R48*$T$2 -> 0
... N118: =IF(O118="Mercado Envíos Flex","SI","NO") -> NO | Q118: =_xlfn.XLOOKUP(F118, AE:AE, AF:AF) * G118 -> 0 | R118: =IF(N118="Si", P118-Q118-L118, P118-Q118) -> 0 | S118: =R118*0.05 -> 0 | T118: =R118*$T$2 -> 0
N119: =IF(O119="Mercado Envíos Flex","SI","NO") -> NO | Q119: =_xlfn.XLOOKUP(F119, AE:AE, AF:AF) * G119 -> 0 | R119: =IF(N119="Si", P119-Q119-L119, P119-Q119) -> 0 | S119: =R119*0.05 -> 0 | T119: =R119*$T$2 -> 0 | X119: =IF(OR(F42="D6 Classic",F42="D6 Deluxe",F42="D6 Gold"),6*G42, IF(OR(F42="D2",F42="D2 moño"),2*G42, IF(F42="Cajita de 4",4*G42, IF(OR(F42="Mini Recuerdo",F42="Choco Cintas",F42="Choco Suelto"),1*G42, IF(F42="Caja 22 Chocos",22*G42, IF(F42="Caja 44 Chocos",44*G42,"")))))) | Y119: =IF(#REF!="Falta", X119, 0) -> #REF!
N120: =IF(O120="Mercado Envíos Flex","SI","NO") -> NO | Q120: =_xlfn.XLOOKUP(F120, AE:AE, AF:AF) * G120 -> 0 | R120: =IF(N120="Si", P120-Q120-L120, P120-Q120) -> 0 | S120: =R120*0.05 -> 0 | T120: =R120*$T$2 -> 0 | X120: =IF(OR(F43="D6 Classic",F43="D6 Deluxe",F43="D6 Gold"),6*G43, IF(OR(F43="D2",F43="D2 moño"),2*G43, IF(F43="Cajita de 4",4*G43, IF(OR(F43="Mini Recuerdo",F43="Choco Cintas",F43="Choco Suelto"),1*G43, IF(F43="Caja 22 Chocos",22*G43, IF(F43="Caja 44 Chocos",44*G43,"")))))) | Y120: =IF(#REF!="Falta", X120, 0) -> #REF!
N121: =IF(O121="Mercado Envíos Flex","SI","NO") -> NO | Q121: =_xlfn.XLOOKUP(F121, AE:AE, AF:AF) * G121 -> 0 | R121: =IF(N121="Si", P121-Q121-L121, P121-Q121) -> 0 | S121: =R121*0.05 -> 0 | T121: =R121*$T$2 -> 0 | X121: =IF(OR(F44="D6 Classic",F44="D6 Deluxe",F44="D6 Gold"),6*G44, IF(OR(F44="D2",F44="D2 moño"),2*G44, IF(F44="Cajita de 4",4*G44, IF(OR(F44="Mini Recuerdo",F44="Choco Cintas",F44="Choco Suelto"),1*G44, IF(F44="Caja 22 Chocos",22*G44, IF(F44="Caja 44 Chocos",44*G44,"")))))) | Y121: =IF(#REF!="Falta", X121, 0) -> #REF!
N122: =IF(O122="Mercado Envíos Flex","SI","NO") -> NO | Q122: =_xlfn.XLOOKUP(F122, AE:AE, AF:AF) * G122 -> 0 | R122: =IF(N122="Si", P122-Q122-L122, P122-Q122) -> 0 | S122: =R122*0.05 -> 0 | T122: =R122*$T$2 -> 0 | X122: =IF(OR(F45="D6 Classic",F45="D6 Deluxe",F45="D6 Gold"),6*G45, IF(OR(F45="D2",F45="D2 moño"),2*G45, IF(F45="Cajita de 4",4*G45, IF(OR(F45="Mini Recuerdo",F45="Choco Cintas",F45="Choco Suelto"),1*G45, IF(F45="Caja 22 Chocos",22*G45, IF(F45="Caja 44 Chocos",44*G45,"")))))) | Y122: =IF(#REF!="Falta", X122, 0) -> #REF!
N123: =IF(O123="Mercado Envíos Flex","SI","NO") -> NO | Q123: =_xlfn.XLOOKUP(F123, AE:AE, AF:AF) * G123 -> 0 | R123: =IF(N123="Si", P123-Q123-L123, P123-Q123) -> 0 | S123: =R123*0.05 -> 0 | T123: =R123*$T$2 -> 0 | X123: =IF(OR(F46="D6 Classic",F46="D6 Deluxe",F46="D6 Gold"),6*G46, IF(OR(F46="D2",F46="D2 moño"),2*G46, IF(F46="Cajita de 4",4*G46, IF(OR(F46="Mini Recuerdo",F46="Choco Cintas",F46="Choco Suelto"),1*G46, IF(F46="Caja 22 Chocos",22*G46, IF(F46="Caja 44 Chocos",44*G46,"")))))) | Y123: =IF(#REF!="Falta", X123, 0) -> #REF!
N124: =IF(O124="Mercado Envíos Flex","SI","NO") -> NO | Q124: =_xlfn.XLOOKUP(F124, AE:AE, AF:AF) * G124 -> 0 | R124: =IF(N124="Si", P124-Q124-L124, P124-Q124) -> 0 | S124: =R124*0.05 -> 0 | T124: =R124*$T$2 -> 0 | X124: =IF(OR(F47="D6 Classic",F47="D6 Deluxe",F47="D6 Gold"),6*G47, IF(OR(F47="D2",F47="D2 moño"),2*G47, IF(F47="Cajita de 4",4*G47, IF(OR(F47="Mini Recuerdo",F47="Choco Cintas",F47="Choco Suelto"),1*G47, IF(F47="Caja 22 Chocos",22*G47, IF(F47="Caja 44 Chocos",44*G47,"")))))) | Y124: =IF(#REF!="Falta", X124, 0) -> #REF!
N125: =IF(O125="Mercado Envíos Flex","SI","NO") -> NO | Q125: =_xlfn.XLOOKUP(F125, AE:AE, AF:AF) * G125 -> 0 | R125: =IF(N125="Si", P125-Q125-L125, P125-Q125) -> 0 | S125: =R125*0.05 -> 0 | T125: =R125*$T$2 -> 0 | X125: =IF(OR(F48="D6 Classic",F48="D6 Deluxe",F48="D6 Gold"),6*G48, IF(OR(F48="D2",F48="D2 moño"),2*G48, IF(F48="Cajita de 4",4*G48, IF(OR(F48="Mini Recuerdo",F48="Choco Cintas",F48="Choco Suelto"),1*G48, IF(F48="Caja 22 Chocos",22*G48, IF(F48="Caja 44 Chocos",44*G48,"")))))) | Y125: =IF(#REF!="Falta", X125, 0) -> #REF!
N126: =IF(O126="Mercado Envíos Flex","SI","NO") -> NO | Q126: =_xlfn.XLOOKUP(F126, AE:AE, AF:AF) * G126 -> 0 | R126: =IF(N126="Si", P126-Q126-L126, P126-Q126) -> 0 | S126: =R126*0.05 -> 0 | T126: =R126*$T$2 -> 0 | X126: =IF(OR(F49="D6 Classic",F49="D6 Deluxe",F49="D6 Gold"),6*G49, IF(OR(F49="D2",F49="D2 moño"),2*G49, IF(F49="Cajita de 4",4*G49, IF(OR(F49="Mini Recuerdo",F49="Choco Cintas",F49="Choco Suelto"),1*G49, IF(F49="Caja 22 Chocos",22*G49, IF(F49="Caja 44 Chocos",44*G49,"")))))) | Y126: =IF(#REF!="Falta", X126, 0) -> #REF!
N127: =IF(O127="Mercado Envíos Flex","SI","NO") -> NO | Q127: =_xlfn.XLOOKUP(F127, AE:AE, AF:AF) * G127 -> 0 | R127: =IF(N127="Si", P127-Q127-L127, P127-Q127) -> 0 | S127: =R127*0.05 -> 0 | T127: =R127*$T$2 -> 0 | X127: =IF(OR(F50="D6 Classic",F50="D6 Deluxe",F50="D6 Gold"),6*G50, IF(OR(F50="D2",F50="D2 moño"),2*G50, IF(F50="Cajita de 4",4*G50, IF(OR(F50="Mini Recuerdo",F50="Choco Cintas",F50="Choco Suelto"),1*G50, IF(F50="Caja 22 Chocos",22*G50, IF(F50="Caja 44 Chocos",44*G50,"")))))) | Y127: =IF(#REF!="Falta", X127, 0) -> #REF!
N128: =IF(O128="Mercado Envíos Flex","SI","NO") -> NO | Q128: =_xlfn.XLOOKUP(F128, AE:AE, AF:AF) * G128 -> 0 | R128: =IF(N128="Si", P128-Q128-L128, P128-Q128) -> 0 | S128: =R128*0.05 -> 0 | T128: =R128*$T$2 -> 0 | X128: =IF(OR(F51="D6 Classic",F51="D6 Deluxe",F51="D6 Gold"),6*G51, IF(OR(F51="D2",F51="D2 moño"),2*G51, IF(F51="Cajita de 4",4*G51, IF(OR(F51="Mini Recuerdo",F51="Choco Cintas",F51="Choco Suelto"),1*G51, IF(F51="Caja 22 Chocos",22*G51, IF(F51="Caja 44 Chocos",44*G51,"")))))) | Y128: =IF(#REF!="Falta", X128, 0) -> #REF!
N129: =IF(O129="Mercado Envíos Flex","SI","NO") -> NO | Q129: =_xlfn.XLOOKUP(F129, AE:AE, AF:AF) * G129 -> 0 | R129: =IF(N129="Si", P129-Q129-L129, P129-Q129) -> 0 | S129: =R129*0.05 -> 0 | T129: =R129*$T$2 -> 0 | X129: =IF(OR(F52="D6 Classic",F52="D6 Deluxe",F52="D6 Gold"),6*G52, IF(OR(F52="D2",F52="D2 moño"),2*G52, IF(F52="Cajita de 4",4*G52, IF(OR(F52="Mini Recuerdo",F52="Choco Cintas",F52="Choco Suelto"),1*G52, IF(F52="Caja 22 Chocos",22*G52, IF(F52="Caja 44 Chocos",44*G52,"")))))) | Y129: =IF(#REF!="Falta", X129, 0) -> #REF!
N130: =IF(O130="Mercado Envíos Flex","SI","NO") -> NO | Q130: =_xlfn.XLOOKUP(F130, AE:AE, AF:AF) * G130 -> 0 | R130: =IF(N130="Si", P130-Q130-L130, P130-Q130) -> 0 | S130: =R130*0.05 -> 0 | T130: =R130*$T$2 -> 0 | X130: =IF(OR(F53="D6 Classic",F53="D6 Deluxe",F53="D6 Gold"),6*G53, IF(OR(F53="D2",F53="D2 moño"),2*G53, IF(F53="Cajita de 4",4*G53, IF(OR(F53="Mini Recuerdo",F53="Choco Cintas",F53="Choco Suelto"),1*G53, IF(F53="Caja 22 Chocos",22*G53, IF(F53="Caja 44 Chocos",44*G53,"")))))) | Y130: =IF(#REF!="Falta", X130, 0) -> #REF!
... N191: =IF(O191="Mercado Envíos Flex","SI","NO") -> NO | Q191: =_xlfn.XLOOKUP(F191, AE:AE, AF:AF) * G191 -> 0 | R191: =IF(N191="Si", P191-Q191-L191, P191-Q191) -> 0 | S191: =R191*0.05 -> 0 | T191: =R191*$T$2 -> 0 | X191: =IF(OR(F114="D6 Classic",F114="D6 Deluxe",F114="D6 Gold"),6*G114, IF(OR(F114="D2",F114="D2 moño"),2*G114, IF(F114="Cajita de 4",4*G114, IF(OR(F114="Mini Recuerdo",F114="Choco Cintas",F114="Choco Suelto"),1*G114, IF(F114="Caja 22 Chocos",22*G114, IF(F114="Caja 44 Chocos",44*G114,"")))))) | Y191: =IF(#REF!="Falta", X191, 0) -> #REF!
N192: =IF(O192="Mercado Envíos Flex","SI","NO") -> NO | Q192: =_xlfn.XLOOKUP(F192, AE:AE, AF:AF) * G192 -> 0 | R192: =IF(N192="Si", P192-Q192-L192, P192-Q192) -> 0 | S192: =R192*0.05 -> 0 | T192: =R192*$T$2 -> 0
N193: =IF(O193="Mercado Envíos Flex","SI","NO") -> NO | Q193: =_xlfn.XLOOKUP(F193, AE:AE, AF:AF) * G193 -> 0 | R193: =IF(N193="Si", P193-Q193-L193, P193-Q193) -> 0 | S193: =R193*0.05 -> 0 | T193: =R193*$T$2 -> 0
N194: =IF(O194="Mercado Envíos Flex","SI","NO") -> NO | Q194: =_xlfn.XLOOKUP(F194, AE:AE, AF:AF) * G194 -> 0 | R194: =IF(N194="Si", P194-Q194-L194, P194-Q194) -> 0 | S194: =R194*0.05 -> 0 | T194: =R194*$T$2 -> 0
N195: =IF(O195="Mercado Envíos Flex","SI","NO") -> NO | Q195: =_xlfn.XLOOKUP(F195, AE:AE, AF:AF) * G195 -> 0 | R195: =IF(N195="Si", P195-Q195-L195, P195-Q195) -> 0 | S195: =R195*0.05 -> 0 | T195: =R195*$T$2 -> 0
N196: =IF(O196="Mercado Envíos Flex","SI","NO") -> NO | Q196: =_xlfn.XLOOKUP(F196, AE:AE, AF:AF) * G196 -> 0 | R196: =IF(N196="Si", P196-Q196-L196, P196-Q196) -> 0 | S196: =R196*0.05 -> 0 | T196: =R196*$T$2 -> 0
N197: =IF(O197="Mercado Envíos Flex","SI","NO") -> NO | Q197: =_xlfn.XLOOKUP(F197, AE:AE, AF:AF) * G197 -> 0 | R197: =IF(N197="Si", P197-Q197-L197, P197-Q197) -> 0 | S197: =R197*0.05 -> 0 | T197: =R197*$T$2 -> 0
N198: =IF(O198="Mercado Envíos Flex","SI","NO") -> NO | Q198: =_xlfn.XLOOKUP(F198, AE:AE, AF:AF) * G198 -> 0 | R198: =IF(N198="Si", P198-Q198-L198, P198-Q198) -> 0 | S198: =R198*0.05 -> 0 | T198: =R198*$T$2 -> 0
N199: =IF(O199="Mercado Envíos Flex","SI","NO") -> NO | Q199: =_xlfn.XLOOKUP(F199, AE:AE, AF:AF) * G199 -> 0 | R199: =IF(N199="Si", P199-Q199-L199, P199-Q199) -> 0 | S199: =R199*0.05 -> 0 | T199: =R199*$T$2 -> 0
N200: =IF(O200="Mercado Envíos Flex","SI","NO") -> NO | Q200: =_xlfn.XLOOKUP(F200, AE:AE, AF:AF) * G200 -> 0 | R200: =IF(N200="Si", P200-Q200-L200, P200-Q200) -> 0 | S200: =R200*0.05 -> 0 | T200: =R200*$T$2 -> 0
N201: =IF(O201="Mercado Envíos Flex","SI","NO") -> NO | Q201: =_xlfn.XLOOKUP(F201, AE:AE, AF:AF) * G201 -> 0 | R201: =IF(N201="Si", P201-Q201-L201, P201-Q201) -> 0 | S201: =R201*0.05 -> 0 | T201: =R201*$T$2 -> 0
N202: =IF(O202="Mercado Envíos Flex","SI","NO") -> NO | Q202: =_xlfn.XLOOKUP(F202, AE:AE, AF:AF) * G202 -> 0 | R202: =IF(N202="Si", P202-Q202-L202, P202-Q202) -> 0 | S202: =R202*0.05 -> 0 | T202: =R202*$T$2 -> 0
N203: =IF(O203="Mercado Envíos Flex","SI","NO") -> NO | Q203: =_xlfn.XLOOKUP(F203, AE:AE, AF:AF) * G203 -> 0 | R203: =IF(N203="Si", P203-Q203-L203, P203-Q203) -> 0 | S203: =R203*0.05 -> 0 | T203: =R203*$T$2 -> 0
... N262: =IF(O262="Mercado Envíos Flex","SI","NO") -> NO | Q262: =_xlfn.XLOOKUP(F262, AE:AE, AF:AF) * G262 -> 0 | R262: =IF(N262="Si", P262-Q262-L262, P262-Q262) -> 0 | S262: =R262*0.05 -> 0 | T262: =R262*$T$2 -> 0
Q263: =_xlfn.XLOOKUP(F263, AE:AE, AF:AF) * G263 -> 0 | R263: =IF(N263="Si", P263-Q263-L263, P263-Q263) -> 0 | S263: =R263*0.05 -> 0 | T263: =R263*$T$2 -> 0
Q264: =_xlfn.XLOOKUP(F264, AE:AE, AF:AF) * G264 -> 0 | R264: =IF(N264="Si", P264-Q264-L264, P264-Q264) -> 0 | S264: =R264*0.05 -> 0 | T264: =R264*$T$2 -> 0
Q265: =_xlfn.XLOOKUP(F265, AE:AE, AF:AF) * G265 -> 0 | R265: =IF(N265="Si", P265-Q265-L265, P265-Q265) -> 0 | S265: =R265*0.05 -> 0 | T265: =R265*$T$2 -> 0
Q266: =_xlfn.XLOOKUP(F266, AE:AE, AF:AF) * G266 -> 0 | R266: =IF(N266="Si", P266-Q266-L266, P266-Q266) -> 0 | S266: =R266*0.05 -> 0 | T266: =R266*$T$2 -> 0
Q267: =_xlfn.XLOOKUP(F267, AE:AE, AF:AF) * G267 -> 0 | R267: =IF(N267="Si", P267-Q267-L267, P267-Q267) -> 0 | S267: =R267*0.05 -> 0 | T267: =R267*$T$2 -> 0
Q268: =_xlfn.XLOOKUP(F268, AE:AE, AF:AF) * G268 -> 0 | R268: =IF(N268="Si", P268-Q268-L268, P268-Q268) -> 0 | S268: =R268*0.05 -> 0 | T268: =R268*$T$2 -> 0
Q269: =_xlfn.XLOOKUP(F269, AE:AE, AF:AF) * G269 -> 0 | R269: =IF(N269="Si", P269-Q269-L269, P269-Q269) -> 0 | S269: =R269*0.05 -> 0 | T269: =R269*$T$2 -> 0
Q270: =_xlfn.XLOOKUP(F270, AE:AE, AF:AF) * G270 -> 0 | R270: =IF(N270="Si", P270-Q270-L270, P270-Q270) -> 0 | S270: =R270*0.05 -> 0 | T270: =R270*$T$2 -> 0
Q271: =_xlfn.XLOOKUP(F271, AE:AE, AF:AF) * G271 -> 0 | R271: =IF(N271="Si", P271-Q271-L271, P271-Q271) -> 0 | S271: =R271*0.05 -> 0 | T271: =R271*$T$2 -> 0
Q272: =_xlfn.XLOOKUP(F272, AE:AE, AF:AF) * G272 -> 0 | R272: =IF(N272="Si", P272-Q272-L272, P272-Q272) -> 0 | S272: =R272*0.05 -> 0 | T272: =R272*$T$2 -> 0
Q273: =_xlfn.XLOOKUP(F273, AE:AE, AF:AF) * G273 -> 0 | R273: =IF(N273="Si", P273-Q273-L273, P273-Q273) -> 0 | S273: =R273*0.05 -> 0 | T273: =R273*$T$2 -> 0
Q274: =_xlfn.XLOOKUP(F274, AE:AE, AF:AF) * G274 -> 0 | R274: =IF(N274="Si", P274-Q274-L274, P274-Q274) -> 0 | S274: =R274*0.05 -> 0 | T274: =R274*$T$2 -> 0
... Q398: =_xlfn.XLOOKUP(F398, AE:AE, AF:AF) * G398 -> 0 | R398: =IF(N398="Si", P398-Q398-L398, P398-Q398) -> 0 | S398: =R398*0.05 -> 0 | T398: =R398*$T$2 -> 0
Q399: =_xlfn.XLOOKUP(F399, AE:AE, AF:AF) * G399 -> 0 | R399: =IF(N399="Si", P399-Q399-L399, P399-Q399) -> 0 | T399: =R399*$T$2 -> 0
Q400: =_xlfn.XLOOKUP(F400, AE:AE, AF:AF) * G400 -> 0 | R400: =IF(N400="Si", P400-Q400-L400, P400-Q400) -> 0 | T400: =R400*$T$2 -> 0
Q401: =_xlfn.XLOOKUP(F401, AE:AE, AF:AF) * G401 -> 0 | R401: =IF(N401="Si", P401-Q401-L401, P401-Q401) -> 0 | T401: =R401*$T$2 -> 0
Q402: =_xlfn.XLOOKUP(F402, AE:AE, AF:AF) * G402 -> 0 | R402: =IF(N402="Si", P402-Q402-L402, P402-Q402) -> 0 | T402: =R402*$T$2 -> 0
Q403: =_xlfn.XLOOKUP(F403, AE:AE, AF:AF) * G403 -> 0 | R403: =IF(N403="Si", P403-Q403-L403, P403-Q403) -> 0 | T403: =R403*$T$2 -> 0
Q404: =_xlfn.XLOOKUP(F404, AE:AE, AF:AF) * G404 -> 0 | R404: =IF(N404="Si", P404-Q404-L404, P404-Q404) -> 0 | T404: =R404*$T$2 -> 0
Q405: =_xlfn.XLOOKUP(F405, AE:AE, AF:AF) * G405 -> 0 | R405: =IF(N405="Si", P405-Q405-L405, P405-Q405) -> 0 | T405: =R405*$T$2 -> 0
Q406: =_xlfn.XLOOKUP(F406, AE:AE, AF:AF) * G406 -> 0 | R406: =IF(N406="Si", P406-Q406-L406, P406-Q406) -> 0 | T406: =R406*$T$2 -> 0
Q407: =_xlfn.XLOOKUP(F407, AE:AE, AF:AF) * G407 -> 0 | R407: =IF(N407="Si", P407-Q407-L407, P407-Q407) -> 0 | T407: =R407*$T$2 -> 0
Q408: =_xlfn.XLOOKUP(F408, AE:AE, AF:AF) * G408 -> 0 | R408: =IF(N408="Si", P408-Q408-L408, P408-Q408) -> 0 | T408: =R408*$T$2 -> 0
Q409: =_xlfn.XLOOKUP(F409, AE:AE, AF:AF) * G409 -> 0 | R409: =IF(N409="Si", P409-Q409-L409, P409-Q409) -> 0 | T409: =R409*$T$2 -> 0
Q410: =_xlfn.XLOOKUP(F410, AE:AE, AF:AF) * G410 -> 0 | R410: =IF(N410="Si", P410-Q410-L410, P410-Q410) -> 0 | T410: =R410*$T$2 -> 0
...

Sheet Coloniales S.C
Q1: Descontar
O2: Aumento | Q2: 0.0925
O3: 0.1
O4: 0.1 | Q4: 0.0761 | R4: =O7*Q4 -> 60.119
O5: =O3+O4 -> 0.2 | Q5: =Q3+Q4+Q2 -> 0.1686 | T5: Descuento | U5: Descuento | V5: Descuento
B6: Choco suelto simple o full color | C6: Choco | D6: Etiqueta choco | K6: Costo | L6: Ganancia | M6: Total | O6: MP | P6: MP | Q6: Ganan MP | T6: 0 | U6: 0 | V6: 0.05
C7: =Insumos!C6 -> 224 | D7: =Insumos!$G$6/28 -> 8.5685714 | F7: 40 | K7: =C7+D7 -> 232.56857 | L7: =M7-K7 -> 418.62343 | M7: =K7*2.8 -> 651.192 | O7: =ROUNDUP(P7, -1) -> 790 | P7: =M7+(M7*O5) -> 781.4304 | Q7: =O7-(O7*Q5)-K7 -> 424.23743 | T7: 50 | U7: 100 | V7: 200
T8: Costo total
B9: 2000 | C9: =Insumos!D12 -> 205.838 | D9: =Insumos!$G$6/28 -> 8.5685714 | K9: =C9+D9 -> 214.40657 | M9: =$L$7+K9 -> 633.03 | T9: =$K$7*T7 -> 11628.429 | U9: =$K$7*U7 -> 23256.857 | V9: =$K$7*V7 -> 46513.714
T10: Mercado Pago
O11: descuento | Q11: IIBB | T11: =($O7*T7)-(($O7*T7)*T6) -> 39500 | U11: =($O7*U7)-(($O7*U7)*U6) -> 79000 | V11: =($O7*V7)-(($O7*V7)*V6) -> 150100
O12: 0.1 | Q12: 0.06 | T12: =T11/T7 -> 790 | U12: =U11/U7 -> 790 | V12: =V11/V7 -> 750.5
O13: Transf | Q13: G. Transf | T13: Ganancia MP
O14: =O7-(O7*O12) -> 711 | Q14: =(O14-(O14*Q12))-#REF! -> #REF! | T14: =(T11-T9)-(T11*$Q$5) -> 21211.871 | U14: =(U11-U9)-(U11*$Q$5) -> 42423.743 | V14: =(V11-V9)-(V11*$Q$5) -> 78279.426
T15: =T14/T7 -> 424.23743 | U15: =U14/U7 -> 424.23743 | V15: =V14/V7 -> 391.39713
T16: Transferencia
T17: =T11-(T11*T18) -> 35550 | U17: =U11-(U11*U18) -> 71100 | V17: =V11-(V11*V18) -> 135090
T18: =$O$12 -> 0.1 | U18: =$O$12 -> 0.1 | V18: =$O$12 -> 0.1
T19: =T17/T7 -> 711 | U19: =U17/U7 -> 711 | V19: =V17/V7 -> 675.45
T20: Ganancia transferencia
T21: =T17-(T17*$Q$12)-T9 -> 21788.571 | U21: =U17-(U17*$Q$117)-U9 -> 42432.433 | V21: =V17-(V17*$Q$117)-V9 -> 78295.937
T22: =T21/T7 -> 435.77143 | U22: =U21/U7 -> 424.32433 | V22: =V21/V7 -> 391.47968
Q24: Descontar
O25: Aumento | Q25: 0.0925
O26: 0.1
C27: Coloniales | O27: 0.1 | Q27: 0.0761 | R27: IIBB
M28: =(M30-K30) -> 546.53714 | O28: =O26+O27 -> 0.2 | Q28: =Q26+Q27+Q25 -> 0.1686 | T28: Descuento | U28: Descuento | V28: Descuento
B29: Mini Recuerdo | C29: Choco | D29: Etiqueta | E29: Tarjeta | K29: Costo real | L29: Ganancia | M29: Total | O29: MP | P29: MP | Q29: Ganan MP | T29: 0.05 | U29: 0.1 | V29: 0.15
C30: =C7 -> 224 | D30: =D7 -> 8.5685714 | E30: =Insumos!G12/10 -> 40.7 | K30: =SUM(C30:E30) -> 273.26857 | L30: =M30-K30 -> 546.53714 | M30: =K30*3 -> 819.80571 | O30: =ROUNDUP(P30, -1) -> 990 | P30: =M30+(M30*O28) -> 983.76686 | Q30: =O30-(O30*Q28)-K30 -> 549.81743 | T30: 50 | U30: 100 | V30: 200
T31: Costo total | U31: Costo total | V31: Costo total
T32: =$K$30*T30 -> 13663.429 | U32: =$K$30*U30 -> 27326.857 | V32: =$K$30*V30 -> 54653.714
T33: MP | U33: MP | V33: MP
O34: descuento | Q34: IIBB | T34: =($O30*T30)-(($O30*T30)*T29) -> 47025 | U34: =($O30*U30)-(($O30*U30)*U29) -> 89100 | V34: =($O30*V30)-(($O30*V30)*V29) -> 168300
O35: 0.1 | Q35: 0.06 | T35: =T34/T30 -> 940.5 | U35: =U34/U30 -> 891 | V35: =V34/V30 -> 841.5
O36: Transf | Q36: G. Transf | T36: Ganancia MP | U36: Ganancia MP | V36: Ganancia MP
O37: =O30-(O30*O35) -> 891 | Q37: =(O37-(O37*Q35))-K30 -> 564.27143 | T37: =(T34-T32)-(T34*$Q$28) -> 25433.156 | U37: =(U34-U32)-(U34*$Q$28) -> 46750.883 | V37: =(V34-V32)-(V34*$Q$28) -> 85270.906
T38: =T37/T30 -> 508.66313 | U38: =U37/U30 -> 467.50883 | V38: =V37/V30 -> 426.35453
T39: Transf | U39: Transf | V39: Transf
T40: =T34-(T34*T41) -> 42322.5 | U40: =U34-(U34*U41) -> 80190 | V40: =V34-(V34*V41) -> 151470
T41: =$O$12 -> 0.1 | U41: =$O$12 -> 0.1 | V41: =$O$12 -> 0.1
M42: =K32*130 -> 0 | T42: =T40/T30 -> 846.45 | U42: =U40/U30 -> 801.9 | V42: =V40/V30 -> 757.35
T43: Ganancia trans | U43: Ganancia trans | V43: Ganancia trans
Q44: Descontar | T44: =T40-(T40*$Q$12)-T32 -> 26119.721 | U44: =U40-(U40*$Q$12)-U32 -> 48051.743 | V44: =V40-(V40*$Q$117)-V32 -> 85289.419
O45: Aumento | Q45: 0.0925 | T45: =T44/T30 -> 522.39443 | U45: =U44/U30 -> 480.51743 | V45: =V44/V30 -> 426.44709
O46: 0.1
O47: 0.1 | Q47: 0.0761
M48: =(M50-K50) -> 555.12114 | O48: =O46+O47 -> 0.2 | Q48: =Q46+Q47+Q45 -> 0.1686 | T48: Descuento | U48: Descuento | V48: Descuento | W48: Descuento | X48: Descuento | Y48: Descuento
B49: Tarjeta con choco | C49: Choco | D49: Etiqueta choco | E49: Tarjeta | K49: Costo real | L49: Ganancia | M49: Total | O49: MP | P49: MP | Q49: Ganan MP | T49: 0.05 | U49: 0.1 | V49: 0.15 | W49: 0.2 | X49: 0.25 | Y49: 0.3
C50: =C30 -> 224 | D50: =Insumos!G6/28 -> 8.5685714 | E50: =(Insumos!G6/10)+(Insumos!G33/10) -> 44.992 | K50: =SUM(C50:E50) -> 277.56057 | L50: =M50-K50 -> 555.12114 | M50: =K50*3 -> 832.68171 | O50: =ROUNDUP(P50, -1) -> 1000 | P50: =M50+(M50*O48) -> 999.21806 | Q50: =O50-(O50*Q48)-K50 -> 553.83943 | T50: 50 | U50: 100 | V50: 200 | W50: 500 | X50: 1000 | Y50: 2000
T51: Costo total | U51: Costo total | V51: Costo total | W51: Costo total | X51: Costo total | Y51: Costo total
B52: 100 | C52: =C32 -> 0 | D52: =D50 -> 8.5685714 | E52: =E50 -> 44.992 | K52: =SUM(C52:E52) -> 53.560571 | T52: =K50*T50 -> 13878.029 | U52: =K52*U50 -> 5356.0571 | V52: =K54*V50 -> 10712.114 | W52: =K56*W50 -> 26780.286 | X52: =K58*X50 -> 53560.571 | Y52: =K60*Y50 -> 107121.14
T53: MP | U53: MP | V53: MP | W53: MP | X53: MP | Y53: MP
B54: 200 | C54: =C34 -> 0 | D54: =D52 -> 8.5685714 | E54: =E50 -> 44.992 | K54: =SUM(C54:E54) -> 53.560571 | M54: 0.2 | O54: descuento | Q54: IIBB | T54: =($O50*T50)-(($O50*T50)*T49) -> 47500 | U54: =($O50*U50)-(($O50*U50)*U49) -> 90000 | V54: =($O50*V50)-(($O50*V50)*V49) -> 170000 | W54: =($O50*W50)-(($O50*W50)*W49) -> 400000 | X54: =($O50*X50)-(($O50*X50)*X49) -> 750000 | Y54: =($O50*Y50)-(($O50*Y50)*Y49) -> 1400000
O55: 0.1 | Q55: 0.06 | T55: =T54/T50 -> 950 | U55: =U54/U50 -> 900 | V55: =V54/V50 -> 850 | W55: =W54/W50 -> 800 | X55: =X54/X50 -> 750 | Y55: =Y54/Y50 -> 700
B56: 500 | C56: =C36 -> 0 | D56: =D54 -> 8.5685714 | E56: =E50 -> 44.992 | K56: =SUM(C56:E56) -> 53.560571 | O56: Transf | Q56: G. Transf | T56: Ganancia MP | U56: Ganancia MP | V56: Ganancia MP | W56: Ganancia MP | X56: Ganancia MP | Y56: Ganancia MP
O57: =O50-(O50*O55) -> 900 | Q57: =(O57-(O57*Q55))-K50 -> 568.43943 | T57: =(T54-T52)-(T54*$Q$28) -> 25613.471 | U57: =(U54-U52)-(U54*$Q$28) -> 69469.943 | V57: =(V54-V52)-(V54*$Q$28) -> 130625.89 | W57: =(W54-W52)-(W54*$Q$28) -> 305779.71 | X57: =(X54-X52)-(X54*$Q$28) -> 569989.43 | Y57: =(Y54-Y52)-(Y54*$Q$28) -> 1056838.9
B58: 1000 | C58: =C38 -> 0 | D58: =D56 -> 8.5685714 | E58: =E50 -> 44.992 | K58: =SUM(C58:E58) -> 53.560571 | T58: =T57/T50 -> 512.26943 | U58: =U57/U50 -> 694.69943 | V58: =V57/V50 -> 653.12943 | W58: =W57/W50 -> 611.55943 | X58: =X57/X50 -> 569.98943 | Y58: =Y57/Y50 -> 528.41943
T59: Transf | U59: Transf | V59: Transf | W59: Transf | X59: Transf | Y59: Transf
B60: 2000 | C60: =C40 -> 0 | D60: =D58 -> 8.5685714 | E60: =E50 -> 44.992 | K60: =SUM(C60:E60) -> 53.560571 | T60: =T54-(T54*T61) -> 42750 | U60: =U54-(U54*U61) -> 81000 | V60: =V54-(V54*V61) -> 153000 | W60: =W54-(W54*W61) -> 360000 | X60: =X54-(X54*X61) -> 675000 | Y60: =Y54-(Y54*Y61) -> 1260000
T61: =$O$12 -> 0.1 | U61: =$O$12 -> 0.1 | V61: =$O$12 -> 0.1 | W61: =$O$12 -> 0.1 | X61: =$O$12 -> 0.1 | Y61: =$O$12 -> 0.1
T62: =T60/T50 -> 855 | U62: =U60/U50 -> 810 | V62: =V60/V50 -> 765 | W62: =W60/W50 -> 720 | X62: =X60/X50 -> 675 | Y62: =Y60/Y50 -> 630
T63: Ganancia trans | U63: Ganancia trans | V63: Ganancia trans | W63: Ganancia trans | X63: Ganancia trans | Y63: Ganancia trans
T64: =T60-(T60*$Q$12)-T52 -> 26306.971 | U64: =U60-(U60*$Q$12)-U52 -> 70783.943 | V64: =V60-(V60*$Q$117)-V52 -> 130644.59 | W64: =W60-(W60*$Q$117)-W52 -> 305823.71 | X64: =X60-(X60*$Q$117)-X52 -> 570071.93 | Y64: =Y60-(Y60*$Q$117)-Y52 -> 1056992.9
T65: =T64/T50 -> 526.13943 | U65: =U64/U50 -> 707.83943 | V65: =V64/V50 -> 653.22293 | W65: =W64/W50 -> 611.64743 | X65: =X64/X50 -> 570.07193 | Y65: =Y64/Y50 -> 528.49643
Q66: Descontar
O67: Aumento | Q67: 0.0925
O68: 0.1
O69: 0.1 | Q69: 0.0761
M70: =(M72-K72) -> 780.08381 | O70: =O68+O69 -> 0.2 | Q70: =Q68+Q69+Q67 -> 0.1686 | T70: Descuento | U70: Descuento | V70: Descuento | W70: Descuento | X70: Descuento | Y70: Descuento
B71: Señalador Choco 17*6 | C71: Choco | D71: Etiqueta choco | E71: Tarjeta | K71: Costo real | L71: Ganancia | M71: Total | O71: MP | P71: MP | Q71: Ganan MP | T71: 0 | U71: 0 | V71: 0 | W71: 0.05 | X71: 0.1 | Y71: 0.15
C72: =C50 -> 224 | D72: =Insumos!G6/28 -> 8.5685714 | E72: =(Insumos!G6/6)+(Insumos!G33/12)+(Insumos!G6/6) -> 97.473333 | K72: =SUM(C72:E72)+60 -> 390.0419 | L72: =M72-K72 -> 780.08381 | M72: =K72*3 -> 1170.1257 | O72: =ROUNDUP(P72, -1) -> 1410 | P72: =M72+(M72*O70) -> 1404.1509 | Q72: =O72-(O72*Q70)-K72 -> 782.2321 | T72: 50 | U72: 100 | V72: 200 | W72: 500 | X72: 1000 | Y72: 2000
T73: Costo total | U73: Costo total | V73: Costo total | W73: Costo total | X73: Costo total | Y73: Costo total
B74: 100 | C74: =C52 -> 0 | D74: =D72 -> 8.5685714 | E74: =E72 -> 97.473333 | K74: =SUM(C74:E74)+60 -> 166.0419 | T74: =K72*T72 -> 19502.095 | U74: =K74*U72 -> 16604.19 | V74: =K76*V72 -> 33208.381 | W74: =K78*W72 -> 83020.952 | X74: =K80*X72 -> 166041.9 | Y74: =K82*Y72 -> 332083.81
T75: MP | U75: MP | V75: MP | W75: MP | X75: MP | Y75: MP
B76: 200 | C76: =C54 -> 0 | D76: =D74 -> 8.5685714 | E76: =E72 -> 97.473333 | K76: =SUM(C76:E76)+60 -> 166.0419 | M76: 0.2 | O76: descuento | Q76: IIBB | T76: =($O72*T72)-(($O72*T72)*T71) -> 70500 | U76: =($O72*U72)-(($O72*U72)*U71) -> 141000 | V76: =($O72*V72)-(($O72*V72)*V71) -> 282000 | W76: =($O72*W72)-(($O72*W72)*W71) -> 669750 | X76: =($O72*X72)-(($O72*X72)*X71) -> 1269000 | Y76: =($O72*Y72)-(($O72*Y72)*Y71) -> 2397000
O77: 0.1 | Q77: 0.06 | T77: =T76/T72 -> 1410 | U77: =U76/U72 -> 1410 | V77: =V76/V72 -> 1410 | W77: =W76/W72 -> 1339.5 | X77: =X76/X72 -> 1269 | Y77: =Y76/Y72 -> 1198.5
B78: 500 | C78: =C56 -> 0 | D78: =D76 -> 8.5685714 | E78: =E72 -> 97.473333 | K78: =SUM(C78:E78)+60 -> 166.0419 | O78: Transf | Q78: G. Transf | T78: Ganancia MP | U78: Ganancia MP | V78: Ganancia MP | W78: Ganancia MP | X78: Ganancia MP | Y78: Ganancia MP
O79: =O72-(O72*O77) -> 1269 | Q79: =(O79-(O79*Q77))-K72 -> 802.8181 | T79: =(T76-T74)-(T76*$Q$28) -> 39111.605 | U79: =(U76-U74)-(U76*$Q$28) -> 100623.21 | V79: =(V76-V74)-(V76*$Q$28) -> 201246.42 | W79: =(W76-W74)-(W76*$Q$28) -> 473809.2 | X79: =(X76-X74)-(X76*$Q$28) -> 889004.7 | Y79: =(Y76-Y74)-(Y76*$Q$28) -> 1660782
B80: 1000 | C80: =C58 -> 0 | D80: =D78 -> 8.5685714 | E80: =E72 -> 97.473333 | K80: =SUM(C80:E80)+60 -> 166.0419 | T80: =T79/T72 -> 782.2321 | U80: =U79/U72 -> 1006.2321 | V80: =V79/V72 -> 1006.2321 | W80: =W79/W72 -> 947.6184 | X80: =X79/X72 -> 889.0047 | Y80: =Y79/Y72 -> 830.391
T81: Transf | U81: Transf | V81: Transf | W81: Transf | X81: Transf | Y81: Transf
B82: 2000 | C82: =C60 -> 0 | D82: =D80 -> 8.5685714 | E82: =E72 -> 97.473333 | K82: =SUM(C82:E82)+60 -> 166.0419 | T82: =T76-(T76*T83) -> 63450 | U82: =U76-(U76*U83) -> 126900 | V82: =V76-(V76*V83) -> 253800 | W82: =W76-(W76*W83) -> 602775 | X82: =X76-(X76*X83) -> 1142100 | Y82: =Y76-(Y76*Y83) -> 2157300
T83: =$O$12 -> 0.1 | U83: =$O$12 -> 0.1 | V83: =$O$12 -> 0.1 | W83: =$O$12 -> 0.1 | X83: =$O$12 -> 0.1 | Y83: =$O$12 -> 0.1
T84: =T82/T72 -> 1269 | U84: =U82/U72 -> 1269 | V84: =V82/V72 -> 1269 | W84: =W82/W72 -> 1205.55 | X84: =X82/X72 -> 1142.1 | Y84: =Y82/Y72 -> 1078.65
T85: Ganancia trans | U85: Ganancia trans | V85: Ganancia trans | W85: Ganancia trans | X85: Ganancia trans | Y85: Ganancia trans
T86: =T82-(T82*$Q$12)-T74 -> 40140.905 | U86: =U82-(U82*$Q$12)-U74 -> 102681.81 | V86: =V82-(V82*$Q$117)-V74 -> 201277.44 | W86: =W82-(W82*$Q$117)-W74 -> 473882.87 | X86: =X82-(X82*$Q$117)-X74 -> 889144.29 | Y86: =Y82-(Y82*$Q$117)-Y74 -> 1661045.7
T87: =T86/T72 -> 802.8181 | U87: =U86/U72 -> 1026.8181 | V87: =V86/V72 -> 1006.3872 | W87: =W86/W72 -> 947.76574 | X87: =X86/X72 -> 889.14429 | Y87: =Y86/Y72 -> 830.52283
Q90: Descontar
O91: Aumento | Q91: 0.0925
O92: 0.1
O93: 0.1 | Q93: 0.0761
M94: =(M96-K96) -> 2231.1026 | O94: =O92+O93 -> 0.2 | Q94: =Q92+Q93+Q91 -> 0.1686 | T94: Descuento | U94: Descuento | V94: Descuento | W94: Descuento | X94: Descuento | Y94: Descuento
B95: Cajita de 4 | C95: Chocos | D95: Eti. Choco | E95: Caja | K95: Costo real | L95: Ganancia | M95: Total | O95: MP | P95: MP | Q95: Ganan MP | T95: 0 | U95: 0.05 | V95: 0.1 | W95: 0.15 | X95: 0.2 | Y95: 0.25
C96: =C72*4 -> 896 | D96: =(Insumos!G30/28)*4 -> 19.501429 | E96: =Insumos!N20 -> 324 | K96: =SUM(C96:E96) -> 1239.5014 | L96: =M96-K96 -> 2231.1026 | M96: =K96*2.8 -> 3470.604 | O96: =ROUNDUP(P96, -1) -> 4170 | P96: =M96+(M96*O94) -> 4164.7248 | Q96: =O96-(O96*Q94)-K96 -> 2227.4366 | T96: 50 | U96: 100 | V96: 200 | W96: 500 | X96: 1000 | Y96: 2000
T97: Costo total | U97: Costo total | V97: Costo total | W97: Costo total | X97: Costo total | Y97: Costo total
B98: 100 | C98: =C74*4 -> 0 | D98: =D96 -> 19.501429 | E98: =E96 -> 324 | K98: =SUM(C98:E98) -> 343.50143 | T98: =K96*T96 -> 61975.071 | U98: =K98*U96 -> 34350.143 | V98: =K100*V96 -> 68700.286 | W98: =K102*W96 -> 171750.71 | X98: =K104*X96 -> 343501.43 | Y98: =K106*Y96 -> 687002.86
T99: MP | U99: MP | V99: MP | W99: MP | X99: MP | Y99: MP
B100: 200 | C100: =C76*4 -> 0 | D100: =D98 -> 19.501429 | E100: =E96 -> 324 | K100: =SUM(C100:E100) -> 343.50143 | M100: 0.2 | O100: descuento | Q100: IIBB | T100: =($O96*T96)-(($O96*T96)*T95) -> 208500 | U100: =($O96*U96)-(($O96*U96)*U95) -> 396150 | V100: =($O96*V96)-(($O96*V96)*V95) -> 750600 | W100: =($O96*W96)-(($O96*W96)*W95) -> 1772250 | X100: =($O96*X96)-(($O96*X96)*X95) -> 3336000 | Y100: =($O96*Y96)-(($O96*Y96)*Y95) -> 6255000
O101: 0.1 | Q101: 0.06 | T101: =T100/T96 -> 4170 | U101: =U100/U96 -> 3961.5 | V101: =V100/V96 -> 3753 | W101: =W100/W96 -> 3544.5 | X101: =X100/X96 -> 3336 | Y101: =Y100/Y96 -> 3127.5
B102: 500 | C102: =C78*4 -> 0 | D102: =D100 -> 19.501429 | E102: =E96 -> 324 | K102: =SUM(C102:E102) -> 343.50143 | O102: Transf | Q102: G. Transf | T102: Ganancia MP | U102: Ganancia MP | V102: Ganancia MP | W102: Ganancia MP | X102: Ganancia MP | Y102: Ganancia MP
O103: =O96-(O96*O101) -> 3753 | Q103: =(O103-(O103*Q101))-K96 -> 2288.3186 | T103: =(T100-T98)-(T100*$Q$5) -> 111371.83 | U103: =(U100-U98)-(U100*$Q$5) -> 295008.97 | V103: =(V100-V98)-(V100*$Q$5) -> 555348.55 | W103: =(W100-W98)-(W100*$Q$5) -> 1301697.9 | X103: =(X100-X98)-(X100*$Q$5) -> 2430049 | Y103: =(Y100-Y98)-(Y100*$Q$5) -> 4513404.1
...

Sheet $ Mercado Libre $
E1: 1100 | G1: 2300 | I1: 2810 | K1: 6300 | M1: 1400 | N1: 33000 | O1: 613000
C2: Producto | D2: Unidades | E2: costo unidad | F2: COSTO TOTAL | G2: $ Venta Por Unidad | H2: Venta Total | I2: % | J2: 0.02 | L2: Envio | M2: Costo extra | N2: $ EN ML | O2: Cuanto queda | P2: Impuesto | Q2: $ C/U | R2: Cuanto $ Afuera
G3: Por unidad | M3: 15000 | P3: 0.06
M4: 25000 | R4: $ Transf | S4: Packaging
G5: Chocos Sueltos
C6: Chocos Sueltos | D6: 10 | E6: ='Coloniales S.C'!K7 -> 232.56857 | F6: =E6*D6 -> 2325.6857 | G6: ='Coloniales S.C'!M7 -> 651.192 | H6: =(G6*D6)+S6 -> 8511.92 | I6: 0.43 | J6: 0.145 | K6: =N6*J6 -> 1764.9466 | M6: =IF(N6<=$M$3,$E$1,IF(N6<=$M$4,$G$1,IF(N6<=$N$1,$I$1,0))) -> 1100 | N6: =H6+(H6*I6) -> 12172.046 | O6: =N6 - K6 - P7 - M6-L6 -> 8576.7763 | R6: =G6*D6 -> 6511.92 | S6: 2000
H7: =O6-F6-$S$6 -> 4251.0905 | J7: 0.06 | O7: =O6-F6 -> 6251.0905 | P7: =N6*J7 -> 730.32274
D8: 1 | E8: =[1]Precios!M147*D8 -> 1126.4923 | G8: =[1]Precios!#REF!*D8 -> #REF! | I8: 0.6 | J8: 0.145 | K8: =(N8*J8) -> #REF! | M8: =IF(N8<$N$1,"600", "0") -> #REF! | N8: =(G8+(G8*I8)) -> #REF! | O8: =(N8 -P9-K8-M8-#REF!) -> #REF!
G9: =O8-E8 -> #REF! | P9: =(N8*$P$3) -> #REF!
S10: Packaging mas Flex
D11: 25 | E11: =$E$6 -> 232.56857 | F11: =E11*D11 -> 5814.2143 | G11: =G6 -> 651.192 | H11: =(G11*D11)+S6 -> 18279.8 | I11: 0.45 | J11: 0.145 | K11: =N11*J11 -> 3843.3279 | M11: =IF(N11<=$M$3,$E$1,IF(N11<=$M$4,$G$1,IF(N11<=$N$1,$I$1,0))) -> 2810 | N11: =H11+(H11*I11) -> 26505.71 | O11: =N11 - K11 - P12 - M11 -> 18262.039 | R11: =G11*D11 -> 16279.8 | S11: 4000
H12: =O11-F11-$S$6 -> 10447.825 | J12: 0.06 | P12: =N11*J12 -> 1590.3426
D16: 50 | E16: =$E$6 -> 232.56857 | F16: =E16*D16 -> 11628.429 | G16: ='Coloniales S.C'!$M$7 -> 651.192 | H16: =(G16*D16)+$S$6 -> 34559.6 | I16: 0.45 | J16: 0.145 | K16: =N16*J16 -> 7266.1559 | L16: 7000 | M16: =IF(N16<=$M$3,$E$1,IF(N16<=$M$4,$G$1,IF(N16<=$N$1,$I$1,0))) -> 0 | N16: =H16+(H16*I16) -> 50111.42 | O16: =N16 - K16 - P17 - M16-L16 -> 32838.579 | R16: =G16*D16 -> 32559.6
H17: =O16-F16-$S$6 -> 19210.15 | J17: 0.06 | P17: =N16*J17 -> 3006.6852
D19: 100 | E19: =$E$6 -> 232.56857 | F19: =E19*D19 -> 23256.857 | G19: ='Coloniales S.C'!$M$7 -> 651.192 | H19: =(G19*D19)+S6 -> 67119.2 | I19: 0.4 | J19: 0.145 | K19: =N19*J19 -> 13625.198 | L19: 7000 | M19: =IF(N19<=$M$3,$E$1,IF(N19<=$M$4,$G$1,IF(N19<=$N$1,$I$1,0))) -> 0 | N19: =H19+(H19*I19) -> 93966.88 | O19: =N19 - K19 - P20 - M19-L19 -> 67703.67 | R19: =G19*D19 -> 65119.2
H20: =O19-F19-$S$6 -> 42446.812 | J20: 0.06 | P20: =N19*J20 -> 5638.0128
G22: Mini Recuerdos
C23: Mini recuerdos | D23: 10 | E23: ='Coloniales S.C'!K30 -> 273.26857 | F23: =E23*D23 -> 2732.6857 | G23: =('Coloniales S.C'!M30) -> 819.80571 | H23: =(G23*D23)+$S$6 -> 10198.057 | I23: 0.4 | J23: 0.145 | K23: =N23*J23 -> 2070.2056 | M23: =IF(N23<=$M$3,$E$1,IF(N23<=$M$4,$G$1,IF(N23<=$N$1,$I$1,0))) -> 1100 | N23: =H23+(H23*I23) -> 14277.28 | O23: =N23 - K23 - P24 - M23-L23 -> 10250.438 | Q23: =N23/D23 -> 1427.728 | R23: =G23*D23 -> 8198.0571
H24: =O23-F23-$S$6 -> 5517.7519 | J24: 0.06 | P24: =N23*J24 -> 856.6368
D26: 20 | E26: ='Coloniales S.C'!K30 -> 273.26857 | F26: =E26*D26 -> 5465.3714 | G26: =('Coloniales S.C'!M30) -> 819.80571 | H26: =(G26*D26)+$S$6 -> 18396.114 | I26: 0.45 | J26: 0.145 | K26: =N26*J26 -> 3867.783 | M26: =IF(N26<=$M$3,$E$1,IF(N26<=$M$4,$G$1,IF(N26<=$N$1,$I$1,0))) -> 2810 | N26: =H26+(H26*I26) -> 26674.366 | O26: =N26 - K26 - P27 - M26-L26 -> 18396.121 | Q26: =N26/D26 -> 1333.7183 | R26: =G26*D26 -> 16396.114
H27: =O26-F26-$S$6 -> 10930.749 | J27: 0.06 | P27: =N26*J27 -> 1600.4619
D29: 50 | E29: ='Coloniales S.C'!K30 -> 273.26857 | F29: =E29*D29 -> 13663.429 | G29: ='Coloniales S.C'!M30 -> 819.80571 | H29: =(G29*D29)+S6 -> 42990.286 | I29: 0.46 | J29: 0.145 | K29: =N29*J29 -> 9101.0435 | L29: 7000 | M29: =IF(N29<=$M$3,$E$1,IF(N29<=$M$4,$G$1,IF(N29<=$N$1,$I$1,0))) -> 0 | N29: =H29+(H29*I29) -> 62765.817 | O29: =N29 - K29 - P30 - M29-L29 -> 42898.825 | Q29: =N29/D29 -> 1255.3163 | R29: =G29*D29 -> 40990.286
H30: =O29-F29-$S$6 -> 27235.396 | J30: 0.06 | P30: =N29*J30 -> 3765.949
D32: 100 | E32: =E29 -> 273.26857 | F32: =E32*D32 -> 27326.857 | G32: =G29 -> 819.80571 | H32: =(G32*D32)+$S$6 -> 83980.571 | I32: 0.4 | J32: 0.145 | K32: =N32*J32 -> 17048.056 | L32: 9357 | M32: =IF(N32<=$M$3,$E$1,IF(N32<=$M$4,$G$1,IF(N32<=$N$1,$I$1,0))) -> 0 | N32: =H32+(H32*I32) -> 117572.8 | O32: =N32 - K32 - P33 - M32-L32 -> 84113.376 | Q32: =N32/D32 -> 1175.728 | R32: =G32*D32 -> 81980.571
H33: =O32-F32-$S$6 -> 54786.519 | J33: 0.06 | P33: =N32*J33 -> 7054.368
G35: Tarjetas Firmes
C36: Tarjetas Flex | D36: 10 | E36: ='Coloniales S.C'!K50 -> 277.56057 | F36: =E36*D36 -> 2775.6057 | G36: ='Coloniales S.C'!M50 -> 832.68171 | H36: =(G36*D36)+$S$11 -> 12326.817 | I36: 0.4 | J36: 0.145 | K36: =N36*J36 -> 2502.3439 | M36: =IF(N36<=$M$3,$E$1,IF(N36<=$M$4,$G$1,IF(N36<=$N$1,$I$1,0))) -> 2300 | N36: =H36+(H36*I36) -> 17257.544 | O36: =N36 - K36 - P37 - M36-L36 -> 11419.747 | R36: =G36*D36 -> 8326.8171
H37: =O36-F36-$S$6 -> 6644.1418 | J37: 0.06 | P37: =N36*J37 -> 1035.4526
D39: 30 | E39: =E36 -> 277.56057 | F39: =E39*D39 -> 8326.8171 | G39: =G36 -> 832.68171 | H39: =(G39*D39)+$S$6 -> 26980.451 | I39: 0.4 | J39: 0.145 | K39: =N39*J39 -> 5477.0316 | M39: =IF(N39<=$M$3,$E$1,IF(N39<=$M$4,$G$1,IF(N39<=$N$1,$I$1,0))) -> 0 | N39: =H39+(H39*I39) -> 37772.632 | O39: =N39 - K39 - P40 - M39-L39 -> 30029.242 | R39: =G39*D39 -> 24980.451
H40: =O39-F39-$S$6 -> 19702.425 | J40: 0.06 | P40: =N39*J40 -> 2266.3579
D42: 50 | E42: =$E$36 -> 277.56057 | F42: =E42*D42 -> 13878.029 | G42: =$G$36 -> 832.68171 | H42: =(G42*D42)+$S$6 -> 43634.086 | I42: 0.4 | J42: 0.145 | K42: =N42*J42 -> 8857.7194 | M42: =IF(N42<=$M$3,$E$1,IF(N42<=$M$4,$G$1,IF(N42<=$N$1,$I$1,0))) -> 0 | N42: =H42+(H42*I42) -> 61087.72 | O42: =N42 - K42 - P43 - M42-L42 -> 48564.737 | R42: =G42*D42 -> 41634.086
H43: =O42-F42-$S$6 -> 32686.709 | J43: 0.06 | P43: =N42*J43 -> 3665.2632
D45: 100 | E45: ='Coloniales S.C'!K96 -> 1239.5014 | F45: =E45*D45 -> 123950.14 | G45: =G36 -> 832.68171 | H45: =(G45*D45)+850 -> 84118.171 | I45: 0.4 | J45: 0.145 | K45: =N45*J45 -> 17075.989 | M45: =IF(N45<=$M$3,$E$1,IF(N45<=$M$4,$G$1,IF(N45<=$N$1,$I$1,0))) -> 0 | N45: =H45+(H45*I45) -> 117765.44 | O45: =N45 - K45 - P46 - M45-L45 -> 93623.525 | R45: =G45*D45 -> 83268.171
H46: =O45-F45-$S$6 -> -32326.618 | J46: 0.06 | P46: =N45*J46 -> 7065.9264
G48: Petit Box N4
C49: Petit Box N°4 Flex | D49: 5 | E49: ='Coloniales S.C'!K96 -> 1239.5014 | F49: =E49*D49 -> 6197.5071 | G49: ='Coloniales S.C'!M96 -> 3470.604 | H49: =(G49*D49)+$S$11 -> 21353.02 | I49: 0.43 | J49: 0.145 | K49: =N49*J49 -> #VALUE! | M49: =IF(N49<=$M$3,$E$1,IF(N49<=$M$4,$G$1,IF(N49<=$N$1,$I$1,0))) -> 0 | O49: =N49 - K49 - P50 - M49-L49 -> #VALUE! | R49: =G49*D49 -> 17353.02
H50: =O49-F49-$S$6 -> #VALUE! | J50: 0.06 | P50: =N49*J50 -> #VALUE!
D52: 30 | E52: =E49 -> 1239.5014 | F52: =E52*D52 -> 37185.043 | G52: =G49 -> 3470.604 | H52: =(G52*D52)+$S$6 -> 106118.12 | I52: 0.35 | J52: 0.145 | K52: =N52*J52 -> 20772.622 | L52: 7000 | M52: =IF(N52<=$M$3,$E$1,IF(N52<=$M$4,$G$1,IF(N52<=$N$1,$I$1,0))) -> 0 | N52: =H52+(H52*I52) -> 143259.46 | O52: =N52 - K52 - P53 - M52-L52 -> 106891.27 | R52: =G52*D52 -> 104118.12
H53: =O52-F52-$S$6 -> 67706.229 | J53: 0.06 | P53: =N52*J53 -> 8595.5677
D55: 50 | E55: =E49 -> 1239.5014 | F55: =E55*D55 -> 61975.071 | G55: =G52 -> 3470.604 | H55: =(G55*D55)+$S$11 -> 177530.2 | I55: 0.31 | J55: 0.145 | K55: =N55*J55 -> 33721.861 | L55: 7000 | M55: =IF(N55<=$M$3,$E$1,IF(N55<=$M$4,$G$1,IF(N55<=$N$1,$I$1,0))) -> 0 | N55: =H55+(H55*I55) -> 232564.56 | O55: =N55 - K55 - P56 - M55-L55 -> 177888.83 | R55: =G55*D55 -> 173530.2
H56: =O55-F55-$S$6 -> 113913.76 | J56: 0.06 | P56: =N55*J56 -> 13953.874
D58: 100 | E58: =E49 -> 1239.5014 | F58: =E58*D58 -> 123950.14 | G58: =G49 -> 3470.604 | H58: =(G58*D58)+$S$6 -> 349060.4 | I58: 0.3 | J58: 0.145 | K58: =N58*J58 -> 65797.885 | L58: 9000 | M58: =IF(N58<=$M$3,$E$1,IF(N58<=$M$4,$G$1,IF(N58<=$N$1,$I$1,0))) -> 0 | N58: =H58+(H58*I58) -> 453778.52 | O58: =N58 - K58 - P59 - M58-L58 -> 351753.92 | R58: =G58*D58 -> 347060.4
H59: =O58-F58-$S$6 -> 225803.78 | J59: 0.06 | P59: =N58*J59 -> 27226.711
G61: Cajas de 6 Chocos GOLD
C62: Cajas GOLD | D62: 1 | E62: ='Coloniales S.C'!K150 -> 2078.1243 | F62: =E62*D62 -> 2078.1243 | G62: ='Coloniales S.C'!M150 -> 5195.3107 | H62: =(G62*D62)+$S$6 -> 7195.3107 | I62: 0.39 | J62: 0.145 | K62: =N62*J62 -> 1450.2149 | M62: =IF(N62<=$M$3,$E$1,IF(N62<=$M$4,$G$1,IF(N62<=$N$1,$I$1,0))) -> 1100 | N62: =H62+(H62*I62) -> 10001.482 | O62: =N62 - K62 - P63 - M62-L62 -> 6851.1781 | Q62: =N62/D62 -> 10001.482 | R62: =G62*D62 -> 5195.3107
H63: =O62-F62-$S$6 -> 2773.0538 | J63: 0.06 | P63: =N62*J63 -> 600.08891
D65: 5 | E65: =E62 -> 2078.1243 | F65: =E65*D65 -> 10390.621 | G65: =G62 -> 5195.3107 | H65: =(G65*D65)+$S$6 -> 27976.554 | I65: 0.52 | J65: 0.145 | K65: =N65*J65 -> 6166.0324 | L65: 7000 | M65: =IF(N65<=$M$3,$E$1,IF(N65<=$M$4,$G$1,IF(N65<=$N$1,$I$1,0))) -> 0 | N65: =H65+(H65*I65) -> 42524.361 | O65: =N65 - K65 - P66 - M65-L65 -> 26806.867 | Q65: =N65/D65 -> 8504.8723 | R65: =G65*D65 -> 25976.554
H66: =O65-F65-$S$6 -> 14416.246 | J66: 0.06 | P66: =N65*J66 -> 2551.4617
D68: 20 | E68: =E62 -> 2078.1243 | F68: =E68*D68 -> 41562.486 | G68: =G62 -> 5195.3107 | H68: =(G68*D68)+$S$6 -> 105906.21 | I68: 0.37 | J68: 0.145 | K68: =N68*J68 -> 21038.269 | L68: 9500 | M68: =IF(N68<=$M$3,$E$1,IF(N68<=$M$4,$G$1,IF(N68<=$N$1,$I$1,0))) -> 0 | N68: =H68+(H68*I68) -> 145091.51 | O68: =N68 - K68 - P69 - M68-L68 -> 105847.75 | Q68: =N68/D68 -> 7254.5757 | R68: =G68*D68 -> 103906.21
H69: =O68-F68-$S$6 -> 62285.268 | J69: 0.06 | P69: =N68*J69 -> 8705.4908
D71: 25 | E71: =E62 -> 2078.1243 | F71: =E71*D71 -> 51953.107 | G71: =G62 -> 5195.3107 | H71: =(G71*D71)+$S$6 -> 131882.77 | I71: 0.32 | J71: 0.145 | K71: =N71*J71 -> 25242.362 | L71: 10000 | M71: =IF(N71<=$M$3,$E$1,IF(N71<=$M$4,$G$1,IF(N71<=$N$1,$I$1,0))) -> 0 | N71: =H71+(H71*I71) -> 174085.25 | O71: =N71 - K71 - P72 - M71-L71 -> 128397.78 | Q71: =N71/D71 -> 6963.4101 | R71: =G71*D71 -> 129882.77
H72: =O71-F71-$S$6 -> 74444.669 | J72: 0.06 | P72: =N71*J72 -> 10445.115
D74: 50 | E74: =E62 -> 2078.1243 | F74: =E74*D74 -> 103906.21 | G74: =G62 -> 5195.3107 | H74: =(G74*D74)+$S$6 -> 261765.54 | I74: 0.31 | J74: 0.145 | K74: =N74*J74 -> 49722.364 | L74: 10000 | M74: =IF(N74<=$M$3,$E$1,IF(N74<=$M$4,$G$1,IF(N74<=$N$1,$I$1,0))) -> 0 | N74: =H74+(H74*I74) -> 342912.85 | O74: =N74 - K74 - P75 - M74-L74 -> 262615.72 | Q74: =N74/D74 -> 6858.257 | R74: =G74*D74 -> 259765.54
H75: =O74-F74-$S$6 -> 156709.5 | J75: 0.06 | P75: =N74*J75 -> 20574.771
G76: 0
G77: Caja DELUXE
D78: 1 | E78: ='Coloniales S.C'!K197 -> 2116.0714 | F78: =E78*D78 -> 2116.0714 | G78: ='Coloniales S.C'!M197 -> 6348.2143 | H78: =(G78*D78)+$S$6 -> 8348.2143 | I78: 0.4 | J78: 0.145 | K78: =N78*J78 -> 1694.6875 | M78: =IF(N78<=$M$3,$E$1,IF(N78<=$M$4,$G$1,IF(N78<=$N$1,$I$1,0))) -> 1100 | N78: =H78+(H78*I78) -> 11687.5 | O78: =N78 - K78 - P79 - M78-L78 -> 8191.5625 | R78: =G78*D78 -> 6348.2143
H79: =O78-F78 -> 6075.4911 | J79: 0.06 | P79: =N78*J79 -> 701.25
D81: 10 | E81: =$E$78 -> 2116.0714 | F81: =E81*D81 -> 21160.714 | G81: =$G$78 -> 6348.2143 | H81: =(G81*D81)+$S$6 -> 65482.143 | I81: 0.4 | J81: 0.145 | K81: =N81*J81 -> 13292.875 | L81: 7000 | M81: =IF(N81<=$M$3,$E$1,IF(N81<=$M$4,$G$1,IF(N81<=$N$1,$I$1,0))) -> 0 | N81: =H81+(H81*I81) -> 91675 | O81: =N81 - K81 - P82 - M81-L81 -> 65881.625 | R81: =G81*D81 -> 63482.143
H82: =O81-F81 -> 44720.911 | J82: 0.06 | P82: =N81*J82 -> 5500.5
D84: 25 | E84: =$E$78 -> 2116.0714 | F84: =E84*D84 -> 52901.786 | G84: =$G$78 -> 6348.2143 | H84: =(G84*D84)+$S$6 -> 160705.36 | I84: 0.33 | J84: 0.145 | K84: =N84*J84 -> 30992.028 | L84: 9000 | M84: =IF(N84<=$M$3,$E$1,IF(N84<=$M$4,$G$1,IF(N84<=$N$1,$I$1,0))) -> 0 | N84: =H84+(H84*I84) -> 213738.12 | O84: =N84 - K84 - P85 - M84-L84 -> 160921.81 | R84: =G84*D84 -> 158705.36
H85: =O84-F84 -> 108020.02 | J85: 0.06 | P85: =N84*J85 -> 12824.288
D87: 50 | E87: =$E$78 -> 2116.0714 | F87: =E87*D87 -> 105803.57 | G87: =$G$78 -> 6348.2143 | H87: =(G87*D87)+$S$6 -> 319410.71 | I87: 0.3 | J87: 0.145 | K87: =N87*J87 -> 60208.92 | L87: 9000 | M87: =IF(N87<=$M$3,$E$1,IF(N87<=$M$4,$G$1,IF(N87<=$N$1,$I$1,0))) -> 0 | N87: =H87+(H87*I87) -> 415233.93 | O87: =N87 - K87 - P88 - M87-L87 -> 321110.97 | R87: =G87*D87 -> 317410.71
H88: =O87-F87 -> 215307.4 | J88: 0.06 | P88: =N87*J88 -> 24914.036
G90: Caja Classic
C91: Clasica | D91: 1 | E91: ='Coloniales S.C'!K120 -> 1957.9304 | F91: =E91*D91 -> 1957.9304 | G91: ='Coloniales S.C'!M120 -> 4503.2399 | H91: =(G91*D91)+$S$6 -> 6503.2399 | I91: 0.5 | J91: 0.145 | K91: =N91*J91 -> 1414.4547 | M91: =IF(N91<=$M$3,$E$1,IF(N91<=$M$4,$G$1,IF(N91<=$N$1,$I$1,0))) -> 1100 | N91: =H91+(H91*I91) -> 9754.8599 | O91: =N91 - K91 - P92 - M91-L91 -> 6655.1136 | R91: =G91*D91 -> 4503.2399
H92: =O91-F91 -> 4697.1832 | J92: 0.06 | P92: =N91*J92 -> 585.29159
D94: 10 | E94: =$E$91 -> 1957.9304 | F94: =E94*D94 -> 19579.304 | G94: =$G$91 -> 4503.2399 | H94: =(G94*D94)+$S$6 -> 47032.399 | I94: 0.48 | J94: 0.145 | K94: =N94*J94 -> 10093.153 | L94: 7000 | M94: =IF(N94<=$M$3,$E$1,IF(N94<=$M$4,$G$1,IF(N94<=$N$1,$I$1,0))) -> 0 | N94: =H94+(H94*I94) -> 69607.951 | O94: =N94 - K94 - P95 - M94-L94 -> 48338.321 | R94: =G94*D94 -> 45032.399
H95: =O94-F94 -> 28759.017 | J95: 0.06 | P95: =N94*J95 -> 4176.4771
D97: 25 | E97: =$E$91 -> 1957.9304 | F97: =E97*D97 -> 48948.26 | G97: =$G$91 -> 4503.2399 | H97: =(G97*D97)+$S$6 -> 114581 | I97: 0.35 | J97: 0.145 | K97: =N97*J97 -> 22429.23 | L97: 7000 | M97: =IF(N97<=$M$3,$E$1,IF(N97<=$M$4,$G$1,IF(N97<=$N$1,$I$1,0))) -> 0 | N97: =H97+(H97*I97) -> 154684.35 | O97: =N97 - K97 - P98 - M97-L97 -> 115974.06 | R97: =G97*D97 -> 112581
H98: =O97-F97 -> 67025.796 | J98: 0.06 | P98: =N97*J98 -> 9281.0609
D100: 50 | E100: =$E$91 -> 1957.9304 | F100: =E100*D100 -> 97896.52 | G100: =$G$91 -> 4503.2399 | H100: =(G100*D100)+$S$11 -> 229162 | I100: 0.32 | J100: 0.145 | K100: =N100*J100 -> 43861.606 | L100: 9000 | M100: =IF(N100<=$M$3,$E$1,IF(N100<=$M$4,$G$1,IF(N100<=$N$1,$I$1,0))) -> 0 | N100: =H100+(H100*I100) -> 302493.84 | O100: =N100 - K100 - P101 - M100-L100 -> 231482.6 | R100: =G100*D100 -> 225162
H101: =O100-F100 -> 133586.08 | J101: 0.06 | P101: =N100*J101 -> 18149.63
G103: Caja 2 Chocos
C104: Georgalos | D104: 1 | E104: =Georgalos!I7 -> 1293.7707 | F104: =E104*D104 -> 1293.7707 | G104: =Georgalos!K7 -> 3881.312 | H104: =(G104*D104)+$S$6 -> 5881.312 | I104: 0.48 | J104: 0.145 | K104: =N104*J104 -> 1262.1296 | M104: =IF(N104<=$M$3,$E$1,IF(N104<=$M$4,$G$1,IF(N104<=$N$1,$I$1,0))) -> 1100 | N104: =H104+(H104*I104) -> 8704.3418 | O104: =N104 - K104 - P105 - M104-L104 -> 5819.9517 | R104: =G104*D104 -> 3881.312
H105: =O104-F104 -> 4526.181 | J105: 0.06 | P105: =N104*J105 -> 522.26051
D107: 10 | E107: =Georgalos!I9 -> 1182.4457 | F107: =E107*D107 -> 11824.457 | G107: =Georgalos!K9 -> 3769.987 | H107: =(G107*D107)+$S$6 -> 39699.87 | I107: 0.44 | J107: 0.145 | K107: =N107*J107 -> 8289.3329 | L107: 5400 | M107: =IF(N107<=$M$3,$E$1,IF(N107<=$M$4,$G$1,IF(N107<=$N$1,$I$1,0))) -> 0 | N107: =H107+(H107*I107) -> 57167.813 | O107: =N107 - K107 - P108 - M107-L107 -> 40048.411 | R107: =G107*D107 -> 37699.87
H108: =O107-F107 -> 28223.955 | J108: 0.06 | P108: =N107*J108 -> 3430.0688
D110: 25 | E110: =Georgalos!I31 -> 1367.5307 | F110: =E110*D110 -> 34188.267 | G110: =Georgalos!K31 -> 4376.0981 | H110: =(G110*D110)+$S$6 -> 111402.45 | I110: 0.35 | J110: 0.145 | K110: =N110*J110 -> 21807.03 | L110: 7000 | M110: =IF(N110<=$M$3,$E$1,IF(N110<=$M$4,$G$1,IF(N110<=$N$1,$I$1,0))) -> 0 | N110: =H110+(H110*I110) -> 150393.31 | O110: =N110 - K110 - P111 - M110-L110 -> 112562.68 | R110: =G110*D110 -> 109402.45
H111: =O110-F110 -> 78374.416 | J111: 0.06 | P111: =N110*J111 -> 9023.5987
D113: 50 | E113: 0 | F113: =E113*D113 -> 0 | G113: 2000 | H113: =(G113*D113)+$S$6 -> 102000 | I113: 0.38 | J113: 0.145 | K113: =N113*J113 -> 20410.2 | L113: 9000 | M113: =IF(N113<=$M$3,$E$1,IF(N113<=$M$4,$G$1,IF(N113<=$N$1,$I$1,0))) -> 0 | N113: =H113+(H113*I113) -> 140760 | O113: =N113 - K113 - P114 - M113-L113 -> 102904.2 | R113: =G113*D113 -> 100000
H114: =O113-F113 -> 102904.2 | J114: 0.06 | P114: =N113*J114 -> 8445.6
G116: Caja 2 Chocos MOÑO
C117: Georgalos | D117: 1 | E117: =Georgalos!I31 -> 1367.5307 | F117: =E117*D117 -> 1367.5307 | G117: =Georgalos!K31 -> 4376.0981 | H117: =(G117*D117)+$S$6 -> 6376.0981 | I117: 0.47 | J117: 0.145 | K117: =N117*J117 -> 1359.0653 | M117: =IF(N117<=$M$3,$E$1,IF(N117<=$M$4,$G$1,IF(N117<=$N$1,$I$1,0))) -> 1100 | N117: =H117+(H117*I117) -> 9372.8643 | O117: =N117 - K117 - P118 - M117-L117 -> 6351.4271 | R117: =G117*D117 -> 4376.0981
H118: =O117-F117 -> 4983.8964 | J118: 0.06 | P118: =N117*J118 -> 562.37186
D120: 10 | E120: =E117 -> 1367.5307 | F120: =E120*D120 -> 13675.307 | G120: =G117 -> 4376.0981 | H120: =(G120*D120)+$S$6 -> 45760.981 | I120: 0.42 | J120: 0.145 | K120: =N120*J120 -> 9422.1861 | L120: 5700 | M120: =IF(N120<=$M$3,$E$1,IF(N120<=$M$4,$G$1,IF(N120<=$N$1,$I$1,0))) -> 0 | N120: =H120+(H120*I120) -> 64980.593 | O120: =N120 - K120 - P121 - M120-L120 -> 45959.572 | R120: =G120*D120 -> 43760.981
H121: =O120-F120 -> 32284.265 | J121: 0.06 | P121: =N120*J121 -> 3898.8356
D123: 25 | E123: =E120 -> 1367.5307 | F123: =E123*D123 -> 34188.267 | G123: =G120 -> 4376.0981 | H123: =(G123*D123)+$S$11 -> 113402.45 | I123: 0.35 | J123: 0.145 | K123: =N123*J123 -> 22198.53 | L123: 7000 | M123: =IF(N123<=$M$3,$E$1,IF(N123<=$M$4,$G$1,IF(N123<=$N$1,$I$1,0))) -> 0 | N123: =H123+(H123*I123) -> 153093.31 | O123: =N123 - K123 - P124 - M123-L123 -> 114709.18 | R123: =G123*D123 -> 109402.45
H124: =O123-F123 -> 80520.916 | J124: 0.06 | P124: =N123*J124 -> 9185.5987
D126: 50 | E126: =E120 -> 1367.5307 | F126: =E126*D126 -> 68376.533 | G126: =G120 -> 4376.0981 | H126: =(G126*D126)+$S$6 -> 220804.91 | I126: 0.31 | J126: 0.145 | K126: =N126*J126 -> 41941.892 | L126: 9000 | M126: =IF(N126<=$M$3,$E$1,IF(N126<=$M$4,$G$1,IF(N126<=$N$1,$I$1,0))) -> 0 | N126: =H126+(H126*I126) -> 289254.43 | O126: =N126 - K126 - P127 - M126-L126 -> 220957.27 | R126: =G126*D126 -> 218804.91
H127: =O126-F126 -> 152580.74 | J127: 0.06 | P127: =N126*J127 -> 17355.266
G129: Señaladores Chocolate
D130: 100 | E130: ='Coloniales S.C'!K152 -> 734.12429 | F130: =E130*D130 -> 73412.429 | G130: =G126 -> 4376.0981 | H130: =(G130*D130)+$S$6 -> 439609.81 | I130: 0.4 | J130: 0.145 | K130: =N130*J130 -> 89240.792 | M130: =IF(N130<=$M$3,$E$1,IF(N130<=$M$4,$G$1,IF(N130<=$N$1,$I$1,0))) -> 0 | N130: =H130+(H130*I130) -> 615453.74 | O130: =N130 - K130 - P131 - M130-L130 -> 489285.72 | R130: =G130*D130 -> 437609.81
H131: =O130-F130 -> 415873.29 | J131: 0.06 | P131: =N130*J131 -> 36927.224
C133: Caja BLACK | D133: 1 | E133: ='Coloniales S.C'!K174 -> 2303.1243 | F133: =E133*D133 -> 2303.1243 | G133: ='Coloniales S.C'!M174 -> 6909.3729 | H133: =(G133*D133)+$S$6 -> 8909.3729 | I133: 0.4 | J133: 0.145 | K133: =N133*J133 -> 1808.6027 | L133: 5700 | M133: =IF(N133<=$M$3,$E$1,IF(N133<=$M$4,$G$1,IF(N133<=$N$1,$I$1,0))) -> 1100 | N133: =H133+(H133*I133) -> 12473.122 | O133: =N133 - K133 - P134 - M133-L133 -> 3116.132 | R133: =G133*D133 -> 6909.3729
H134: =O133-F133 -> 813.0077 | J134: 0.06 | P134: =N133*J134 -> 748.38732
C136: Caja BLACK | D136: 10 | E136: =E133 -> 2303.1243 | F136: =E136*D136 -> 23031.243 | G136: =G133 -> 6909.3729 | H136: =(G136*D136)+$S$6 -> 71093.729 | I136: 0.4 | J136: 0.145 | K136: =N136*J136 -> 14432.027 | M136: =IF(N136<=$M$3,$E$1,IF(N136<=$M$4,$G$1,IF(N136<=$N$1,$I$1,0))) -> 0 | N136: =H136+(H136*I136) -> 99531.22 | O136: =N136 - K136 - P137 - M136-L136 -> 79127.32 | R136: =G136*D136 -> 69093.729
H137: =O136-F136 -> 56096.077 | J137: 0.06 | P137: =N136*J137 -> 5971.8732
G139: Vela 100cc Gold Fragancia
C140: Vela 1-9 | D140: 1 | E140: =Velas!K9 -> 1876.7783 | F140: =E140*D140 -> 1876.7783 | G140: =Velas!M9 -> 5630.3349 | H140: =(G140*D140)+$S$6 -> 7630.3349 | I140: 0.45 | J140: 0.145 | K140: =N140*J140 -> 1604.2779 | M140: =IF(N140<=$M$3,$E$1,IF(N140<=$M$4,$G$1,IF(N140<=$N$1,$I$1,0))) -> 1100 | N140: =H140+(H140*I140) -> 11063.986 | O140: =N140 - K140 - P141 - M140-L140 -> 7695.8685 | Q140: =N140/D140 -> 11063.986 | R140: =G140*D140 -> 5630.3349
...

Sheet Velas
N5: 0.1 | P5: 0.08
N6: 0.09 | P6: 0.06
N7: =N6+N5 -> 0.19 | P7: =P6+P5 -> 0.14 | S7: Descuento | T7: Descuento | U7: Descuento | V7: Descuento | W7: Descuento | X7: Descuento
B8: 100cc Esencia | C8: Frasco | D8: Cera | E8: Etiqueta | F8: Esencia | G8: Pabilo+Ojalillo | H8: Moño | I8: Caja | K8: Costo total | L8: Ganancia | M8: Total | N8: MP | O8: MP | P8: Ganan MP | S8: 0.05 | T8: 0.1 | U8: 0.15 | V8: 0.2 | W8: 0.25 | X8: 0.3
C9: =Insumos!J6 -> 927.11429 | D9: =Insumos!J12*72 -> 354.96 | E9: =(Insumos!G9/30)+(Insumos!G15/30) -> 17.304 | F9: =Insumos!J9*5 -> 550 | G9: =Insumos!J15+Insumos!J18 -> 27.4 | I9: =Insumos!N42 -> 370 | K9: =SUM(C9:G9) -> 1876.7783 | L9: =M9-K9 -> 3753.5566 | M9: =K9*3 -> 5630.3349 | N9: =ROUND(O9/50,0)*50 -> 6700 | O9: =(L9+K9)+((K9+L9)*(N7)) -> 6700.0985 | P9: =N9-(N9*P7)-K9 -> 3885.2217 | S9: 50 | T9: 100 | U9: 200 | V9: 500 | W9: 1000 | X9: 2000
S10: Costo total | T10: Costo total | U10: Costo total | V10: Costo total | W10: Costo total | X10: Costo total
B11: 10 | C11: =L11*B11 -> 28151.674 | L11: =M11-$K$9 -> 2815.1674 | M11: =$K$9*2.5 -> 4691.9457 | S11: =K9*S9 -> 93838.914 | T11: =K9*T9 -> 187677.83 | U11: =$K$9*U9 -> 375355.66 | V11: =$K$9*V9 -> 938389.14 | W11: =$K$9*W9 -> 1876778.3 | X11: =$K$9*X9 -> 3753556.6
N12: Transf | S12: MP | T12: MP | U12: MP | V12: MP | W12: MP | X12: MP
B13: 20 | C13: =L13*B13 -> 48796.235 | L13: =M13-$K$9 -> 2439.8118 | M13: =$K$9*2.3 -> 4316.5901 | N13: =N9-(N9*S20) -> 6030 | S13: =($N9*S9)-(($N9*S9)*S8) -> 318250 | T13: =($N9*T9)-(($N9*T9)*T8) -> 603000 | U13: =($N9*U9)-(($N9*U9)*U8) -> 1139000 | V13: =($N9*V9)-(($N9*V9)*V8) -> 2680000 | W13: =($N9*W9)-(($N9*W9)*W8) -> 5025000 | X13: =($N9*X9)-(($N9*X9)*X8) -> 9380000
N14: G. Transf | S14: =S13/S9 -> 6365 | T14: =T13/T9 -> 6030 | U14: =U13/U9 -> 5695 | V14: =V13/V9 -> 5360 | W14: =W13/W9 -> 5025 | X14: =X13/X9 -> 4690
B15: 50 | C15: =L15*B15 -> 103222.81 | L15: =M15-$K$9 -> 2064.4561 | M15: =$K$9*2.1 -> 3941.2344 | N15: =(N13-(N13*P6))-K9 -> 3791.4217 | S15: Ganancia MP | T15: Ganancia MP | U15: Ganancia MP | V15: Ganancia MP | W15: Ganancia MP | X15: Ganancia MP
S16: =(S13-S11)-(S13*$P$5) -> 198951.09 | T16: =(T13-T11)-(T13*$P$5) -> 367082.17 | U16: =(U13-U11)-(U13*$P$5) -> 672524.34 | V16: =(V13-V11)-(V13*$P$5) -> 1527210.9 | W16: =(W13-W11)-(W13*$P$5) -> 2746221.7 | X16: =(X13-X11)-(X13*$P$5) -> 4876043.4
B17: 100 | C17: =L17*B17 -> 187677.83 | L17: =M17-$K$9 -> 1876.7783 | M17: =$K$9*2 -> 3753.5566 | S17: =S16/S9 -> 3979.0217 | T17: =T16/T9 -> 3670.8217 | U17: =U16/U9 -> 3362.6217 | V17: =V16/V9 -> 3054.4217 | W17: =W16/W9 -> 2746.2217 | X17: =X16/X9 -> 2438.0217
S18: Transf | T18: Transf | U18: Transf | V18: Transf | W18: Transf | X18: Transf
S19: =S13-(S13*S20) -> 286425 | T19: =T13-(T13*T20) -> 542700 | U19: =U13-(U13*U20) -> 1025100 | V19: =V13-(V13*V20) -> 2412000 | W19: =W13-(W13*W20) -> 4522500 | X19: =X13-(X13*X20) -> 8442000
S20: 0.1 | T20: 0.1 | U20: 0.1 | V20: 0.1 | W20: 0.1 | X20: 0.1
S21: =S19/S9 -> 5728.5 | T21: =T19/T9 -> 5427 | U21: =U19/U9 -> 5125.5 | V21: =V19/V9 -> 4824 | W21: =W19/W9 -> 4522.5 | X21: =X19/X9 -> 4221
S22: Ganancia trans | T22: Ganancia trans | U22: Ganancia trans | V22: Ganancia trans | W22: Ganancia trans | X22: Ganancia trans
S23: =S19-(S19*$P$4)-S11 -> 192586.09 | T23: =T19-(T19*$P$4)-T11 -> 355022.17 | U23: =U19-(U19*$P$4)-U11 -> 649744.34 | V23: =V19-(V19*$P$4)-V11 -> 1473610.9 | W23: =W19-(W19*$P$4)-W11 -> 2645721.7 | X23: =X19-(X19*$P$4)-X11 -> 4688443.4
S24: =S23/S9 -> 3851.7217 | T24: =T23/T9 -> 3550.2217 | U24: =U23/U9 -> 3248.7217 | V24: =V23/V9 -> 2947.2217 | W24: =W23/W9 -> 2645.7217 | X24: =X23/X9 -> 2344.2217
N29: 0.1 | P29: 0.08
N30: 0.09 | P30: 0.06
N31: =N30+N29 -> 0.19 | P31: =P30+P29 -> 0.14 | S31: Descuento | T31: Descuento | U31: Descuento | V31: Descuento | W31: Descuento | X31: Descuento
B32: Vela tennese Comunion con caja | C32: Frasco | D32: Cera | E32: Etiqueta | F32: Esencia | G32: Pabilo+Ojalillo | H32: caja | I32: Etiqueta caja | K32: Costo total | L32: Ganancia | M32: Total | N32: MP | O32: MP | P32: Ganan MP | S32: 0.05 | T32: 0.1 | U32: 0.15 | V32: 0.2 | W32: 0.25 | X32: 0.3
C33: =Insumos!J22 -> 1264.2917 | D33: =Insumos!J12*200 -> 986 | E33: =(Insumos!G15/21)+(Insumos!G27/21) -> 20.97619 | F33: =Insumos!J9*10 -> 1100 | G33: =G9 -> 27.4 | H33: =Insumos!N33 -> 400.5 | I33: =(Insumos!G27/20)+(Insumos!G15/20) -> 22.025 | K33: =SUM(C33:J33) -> 3821.1929 | L33: =M33-K33 -> 7642.3857 | M33: =K33*3 -> 11463.579 | N33: =ROUND(O33/50,0)*50 -> 13650 | O33: =(L33+K33)+((K33+L33)*(N31)) -> 13641.659 | P33: =N33-(N33*P31)-K33 -> 7917.8071 | S33: 50 | T33: 100 | U33: 200 | V33: 500 | W33: 1000 | X33: 2000
S34: Costo total | T34: Costo total | U34: Costo total | V34: Costo total | W34: Costo total | X34: Costo total
S35: =K33*S33 -> 191059.64 | T35: =K33*T33 -> 382119.29 | U35: =$K$9*U33 -> 375355.66 | V35: =$K$9*V33 -> 938389.14 | W35: =$K$9*W33 -> 1876778.3 | X35: =$K$9*X33 -> 3753556.6
N36: Transf | S36: MP | T36: MP | U36: MP | V36: MP | W36: MP | X36: MP
N37: =N33-(N33*S44) -> 12285 | S37: =($N33*S33)-(($N33*S33)*S32) -> 648375 | T37: =($N33*T33)-(($N33*T33)*T32) -> 1228500 | U37: =($N33*U33)-(($N33*U33)*U32) -> 2320500 | V37: =($N33*V33)-(($N33*V33)*V32) -> 5460000 | W37: =($N33*W33)-(($N33*W33)*W32) -> 10237500 | X37: =($N33*X33)-(($N33*X33)*X32) -> 19110000
N38: G. Transf | S38: =S37/S33 -> 12967.5 | T38: =T37/T33 -> 12285 | U38: =U37/U33 -> 11602.5 | V38: =V37/V33 -> 10920 | W38: =W37/W33 -> 10237.5 | X38: =X37/X33 -> 9555
N39: =(N37-(N37*P30))-K33 -> 7726.7071 | S39: Ganancia MP | T39: Ganancia MP | U39: Ganancia MP | V39: Ganancia MP | W39: Ganancia MP | X39: Ganancia MP
S40: =(S37-S35)-(S37*$P$5) -> 405445.36 | T40: =(T37-T35)-(T37*$P$5) -> 748100.71 | U40: =(U37-U35)-(U37*$P$5) -> 1759504.3 | V40: =(V37-V35)-(V37*$P$5) -> 4084810.9 | W40: =(W37-W35)-(W37*$P$5) -> 7541721.7 | X40: =(X37-X35)-(X37*$P$5) -> 13827643
S41: =S40/S33 -> 8108.9071 | T41: =T40/T33 -> 7481.0071 | U41: =U40/U33 -> 8797.5217 | V41: =V40/V33 -> 8169.6217 | W41: =W40/W33 -> 7541.7217 | X41: =X40/X33 -> 6913.8217
S42: Transf | T42: Transf | U42: Transf | V42: Transf | W42: Transf | X42: Transf
S43: =S37-(S37*S44) -> 583537.5 | T43: =T37-(T37*T44) -> 1105650 | U43: =U37-(U37*U44) -> 2088450 | V43: =V37-(V37*V44) -> 4914000 | W43: =W37-(W37*W44) -> 9213750 | X43: =X37-(X37*X44) -> 17199000
S44: 0.1 | T44: 0.1 | U44: 0.1 | V44: 0.1 | W44: 0.1 | X44: 0.1
S45: =S43/S33 -> 11670.75 | T45: =T43/T33 -> 11056.5 | U45: =U43/U33 -> 10442.25 | V45: =V43/V33 -> 9828 | W45: =W43/W33 -> 9213.75 | X45: =X43/X33 -> 8599.5
S46: Ganancia trans | T46: Ganancia trans | U46: Ganancia trans | V46: Ganancia trans | W46: Ganancia trans | X46: Ganancia trans
S47: =S43-(S43*$P$4)-S35 -> 392477.86 | T47: =T43-(T43*$P$4)-T35 -> 723530.71 | U47: =U43-(U43*$P$4)-U35 -> 1713094.3 | V47: =V43-(V43*$P$4)-V35 -> 3975610.9 | W47: =W43-(W43*$P$4)-W35 -> 7336971.7 | X47: =X43-(X43*$P$4)-X35 -> 13445443
S48: =S47/S33 -> 7849.5571 | T48: =T47/T33 -> 7235.3071 | U48: =U47/U33 -> 8565.4717 | V48: =V47/V33 -> 7951.2217 | W48: =W47/W33 -> 7336.9717 | X48: =X47/X33 -> 6722.7217
N52: 0.1 | P52: 0.08
N53: 0.09 | P53: 0.06
N54: =N53+N52 -> 0.19 | P54: =P53+P52 -> 0.14 | S54: Descuento | T54: Descuento | U54: Descuento | V54: Descuento | W54: Descuento | X54: Descuento
B55: Vela tennese Comunion | C55: Frasco | D55: Cera | E55: Etiqueta | F55: Esencia | G55: Pabilo+Ojalillo | H55: caja | I55: Etiqueta caja | K55: Costo total | L55: Ganancia | M55: Total | N55: MP | O55: MP | P55: Ganan MP | S55: 0.05 | T55: 0.1 | U55: 0.15 | V55: 0.2 | W55: 0.25 | X55: 0.3
C56: =C33 -> 1264.2917 | D56: =D33 -> 986 | E56: =E33 -> 20.97619 | F56: =F33 -> 1100 | G56: =G33 -> 27.4 | K56: =SUM(C56:J56) -> 3398.6679 | L56: =M56-K56 -> 6797.3357 | M56: =K56*3 -> 10196.004 | N56: =ROUND(O56/50,0)*50 -> 12150 | O56: =(L56+K56)+((K56+L56)*(N54)) -> 12133.244 | P56: =N56-(N56*P54)-K56 -> 7050.3321 | S56: 50 | T56: 100 | U56: 200 | V56: 500 | W56: 1000 | X56: 2000
S57: Costo total | T57: Costo total | U57: Costo total | V57: Costo total | W57: Costo total | X57: Costo total
S58: =K56*S56 -> 169933.39 | T58: =K56*T56 -> 339866.79 | U58: =$K$9*U56 -> 375355.66 | V58: =$K$9*V56 -> 938389.14 | W58: =$K$9*W56 -> 1876778.3 | X58: =$K$9*X56 -> 3753556.6
N59: Transf | S59: MP | T59: MP | U59: MP | V59: MP | W59: MP | X59: MP
N60: =N56-(N56*S67) -> 10935 | S60: =($N56*S56)-(($N56*S56)*S55) -> 577125 | T60: =($N56*T56)-(($N56*T56)*T55) -> 1093500 | U60: =($N56*U56)-(($N56*U56)*U55) -> 2065500 | V60: =($N56*V56)-(($N56*V56)*V55) -> 4860000 | W60: =($N56*W56)-(($N56*W56)*W55) -> 9112500 | X60: =($N56*X56)-(($N56*X56)*X55) -> 17010000
N61: G. Transf | S61: =S60/S56 -> 11542.5 | T61: =T60/T56 -> 10935 | U61: =U60/U56 -> 10327.5 | V61: =V60/V56 -> 9720 | W61: =W60/W56 -> 9112.5 | X61: =X60/X56 -> 8505
N62: =(N60-(N60*P53))-K56 -> 6880.2321 | S62: Ganancia MP | T62: Ganancia MP | U62: Ganancia MP | V62: Ganancia MP | W62: Ganancia MP | X62: Ganancia MP
S63: =(S60-S58)-(S60*$P$5) -> 361021.61 | T63: =(T60-T58)-(T60*$P$5) -> 666153.21 | U63: =(U60-U58)-(U60*$P$5) -> 1524904.3 | V63: =(V60-V58)-(V60*$P$5) -> 3532810.9 | W63: =(W60-W58)-(W60*$P$5) -> 6506721.7 | X63: =(X60-X58)-(X60*$P$5) -> 11895643
S64: =S63/S56 -> 7220.4321 | T64: =T63/T56 -> 6661.5321 | U64: =U63/U56 -> 7624.5217 | V64: =V63/V56 -> 7065.6217 | W64: =W63/W56 -> 6506.7217 | X64: =X63/X56 -> 5947.8217
S65: Transf | T65: Transf | U65: Transf | V65: Transf | W65: Transf | X65: Transf
S66: =S60-(S60*S67) -> 519412.5 | T66: =T60-(T60*T67) -> 984150 | U66: =U60-(U60*U67) -> 1858950 | V66: =V60-(V60*V67) -> 4374000 | W66: =W60-(W60*W67) -> 8201250 | X66: =X60-(X60*X67) -> 15309000
S67: 0.1 | T67: 0.1 | U67: 0.1 | V67: 0.1 | W67: 0.1 | X67: 0.1
S68: =S66/S56 -> 10388.25 | T68: =T66/T56 -> 9841.5 | U68: =U66/U56 -> 9294.75 | V68: =V66/V56 -> 8748 | W68: =W66/W56 -> 8201.25 | X68: =X66/X56 -> 7654.5
S69: Ganancia trans | T69: Ganancia trans | U69: Ganancia trans | V69: Ganancia trans | W69: Ganancia trans | X69: Ganancia trans
S70: =S66-(S66*$P$4)-S58 -> 349479.11 | T70: =T66-(T66*$P$4)-T58 -> 644283.21 | U70: =U66-(U66*$P$4)-U58 -> 1483594.3 | V70: =V66-(V66*$P$4)-V58 -> 3435610.9 | W70: =W66-(W66*$P$4)-W58 -> 6324471.7 | X70: =X66-(X66*$P$4)-X58 -> 11555443
S71: =S70/S56 -> 6989.5821 | T71: =T70/T56 -> 6442.8321 | U71: =U70/U56 -> 7417.9717 | V71: =V70/V56 -> 6871.2217 | W71: =W70/W56 -> 6324.4717 | X71: =X70/X56 -> 5777.7217
B75: Caramelera Circo | C75: Envase
C76: 2718.3

Sheet Insumos
AD1: Impresión | AE1: Por hoja
B2: Chocolates | F2: Hojas | I2: Velas | M2: Cajas | Q2: Extras | U2: Tejidos | Y2: Bolsas Polipropileno | AD2: Full | AE2: 200 | AJ2: Cintas | AO2: Dijes
AD3: Pastel | AE3: 50
F4: Autodhesivas | I4: Anchoero | M4: Indubox | T4: Hilo Algodon 36h Colores Macrame 3.5mm Mejor Calidad 100 Mts | MercadoLibre | U4: Cordon | V4: 9205 | Y4: Bolsa De Polipropileno 4x25cm. Ideal Garrapiñadas X 100u. | MercadoLibre | Z4: Tejido Base | AA4: 2108 | AC4: Tinta Epson T544 Original 70 Ml X4 Colores 544 L3110 L3150 | Envío gratis | AI4: Cinta Raso N0 - 3 mm x 50 metros - CandyCraft | AJ4: Raso N° 0 | AK4: 4838 | AN4: Dije de Fundición Letra A - ALMACEN DE ARMADO | AO4: Letras niquel | AP4: 4600
A5: Chocolatinas Con Leche Colonial X 50un | MercadoLibre | B5: Coloniales | C5: 12000 | E5: Papel Fotográfico Autoadhesivo A4 Brillante Foil 100 Hojas | MercadoLibre | F5: Fotografica | G5: 18992 | H5: Frasco Anchoero Vidrio 100 Cc Con Tapa 48 Axial X35 Unidades | MercadoLibre | I5: 100cc | J5: 32449 | L5: 50 Cajas Blancas Deslizantes D128 (16x4x2) Indubox | MercadoLibre | M5: D128 x 100u | N5: 50000 | O5: =N5/100 -> 500 | Q5: Telgopor | R5: 3800 | U5: 10000 | V5: =V4/U5 -> 0.9205 | Y5: 4x25 | Z5: 100 | AA5: =AA4/Z5 -> 21.08 | AJ5: 50 | AK5: =AK4/AJ5 -> 96.76 | AL5: el metro | AO5: 60 | AP5: =AP4/AO5 -> 76.666667 | AQ5: x letra
B6: 50 | C6: 224 | F6: 100 | G6: =(G5/F6)+$AE$3 -> 239.92 | I6: 35 | J6: =J5/I6 -> 927.11429 | Q6: 156 | R6: =R5/Q6 -> 24.358974
L7: 250 Cajas Blancas Deslizantes D128 (16x4x2) - Modelos según tipo - D: Deslizantes estilo fosforeras - D128 (Base 16x4cm / Altura: 2cm) | M7: 250 | N7: 95746 | O7: =N7/M7 -> 382.984 | U7: Argolla | V7: 5185 | Y7: 100 Bolsas Polipropileno 10x20+5 Cierre Adhesivo 40 Mic | MercadoLibre | Z7: Tejido+Tarjeta | AA7: 3466 | AI7: Cinta de Bebe Plateada Lurex | Tienda Online Candy Craft | AJ7: Lurex N°0 | AK7: 2900
B8: 200 | E8: Papel Autoadhesivo A4 Brillante Laser Ilustración Adhesivo | Envío gratis | F8: Glossy Laser | G8: 17712 | H8: Esencia Coco&vainilla Velas Soja Parafinas Pura 100% Intensa | MercadoLibre | I8: Esencias | J8: 27500 | P8: Cinta Raso N2 - 1 cm x 10 metros | Tienda Online Candy Craft | Q8: Cinta Raso | R8: 1888 | U8: 100 | V8: =V7/U8 -> 51.85 | Y8: 10x20 | Z8: 100 | AA8: =AA7/Z8 -> 34.66 | AJ8: 20 | AK8: =AK7/AJ8 -> 145 | AL8: el metro | AO8: surtidos niquel | AP8: 4600
F9: 100 | G9: =(G8/F9)+$AE$3 -> 227.12 | I9: 250 | J9: =J8/I9 -> 110 | L9: 500 Cajas Blancas Deslizantes D128 (16x4x2) - Modelos según tipo - D: Deslizantes estilo fosforeras - D128 (Base 16x4cm / Altura: 2cm) | M9: 500 | N9: 176437 | O9: =N9/M9 -> 352.874 | Q9: 1000 | R9: =R8/Q9 -> 1.888 | AO9: 50 | AP9: =AP8/AO9 -> 92 | AQ9: x gramo
A10: Chocolatinas con leche x 5 gr. - 011-62079 | B10: 900 | C10: 201997 | D10: =C10/B10 -> 224.44111 | T10: Mosquetón de Hierro 2 cm (mod. B) - ALMACEN DE ARMADO | U10: Mosqueton | V10: 16495 | Y10: Bolsas Zipper Con Cierre Hermético Stendy 5x7 Cm Zip Pack X 500 Unidades | MercadoLibre | Z10: Ziploc | AA10: 5500 | AI10: Cinta Trigal 10 mm x 10 metros - Comprar en CandyCraft | AJ10: Cinta trigo | AK10: 4956
E11: Papel Texturado Tarjeteria A4 250grs Opalina Mate Telado X20 | MercadoLibre | F11: Telada | G11: 7140 | H11: Cera de soja ASTRA bpf - Nuevas Luces | I11: Cera BPF | J11: 49300 | L11: 1000 Cajas Blancas Deslizantes D128 (16x4x2) - Modelos según tipo - D: Deslizantes estilo fosforeras - D128 (Base 16x4cm / Altura: 2cm) | M11: 1000 | N11: 310795 | O11: =N11/M11 -> 310.795 | P11: Hilo Dorado O Plateado Lurex Cola De Ratón Souvenir X100 Mts | MercadoLibre | Q11: Lurex | R11: 8700 | U11: 50 | V11: =V10/U11 -> 329.9 | Y11: 5*7 | Z11: 500 | AA11: =AA10/Z11 -> 11 | AJ11: 1000 | AK11: =AK10/AJ11 -> 4.956
A12: Chocolatinas con leche x 5 gr. - Pack de 10 cajas de 200 unidades - 082-62081 | B12: 2000 | C12: 411676 | D12: =C12/B12 -> 205.838 | F12: 20 | G12: =(G11/F12)+$AE$3 -> 407 | I12: 10000 | J12: =J11/I12 -> 4.93 | Q12: 10000 | R12: =R11/Q12 -> 0.87 | AO12: Surtido esmaltados | AP12: 7788
L13: 2000 Cajas Blancas Deslizantes D128 (16x4x2) - Modelos según tipo - D: Deslizantes estilo fosforeras - D128 (Base 16x4cm / Altura: 2cm) | M13: 2000 | N13: 539298 | O13: =N13/M13 -> 269.649 | T13: Bolsa De Polipropileno 4x25cm. Ideal Garrapiñadas X 200 U. | MercadoLibre | U13: Bolsa Tejido base | V13: 2759 | AO13: 20 | AP13: =AP12/AO13 -> 389.4 | AQ13: c/u
E14: Papel Foil Metalizado Textil Para Telas Y Toner 32x6 Film | Envío gratis | F14: Foil | G14: 7300 | H14: Ojalillo chico - Nuevas Luces | I14: Ojalillo | J14: 820 | P14: Borlas Flecos Hilos De Seda X 5 Unidades Varios Colores | MercadoLibre | Q14: Borlas 13cm | R14: 1739 | U14: 200 | V14: =V13/U14 -> 13.795
A15: Chocolatin Georgalos X 40 Unidades 8 Grms | B15: Georgalos | C15: 15648 | F15: 25 | G15: =G14/F15 -> 292 | I15: 50 | J15: =J14/I15 -> 16.4 | Q15: 5 | R15: =R14/Q15 -> 347.8
B16: 40 | C16: =C15/B16 -> 391.2
E17: Opalina Cartulina A4 125 Hojas 210 Grs Chambril Blanco Liso | MercadoLibre | F17: Opalina 210gr | G17: 8170 | H17: Pegamento para ojalillo en rollo x100 puntos - Nuevas Luces | I17: Pegamento Ojalillo | J17: 1100 | P17: Dijes Cruces Lisas De Madera Para Crucifijo Pack X 200 Pcs. | MercadoLibre | Q17: Cruz madera | R17: 19055
F18: 125 | G18: =G17/F18 -> 65.36 | I18: 100 | J18: =J17/I18 -> 11 | Q18: 200 | R18: =R17/Q18 -> 95.275
B19: zafiro | C19: 9565.1 | D19: =C19/B20 -> 191.302 | M19: Anvi | X19: =Y25*4 -> 1400
B20: 50 | E20: Opp Transparente A4 Vinilo Autoadhesivo X20u Papel P/ Laser | MercadoLibre | F20: Transp Laser | G20: 7605 | M20: 4 chocos | N20: 324 | Q20: Aerosol | R20: 4500 | X20: =Y27*6 -> 900 | AB20: =SUM(AA23:AA38) -> 693152
F21: 20 | G21: =G20/F21 -> 380.25 | H21: 24 Vaso Wiskie Tennessee Para Velas Cera X Mayor | MercadoLibre | I21: tennesse | J21: 30343 | Q21: 20 | R21: =R20/Q21 -> 225 | X21: =X19+X20 -> 2300
I22: 24 | J22: =J21/I22 -> 1264.2917 | M22: 5 chocos | N22: 303
B23: Etiquetas de chocos | E23: Papel Kraft A4 270gr Resma X50 Hojas Madera Misionero | MercadoLibre | F23: Kraft | G23: 7285 | Y23: 2000 | Z23: chocos | AA23: =C12 -> 411676 | AG23: hojas
B24: Fotografica | C24: =G6/28 -> 8.5685714 | F24: 50 | G24: =G23/F24 -> 145.7 | M24: 6 chocos | N24: 372 | AE24: 5ml | AG24: 15
I25: =G15+G6 -> 531.92 | Y25: 350 | Z25: cajitas 4 | AA25: =270*Y25 -> 94500 | AG25: 3
E26: Papel Autoadhesivo A4 Obra Mate 100 Hojas Blanco | MercadoLibre | F26: Obra autoadhesiva | G26: 14850 | M26: 8 chocos | N26: 372
B27: Foil | C27: =G15/28 -> 10.428571 | F27: 100 | G27: =G26/F27 -> 148.5 | H27: 1 Kg Cera Soja Apf Alto Punto Fusión Para Moldes. | Envío gratis | I27: CERA APF | J27: 13300 | Y27: 150 | Z27: cajitas de 6 | AA27: 70000 | AG27: 1256
I28: 1000 | J28: =J27/I28 -> 13.3
E29: Papel Ilustración 300 Gramos A4 P/ Tarjetas Resma 100 Hojas Blanco | MercadoLibre | F29: 300gr | G29: 13651 | Y29: 3 | Z29: Autodhesivas | AA29: =G5*3 -> 56976
B30: Laser | C30: =G9/28 -> 8.1114286 | F30: 100 | G30: =G29/F30 -> 136.51 | M30: Doble menta
Y31: 200 | Z31: Hojas teladas | AA31: 60000 | AB31: igual a 2000 mini recuerdos
E32: Carton Cartulina Triplex A4 300 Grs 100 Hojas Cajas Tapas | MercadoLibre | F32: Triplex 300gr A4 | G32: 4200 | L32: Pack de Cajas Blancas 8x8x10 cm - Modelo A32 | M32: Tennesse | N32: 4005
F33: 20 | G33: =G32/F33 -> 210 | M33: 10 | N33: =N32/M33 -> 400.5
B34: Tapa Fotografica | C34: =G6/8 -> 29.99
F35: Triplex 390gr | G35: 5400 | L35: Pack de Cajas Deslizantes 7x7x1 Blancas - MODELO D10 | M35: D10 | N35: 3650
B36: Foil P/Deluxe | C36: =G15/8 -> 36.5 | F36: 20 | G36: =G35/F36 -> 270 | I36: =G33/5 -> 42 | M36: 10 | N36: =N35/M36 -> 365
E38: Holofan Art-jet Adhesivo Noche Estrellada A4 20 Hojas | MercadoLibre | F38: Holofan | G38: 10506 | I38: =G6/5 -> 47.984 | M38: D10 | N38: 31207.5
F39: 20 | G39: =G38/F39 -> 525.3 | M39: 100 | N39: =N38/M39 -> 312.075
B41: Tapa Foil | C41: =G15/3.5 -> 83.428571 | E41: Papel Kraft A4 270gr Resma X50 Hojas Madera Misionero Marrón | MercadoLibre | F41: Kraft | G41: 7285 | I41: =I36+I38 -> 89.984 | L41: Pack de Cajas 6x6x8,5 Kraft - MODELO A30 | M41: A30 - 100cc | N41: 3700
F42: 50 | G42: =G41/F42 -> 145.7 | M42: 10 | N42: =N41/M42 -> 370
E44: Canvas Corteza De Pino 230g A4 50 Hojas Blanco | MercadoLibre | F44: Matelina | G44: 9996
A45: 15 | B45: Sugus confitados | C45: 16706 | F45: 50 | G45: =G44/F45 -> 199.92
A46: 25 | B46: 41.66 | C46: =C45/B46 -> 401.00816
B48: CORAZONITO | C48: 7000 | R48: OO.++WTTTBYHJ*-.>ZXV|
B49: 20 | C49: =C48/B49 -> 350

Sheet XV
P1: 0.1 | R1: 0.09
P2: 0.1 | R2: 0.076
P3: =P2+P1 -> 0.2 | R3: =R2+R1 -> 0.166
B4: Cintas con choco simples | C4: Choco | D4: Cinta comun | E4: Cinta Lurex | F4: Etiqueta | I4: Choco armado | L4: Costo total | M4: Costo real | N4: Ganancia | O4: Total | P4: MP | Q4: MP | R4: Ganan MP
C5: =Insumos!C6 -> 224 | D5: =Insumos!AK5*1 -> 96.76 | E5: =Insumos!AK8*1 -> 145 | F5: =Insumos!G6/28 -> 8.5685714 | I5: ='Coloniales S.C'!M7 -> 651.192 | L5: =SUM(D5:I5) -> 901.52057 | M5: =SUM(C5:H5) -> 474.32857 | N5: 200 | O5: =N5+M5 -> 674.32857 | P5: =ROUND(Q5/50,0)*50 -> 1300 | Q5: =(N5+L5)+((L5+N5)*($P$3)) -> 1321.8247 | R5: =P5-(P5*$R$3)-M5 -> 609.87143
P8: Transf | R8: G. Transf
P9: =P5-(P5*$P$1) -> 1170 | R9: =(P9-(P9*$R$2))-M5 -> 606.75143
P12: 0.1 | R12: 0.08
P13: 0.09 | R13: 0.06
P14: =P13+P12 -> 0.19 | R14: =R13+R12 -> 0.14
B15: Cintas con choco + dije letra | C15: Choco | D15: Cinta comun | E15: Cinta Lurex | F15: Etiqueta | G15: dije letra | H15: Strases final | I15: Choco armado | L15: Costo total | M15: Costo real | N15: Ganancia | O15: Total | P15: MP | Q15: MP | R15: Ganan MP
C16: =C5 -> 224 | D16: =D5 -> 96.76 | E16: =E5 -> 145 | F16: =F5 -> 8.5685714 | G16: =Insumos!AP5 -> 76.666667 | H16: 75 | I16: =$I$5 -> 651.192 | L16: =SUM(D16:I16) -> 1053.1872 | M16: =SUM(C16:H16) -> 625.99524 | N16: 250 | O16: =N16+M16 -> 875.99524 | P16: =ROUND(Q16/50,0)*50 -> 1550 | Q16: =(N16+L16)+((L16+N16)*($P$3)) -> 1563.8247 | R16: =P16-(P16*$R$3)-M16 -> 666.70476
P19: Transf | R19: G. Transf
P20: =P16-(P16*$P$1) -> 1395 | R20: =(P20-(P20*$R$2))-M16 -> 662.98476
P23: 0.1 | R23: 0.08
P24: 0.09 | R24: 0.06
P25: =P24+P23 -> 0.19 | R25: =R24+R23 -> 0.14
B26: Cintas con choco Dije surtido | C26: Choco | D26: Cinta comun | E26: Cinta Lurex | F26: Etiqueta | G26: dije surtidos | I26: Choco armado | L26: Costo total | M26: Costo real | N26: Ganancia | O26: Total | P26: MP | Q26: MP | R26: Ganan MP
C27: =C16 -> 224 | D27: =D16 -> 96.76 | E27: =E16 -> 145 | F27: =F16 -> 8.5685714 | G27: =Insumos!AP9*2 -> 184 | I27: =$I$5 -> 651.192 | L27: =SUM(D27:I27) -> 1085.5206 | M27: =SUM(C27:H27) -> 658.32857 | N27: 250 | O27: =N27+M27 -> 908.32857 | P27: =ROUND(Q27/50,0)*50 -> 1600 | Q27: =(N27+L27)+((L27+N27)*($P$3)) -> 1602.6247 | R27: =P27-(P27*$R$3)-M27 -> 676.07143
P30: Transf | R30: G. Transf
P31: =P27-(P27*$P$1) -> 1440 | R31: =(P31-(P31*$R$2))-M27 -> 672.23143
P34: 0.1 | R34: 0.08
P35: 0.09 | R35: 0.06
P36: =P35+P34 -> 0.19 | R36: =R35+R34 -> 0.14
B37: Cintas con choco + dije esmaltado | C37: Choco | D37: Cinta comun | E37: Cinta Lurex | F37: Etiqueta | G37: Dije esmaltado | I37: Choco armado | L37: Costo total | M37: Costo real | N37: Ganancia | O37: Total | P37: MP | Q37: MP | R37: Ganan MP
C38: =C27 -> 224 | D38: =D27 -> 96.76 | E38: =E27 -> 145 | F38: =F27 -> 8.5685714 | G38: =Insumos!AP13 -> 389.4 | I38: =$I$5 -> 651.192 | L38: =SUM(D38:I38) -> 1290.9206 | M38: =SUM(C38:H38) -> 863.72857 | N38: 250 | O38: =N38+M38 -> 1113.7286 | P38: =ROUND(Q38/50,0)*50 -> 1850 | Q38: =(N38+L38)+((L38+N38)*($P$3)) -> 1849.1047 | R38: =P38-(P38*$R$3)-M38 -> 679.17143
P41: Transf | R41: G. Transf
P42: =P38-(P38*$P$1) -> 1665 | R42: =(P42-(P42*$R$2))-M38 -> 674.73143
P45: 0.1 | R45: 0.08
P46: 0.09 | R46: 0.06
P47: =P46+P45 -> 0.19 | R47: =R46+R45 -> 0.14
B48: Cintas con choco Holográfico | C48: Choco | D48: Cinta comun | E48: Cinta Lurex | F48: Etiqueta | I48: Choco armado | L48: Costo total | M48: Costo real | N48: Ganancia | O48: Total | P48: MP | Q48: MP | R48: Ganan MP
C49: =C38 -> 224 | D49: =D38 -> 96.76 | E49: =E38 -> 145 | F49: =Insumos!G39/28 -> 18.760714 | I49: =C49+F49+250 -> 492.76071 | L49: =SUM(D49:I49) -> 753.28143 | M49: =SUM(C49:H49) -> 484.52071 | N49: 280 | O49: =N49+M49 -> 764.52071 | P49: =ROUND(Q49/50,0)*50 -> 1250 | Q49: =(N49+L49)+((L49+N49)*($P$3)) -> 1239.9377 | R49: =P49-(P49*$R$3)-M49 -> 557.97929
P52: Transf | R52: G. Transf
P53: =P49-(P49*$P$1) -> 1125 | R53: =(P53-(P53*$R$2))-M49 -> 554.97929
P56: 0.1 | R56: 0.08
P57: 0.09 | R57: 0.06
P58: =P57+P56 -> 0.19 | R58: =R57+R56 -> 0.14
B59: Cintas con choco Holográfico + Dije letra | C59: Choco | D59: Cinta comun | E59: Cinta Lurex | F59: Etiqueta | G59: Dije Letra | I59: Choco armado | L59: Costo total | M59: Costo real | N59: Ganancia | O59: Total | P59: MP | Q59: MP | R59: Ganan MP
C60: =C49 -> 224 | D60: =D49 -> 96.76 | E60: =E49 -> 145 | F60: =F49 -> 18.760714 | G60: =G16 -> 76.666667 | I60: =C60+F60+250 -> 492.76071 | L60: =SUM(D60:I60) -> 829.9481 | M60: =SUM(C60:H60) -> 561.18738 | N60: 300 | O60: =N60+M60 -> 861.18738 | P60: =ROUND(Q60/50,0)*50 -> 1350 | Q60: =(N60+L60)+((L60+N60)*($P$3)) -> 1355.9377 | R60: =P60-(P60*$R$3)-M60 -> 564.71262
P63: Transf | R63: G. Transf
P64: =P60-(P60*$P$1) -> 1215 | R64: =(P64-(P64*$R$2))-M60 -> 561.47262
P67: 0.1 | R67: 0.08
P68: 0.09 | R68: 0.06
P69: =P68+P67 -> 0.19 | R69: =R68+R67 -> 0.14
B70: Cintas con choco Holográfico + Dije surtido | C70: Choco | D70: Cinta comun | E70: Cinta Lurex | F70: Etiqueta | G70: dije surtido | I70: Choco armado | L70: Costo total | M70: Costo real | N70: Ganancia | O70: Total | P70: MP | Q70: MP | R70: Ganan MP
C71: =C60 -> 224 | D71: =D60 -> 96.76 | E71: =E60 -> 145 | F71: =F60 -> 18.760714 | G71: =G27 -> 184 | I71: =C71+F71+250 -> 492.76071 | L71: =SUM(D71:I71) -> 937.28143 | M71: =SUM(C71:H71) -> 668.52071 | N71: 300 | O71: =N71+M71 -> 968.52071 | P71: =ROUND(Q71/50,0)*50 -> 1500 | Q71: =(N71+L71)+((L71+N71)*($P$3)) -> 1484.7377 | R71: =P71-(P71*$R$3)-M71 -> 582.47929
P74: Transf | R74: G. Transf
P75: =P71-(P71*$P$1) -> 1350 | R75: =(P75-(P75*$R$2))-M71 -> 578.87929
P78: 0.1 | R78: 0.08
P79: 0.09 | R79: 0.06
P80: =P79+P78 -> 0.19 | R80: =R79+R78 -> 0.14
B81: Cintas con choco Holográfico + Dije esmaltado | C81: Choco | D81: Cinta comun | E81: Cinta Lurex | F81: Etiqueta | G81: Dije esmaltado | I81: Choco armado | L81: Costo total | M81: Costo real | N81: Ganancia | O81: Total | P81: MP | Q81: MP | R81: Ganan MP
C82: =C71 -> 224 | D82: =D71 -> 96.76 | E82: =E71 -> 145 | F82: =F71 -> 18.760714 | G82: =G38 -> 389.4 | I82: =C82+F82+250 -> 492.76071 | L82: =SUM(D82:I82) -> 1142.6814 | M82: =SUM(C82:H82) -> 873.92071 | N82: 300 | O82: =N82+M82 -> 1173.9207 | P82: =ROUND(Q82/50,0)*50 -> 1750 | Q82: =(N82+L82)+((L82+N82)*($P$3)) -> 1731.2177 | R82: =P82-(P82*$R$3)-M82 -> 585.57929
O85: 0.1 | P85: Transf | R85: G. Transf
P86: =P82-(P82*$P$1) -> 1575 | R86: =(P86-(P86*$R$2))-M82 -> 581.37929

Sheet Nacimientos
R1: Descontar
P2: Aumento | R2: 0.0925
P3: 0.1
P4: 0.1 | R4: 0.0761 | S4: =P7*R4 -> 818.836
P5: =P3+P4 -> 0.2 | R5: =R3+R4+R2 -> 0.1686 | U5: Descuento | V5: Descuento | W5: Descuento | X5: Descuento | Y5: Descuento | Z5: Descuento
B6: Sobre corazones | C6: Sugus | D6: Tarjeta | E6: Raso | F6: Impresión | G6: Bolsa | K6: Costo 10 U. | M6: Ganancia | N6: Total | P6: MP | Q6: MP | R6: Ganan MP | U6: 0 | V6: 0 | W6: 0.05 | X6: 0.05 | Y6: 0.1 | Z6: 0.15
C7: =Insumos!C49 -> 350 | D7: =Insumos!G45/3 -> 66.64 | E7: =Insumos!AK5/2 -> 48.38 | F7: 20 | G7: =Insumos!AA11 -> 11 | K7: =SUM(C7:J7)*10 -> 4960.2 | M7: =400*10 -> 4000 | N7: =$M$7+K7 -> 8960.2 | P7: =ROUNDUP(Q7, -1) -> 10760 | Q7: =N7+(N7*P5) -> 10752.24 | R7: =P7-(P7*R5)-L7 -> 8945.864 | U7: 50 | V7: 100 | W7: 200 | X7: 500 | Y7: 1000 | Z7: 2000
U8: Costo total
B9: 100 | K9: =C9+$D$7+$F$7 -> 86.64 | N9: =$M$7+K9 -> 4086.64 | U9: =K7*U7 -> 248010 | V9: =K9*V7 -> 8664 | W9: =K11*W7 -> 17328 | X9: =K13*X7 -> 43320 | Y9: =K15*Y7 -> 86640 | Z9: =K17*Z7 -> 173280
U10: Mercado Pago
B11: 200 | K11: =C11+$D$7+$F$7 -> 86.64 | N11: =$M$7+K11 -> 4086.64 | P11: descuento | R11: IIBB | U11: =($P7*U7)-(($P7*U7)*U6) -> 538000 | V11: =($P7*V7)-(($P7*V7)*V6) -> 1076000 | W11: =($P7*W7)-(($P7*W7)*W6) -> 2044400 | X11: =($P7*X7)-(($P7*X7)*X6) -> 5111000 | Y11: =($P7*Y7)-(($P7*Y7)*Y6) -> 9684000 | Z11: =($P7*Z7)-(($P7*Z7)*Z6) -> 18292000
P12: 0.1 | R12: 0.06 | U12: =U11/U7 -> 10760 | V12: =V11/V7 -> 10760 | W12: =W11/W7 -> 10222 | X12: =X11/X7 -> 10222 | Y12: =Y11/Y7 -> 9684 | Z12: =Z11/Z7 -> 9146
B13: 500 | K13: =C13+$D$7+$F$7 -> 86.64 | N13: =$M$7+K13 -> 4086.64 | P13: Transf | R13: G. Transf | U13: Ganancia MP
P14: =P7-(P7*P12) -> 9684 | R14: =(P14-(P14*R12))-K7 -> 4142.76 | U14: =(U11-U9)-(U11*$R$5) -> 199283.2 | V14: =(V11-V9)-(V11*$R$5) -> 885922.4 | W14: =(W11-W9)-(W11*$R$5) -> 1682386.2 | X14: =(X11-X9)-(X11*$R$5) -> 4205965.4 | Y14: =(Y11-Y9)-(Y11*$R$5) -> 7964637.6 | Z14: =(Z11-Z9)-(Z11*$R$5) -> 15034689
B15: 1000 | K15: =C15+$D$7+$F$7 -> 86.64 | N15: =$M$7+K15 -> 4086.64 | U15: =U14/U7 -> 3985.664 | V15: =V14/V7 -> 8859.224 | W15: =W14/W7 -> 8411.9308 | X15: =X14/X7 -> 8411.9308 | Y15: =Y14/Y7 -> 7964.6376 | Z15: =Z14/Z7 -> 7517.3444
U16: Transferencia
B17: 2000 | K17: =C17+$D$7+$F$7 -> 86.64 | N17: =$M$7+K17 -> 4086.64 | U17: =U11-(U11*U18) -> 484200 | V17: =V11-(V11*V18) -> 968400 | W17: =W11-(W11*W18) -> 1839960 | X17: =X11-(X11*X18) -> 4599900 | Y17: =Y11-(Y11*Y18) -> 8715600 | Z17: =Z11-(Z11*Z18) -> 16462800
U18: =$P$12 -> 0.1 | V18: =$P$12 -> 0.1 | W18: =$P$12 -> 0.1 | X18: =$P$12 -> 0.1 | Y18: =$P$12 -> 0.1 | Z18: =$P$12 -> 0.1
U19: =U17/U7 -> 9684 | V19: =V17/V7 -> 9684 | W19: =W17/W7 -> 9199.8 | X19: =X17/X7 -> 9199.8 | Y19: =Y17/Y7 -> 8715.6 | Z19: =Z17/Z7 -> 8231.4
U20: Ganancia transferencia
U21: =U17-(U17*$R$12)-U9 -> 207138 | V21: =V17-(V17*$R$213)-V9 -> 959736 | W21: =W17-(W17*$R$213)-W9 -> 1822632 | X21: =X17-(X17*$R$213)-X9 -> 4556580 | Y21: =Y17-(Y17*$R$213)-Y9 -> 8628960 | Z21: =Z17-(Z17*$R$213)-Z9 -> 16289520
U22: =U21/U7 -> 4142.76 | V22: =V21/V7 -> 9597.36 | W22: =W21/W7 -> 9113.16 | X22: =X21/X7 -> 9113.16 | Y22: =Y21/Y7 -> 8628.96 | Z22: =Z21/Z7 -> 8144.76

Sheet Globos
A1: G
B4: Globos 18" | C4: 4422
B5: 20 | C5: =C4/B5 -> 221.1
B7: Globo Corazon 9"
B10: Globo Corazon 12"
B13: Globo Corazon 18"
